<?xml version="1.0" encoding="UTF-8" standalone="yes"?>
<trpDocMetadata>
    <docId>1428149</docId>
    <title>A060b Notizen</title>
    <uploadTimestamp>1683710574919</uploadTimestamp>
    <uploader>martin.anton.mueller@oeaw.ac.at</uploader>
    <uploaderId>40391</uploaderId>
    <nrOfPages>23</nrOfPages>
    <pageId>55386323</pageId>
    <url>https://files.transkribus.eu/Get?fileType=view&amp;id=NMZPAAIPHHDIFSMIIYIILXJH</url>
    <thumbUrl>https://files.transkribus.eu/Get?fileType=thumb&amp;id=NMZPAAIPHHDIFSMIIYIILXJH</thumbUrl>
    <status>0</status>
    <fimgStoreColl>TrpDoc_DEA_1428149</fimgStoreColl>
    <origDocId>0</origDocId>
    <collectionList>
        <colList>
            <colId>200901</colId>
            <colName>schnitzler-mikrofilme</colName>
            <description>created by martin.anton.mueller@oeaw.ac.at</description>
            <crowdsourcing>false</crowdsourcing>
            <elearning>false</elearning>
            <nrOfDocuments>0</nrOfDocuments>
        </colList>
    </collectionList>
    <mainColId>200901</mainColId>
</trpDocMetadata>
