<?xml version="1.0" encoding="UTF-8" standalone="yes"?>
<ns3:mets xmlns:ns2="http://www.w3.org/1999/xlink" xmlns:ns3="http://www.loc.gov/METS/" xmlns:xsi="http://www.w3.org/2001/XMLSchema-instance" OBJID="1416451" LABEL="B0055 Kraus, Karl" PROFILE="TRP_V1" xsi:schemaLocation="http://www.loc.gov/METS/ http://www.loc.gov/standards/mets/mets.xsd">
    <ns3:metsHdr CREATEDATE="2024-03-30T21:25:44.518+01:00" LASTMODDATE="2024-03-30T21:25:44.518+01:00" RECORDSTATUS="SUBMITTED">
        <ns3:agent ROLE="CREATOR" TYPE="ORGANIZATION">
            <ns3:name>UIBK</ns3:name>
            <ns3:note>This METS file was generated by Transkribus</ns3:note>
        </ns3:agent>
    </ns3:metsHdr>
    <ns3:amdSec ID="SOURCE">
        <ns3:sourceMD ID="MD_ORIG">
            <ns3:mdWrap ID="TRP_DOC_MD" MDTYPE="OTHER">
                <ns3:xmlData>
                    <trpDocMetadata>
                        <docId>1416451</docId>
                        <title>B0055 Kraus, Karl</title>
                        <uploadTimestamp>1682971354903</uploadTimestamp>
                        <uploader>martin.anton.mueller@oeaw.ac.at</uploader>
                        <uploaderId>40391</uploaderId>
                        <nrOfPages>24</nrOfPages>
                        <pageId>54947330</pageId>
                        <url>https://files.transkribus.eu/Get?fileType=view&amp;id=SARXCMWIZZNGLAPOXBWAMABK</url>
                        <thumbUrl>https://files.transkribus.eu/Get?fileType=thumb&amp;id=SARXCMWIZZNGLAPOXBWAMABK</thumbUrl>
                        <status>0</status>
                        <fimgStoreColl>TrpDoc_DEA_1416451</fimgStoreColl>
                        <localFolder>/mnt/transkribus/export/TRP_EXPORT_3710928009986880300/1416451/B0055_Kraus,_Karl</localFolder>
                        <origDocId>0</origDocId>
                        <collectionList>
                            <colList>
<colId>200901</colId>
<colName>schnitzler-mikrofilme</colName>
<description>created by martin.anton.mueller@oeaw.ac.at</description>
<crowdsourcing>false</crowdsourcing>
<elearning>false</elearning>
<nrOfDocuments>0</nrOfDocuments>
                            </colList>
                        </collectionList>
                        <mainColId>200901</mainColId>
                    </trpDocMetadata>
                </ns3:xmlData>
            </ns3:mdWrap>
        </ns3:sourceMD>
    </ns3:amdSec>
    <ns3:fileSec>
        <ns3:fileGrp ID="MASTER">
            <ns3:fileGrp ID="IMG">
                <ns3:file ID="IMG_1" SEQ="1" MIMETYPE="image/jpeg" CREATED="2023-05-01T22:02:35.175+02:00" CHECKSUM="ce803710a9b3392937117345f46e29c5" CHECKSUMTYPE="MD5">
                    <ns3:FLocat LOCTYPE="OTHER" OTHERLOCTYPE="FILE" ns2:type="simple" ns2:href="1416451_0001.jpg"/>
                </ns3:file>
                <ns3:file ID="IMG_2" SEQ="2" MIMETYPE="image/jpeg" CREATED="2023-05-01T22:02:35.807+02:00" CHECKSUM="c70d881d1afc2c47cf1040f1f96308f5" CHECKSUMTYPE="MD5">
                    <ns3:FLocat LOCTYPE="OTHER" OTHERLOCTYPE="FILE" ns2:type="simple" ns2:href="1416451_0002.jpg"/>
                </ns3:file>
                <ns3:file ID="IMG_3" SEQ="3" MIMETYPE="image/jpeg" CREATED="2023-05-01T22:02:36.438+02:00" CHECKSUM="0d8a40366b3dcc81ce458b95c7a707c0" CHECKSUMTYPE="MD5">
                    <ns3:FLocat LOCTYPE="OTHER" OTHERLOCTYPE="FILE" ns2:type="simple" ns2:href="1416451_0003.jpg"/>
                </ns3:file>
                <ns3:file ID="IMG_4" SEQ="4" MIMETYPE="image/jpeg" CREATED="2023-05-01T22:02:37.685+02:00" CHECKSUM="615d8bf900a9ad7ba8a85ec23f1a7521" CHECKSUMTYPE="MD5">
                    <ns3:FLocat LOCTYPE="OTHER" OTHERLOCTYPE="FILE" ns2:type="simple" ns2:href="1416451_0004.jpg"/>
                </ns3:file>
                <ns3:file ID="IMG_5" SEQ="5" MIMETYPE="image/jpeg" CREATED="2023-05-01T22:02:38.742+02:00" CHECKSUM="34365d53007744a025b9655d10c80799" CHECKSUMTYPE="MD5">
                    <ns3:FLocat LOCTYPE="OTHER" OTHERLOCTYPE="FILE" ns2:type="simple" ns2:href="1416451_0005.jpg"/>
                </ns3:file>
                <ns3:file ID="IMG_6" SEQ="6" MIMETYPE="image/jpeg" CREATED="2023-05-01T22:02:40.404+02:00" CHECKSUM="8e755c50bc77fea0949b4b2cfd451d56" CHECKSUMTYPE="MD5">
                    <ns3:FLocat LOCTYPE="OTHER" OTHERLOCTYPE="FILE" ns2:type="simple" ns2:href="1416451_0006.jpg"/>
                </ns3:file>
                <ns3:file ID="IMG_7" SEQ="7" MIMETYPE="image/jpeg" CREATED="2023-05-01T22:02:41.300+02:00" CHECKSUM="85c7f1adeba307fc64b2045cd8fe56f5" CHECKSUMTYPE="MD5">
                    <ns3:FLocat LOCTYPE="OTHER" OTHERLOCTYPE="FILE" ns2:type="simple" ns2:href="1416451_0007.jpg"/>
                </ns3:file>
                <ns3:file ID="IMG_8" SEQ="8" MIMETYPE="image/jpeg" CREATED="2023-05-01T22:02:42.146+02:00" CHECKSUM="c9559908eed29d8f9b7edc68bfddf862" CHECKSUMTYPE="MD5">
                    <ns3:FLocat LOCTYPE="OTHER" OTHERLOCTYPE="FILE" ns2:type="simple" ns2:href="1416451_0008.jpg"/>
                </ns3:file>
                <ns3:file ID="IMG_9" SEQ="9" MIMETYPE="image/jpeg" CREATED="2023-05-01T22:02:42.912+02:00" CHECKSUM="7390da5f114ca2cefb5e9136208dc562" CHECKSUMTYPE="MD5">
                    <ns3:FLocat LOCTYPE="OTHER" OTHERLOCTYPE="FILE" ns2:type="simple" ns2:href="1416451_0009.jpg"/>
                </ns3:file>
                <ns3:file ID="IMG_10" SEQ="10" MIMETYPE="image/jpeg" CREATED="2023-05-01T22:02:43.665+02:00" CHECKSUM="7df2e0abee41c575a46bd1ce22802ed0" CHECKSUMTYPE="MD5">
                    <ns3:FLocat LOCTYPE="OTHER" OTHERLOCTYPE="FILE" ns2:type="simple" ns2:href="1416451_0010.jpg"/>
                </ns3:file>
                <ns3:file ID="IMG_11" SEQ="11" MIMETYPE="image/jpeg" CREATED="2023-05-01T22:02:44.353+02:00" CHECKSUM="9028c7e894fd7506d4f42dc14bf6630a" CHECKSUMTYPE="MD5">
                    <ns3:FLocat LOCTYPE="OTHER" OTHERLOCTYPE="FILE" ns2:type="simple" ns2:href="1416451_0011.jpg"/>
                </ns3:file>
                <ns3:file ID="IMG_12" SEQ="12" MIMETYPE="image/jpeg" CREATED="2023-05-01T22:02:45.092+02:00" CHECKSUM="a0da38b538bafa44d84f68b2e645edde" CHECKSUMTYPE="MD5">
                    <ns3:FLocat LOCTYPE="OTHER" OTHERLOCTYPE="FILE" ns2:type="simple" ns2:href="1416451_0012.jpg"/>
                </ns3:file>
                <ns3:file ID="IMG_13" SEQ="13" MIMETYPE="image/jpeg" CREATED="2023-05-01T22:02:45.711+02:00" CHECKSUM="0f33abf9ec30d19e5e3e748ca3549644" CHECKSUMTYPE="MD5">
                    <ns3:FLocat LOCTYPE="OTHER" OTHERLOCTYPE="FILE" ns2:type="simple" ns2:href="1416451_0013.jpg"/>
                </ns3:file>
                <ns3:file ID="IMG_14" SEQ="14" MIMETYPE="image/jpeg" CREATED="2023-05-01T22:02:46.470+02:00" CHECKSUM="180fca11d15beb651c07b574844b5b89" CHECKSUMTYPE="MD5">
                    <ns3:FLocat LOCTYPE="OTHER" OTHERLOCTYPE="FILE" ns2:type="simple" ns2:href="1416451_0014.jpg"/>
                </ns3:file>
                <ns3:file ID="IMG_15" SEQ="15" MIMETYPE="image/jpeg" CREATED="2023-05-01T22:02:47.191+02:00" CHECKSUM="b7841c83775e3d007e80464e244c10cb" CHECKSUMTYPE="MD5">
                    <ns3:FLocat LOCTYPE="OTHER" OTHERLOCTYPE="FILE" ns2:type="simple" ns2:href="1416451_0015.jpg"/>
                </ns3:file>
                <ns3:file ID="IMG_16" SEQ="16" MIMETYPE="image/jpeg" CREATED="2023-05-01T22:02:47.844+02:00" CHECKSUM="52914398a4a2ef2e335cc8d62cccd191" CHECKSUMTYPE="MD5">
                    <ns3:FLocat LOCTYPE="OTHER" OTHERLOCTYPE="FILE" ns2:type="simple" ns2:href="1416451_0016.jpg"/>
                </ns3:file>
                <ns3:file ID="IMG_17" SEQ="17" MIMETYPE="image/jpeg" CREATED="2023-05-01T22:02:50.353+02:00" CHECKSUM="d9d87d76463c1c957466c71a04c351e8" CHECKSUMTYPE="MD5">
                    <ns3:FLocat LOCTYPE="OTHER" OTHERLOCTYPE="FILE" ns2:type="simple" ns2:href="1416451_0017.jpg"/>
                </ns3:file>
                <ns3:file ID="IMG_18" SEQ="18" MIMETYPE="image/jpeg" CREATED="2023-05-01T22:02:51.073+02:00" CHECKSUM="c0b5d18d0a017281c002012b43e90278" CHECKSUMTYPE="MD5">
                    <ns3:FLocat LOCTYPE="OTHER" OTHERLOCTYPE="FILE" ns2:type="simple" ns2:href="1416451_0018.jpg"/>
                </ns3:file>
                <ns3:file ID="IMG_19" SEQ="19" MIMETYPE="image/jpeg" CREATED="2023-05-01T22:02:51.749+02:00" CHECKSUM="9589f6dea9a4f51f409d336e34f38cec" CHECKSUMTYPE="MD5">
                    <ns3:FLocat LOCTYPE="OTHER" OTHERLOCTYPE="FILE" ns2:type="simple" ns2:href="1416451_0019.jpg"/>
                </ns3:file>
                <ns3:file ID="IMG_20" SEQ="20" MIMETYPE="image/jpeg" CREATED="2023-05-01T22:02:52.778+02:00" CHECKSUM="33c6a64c63e747d93d74699aa03b5c5a" CHECKSUMTYPE="MD5">
                    <ns3:FLocat LOCTYPE="OTHER" OTHERLOCTYPE="FILE" ns2:type="simple" ns2:href="1416451_0020.jpg"/>
                </ns3:file>
                <ns3:file ID="IMG_21" SEQ="21" MIMETYPE="image/jpeg" CREATED="2023-05-01T22:02:53.483+02:00" CHECKSUM="116bc192a7fb7b581f58cf862e6766b9" CHECKSUMTYPE="MD5">
                    <ns3:FLocat LOCTYPE="OTHER" OTHERLOCTYPE="FILE" ns2:type="simple" ns2:href="1416451_0021.jpg"/>
                </ns3:file>
                <ns3:file ID="IMG_22" SEQ="22" MIMETYPE="image/jpeg" CREATED="2023-05-01T22:02:54.145+02:00" CHECKSUM="50522a7b5669e2e06d67ae7855fb22ce" CHECKSUMTYPE="MD5">
                    <ns3:FLocat LOCTYPE="OTHER" OTHERLOCTYPE="FILE" ns2:type="simple" ns2:href="1416451_0022.jpg"/>
                </ns3:file>
                <ns3:file ID="IMG_23" SEQ="23" MIMETYPE="image/jpeg" CREATED="2023-05-01T22:02:54.808+02:00" CHECKSUM="33d7df5b542a97b10288eecb34b0218e" CHECKSUMTYPE="MD5">
                    <ns3:FLocat LOCTYPE="OTHER" OTHERLOCTYPE="FILE" ns2:type="simple" ns2:href="1416451_0023.jpg"/>
                </ns3:file>
                <ns3:file ID="IMG_24" SEQ="24" MIMETYPE="image/jpeg" CREATED="2023-05-01T22:02:56.300+02:00" CHECKSUM="6f9311e88588b0471c374c857a351b65" CHECKSUMTYPE="MD5">
                    <ns3:FLocat LOCTYPE="OTHER" OTHERLOCTYPE="FILE" ns2:type="simple" ns2:href="1416451_0024.jpg"/>
                </ns3:file>
            </ns3:fileGrp>
            <ns3:fileGrp ID="PAGEXML">
                <ns3:file ID="PAGEXML_1" SEQ="1" MIMETYPE="application/xml" CREATED="2024-03-30T21:25:26.919+01:00" CHECKSUM="1d73252c159528c03b9ca0f20fb6c21c" CHECKSUMTYPE="MD5">
                    <ns3:FLocat LOCTYPE="OTHER" OTHERLOCTYPE="FILE" ns2:type="simple" ns2:href="page/1416451_0001.xml"/>
                </ns3:file>
                <ns3:file ID="PAGEXML_2" SEQ="2" MIMETYPE="application/xml" CREATED="2024-03-30T21:25:27.635+01:00" CHECKSUM="f1e36de704d832067c8e0870b3d7f09b" CHECKSUMTYPE="MD5">
                    <ns3:FLocat LOCTYPE="OTHER" OTHERLOCTYPE="FILE" ns2:type="simple" ns2:href="page/1416451_0002.xml"/>
                </ns3:file>
                <ns3:file ID="PAGEXML_3" SEQ="3" MIMETYPE="application/xml" CREATED="2024-03-30T21:25:28.399+01:00" CHECKSUM="5d99ba160a9cb0942be3c3cdaea8ec52" CHECKSUMTYPE="MD5">
                    <ns3:FLocat LOCTYPE="OTHER" OTHERLOCTYPE="FILE" ns2:type="simple" ns2:href="page/1416451_0003.xml"/>
                </ns3:file>
                <ns3:file ID="PAGEXML_4" SEQ="4" MIMETYPE="application/xml" CREATED="2024-03-30T21:25:29.107+01:00" CHECKSUM="53df92447f8a17adbc62e79f86a3577f" CHECKSUMTYPE="MD5">
                    <ns3:FLocat LOCTYPE="OTHER" OTHERLOCTYPE="FILE" ns2:type="simple" ns2:href="page/1416451_0004.xml"/>
                </ns3:file>
                <ns3:file ID="PAGEXML_5" SEQ="5" MIMETYPE="application/xml" CREATED="2024-03-30T21:25:29.839+01:00" CHECKSUM="8ff7628588d36046069fe682f8f89050" CHECKSUMTYPE="MD5">
                    <ns3:FLocat LOCTYPE="OTHER" OTHERLOCTYPE="FILE" ns2:type="simple" ns2:href="page/1416451_0005.xml"/>
                </ns3:file>
                <ns3:file ID="PAGEXML_6" SEQ="6" MIMETYPE="application/xml" CREATED="2024-03-30T21:25:30.631+01:00" CHECKSUM="98196453de4bbb7a9616a5ff56a07833" CHECKSUMTYPE="MD5">
                    <ns3:FLocat LOCTYPE="OTHER" OTHERLOCTYPE="FILE" ns2:type="simple" ns2:href="page/1416451_0006.xml"/>
                </ns3:file>
                <ns3:file ID="PAGEXML_7" SEQ="7" MIMETYPE="application/xml" CREATED="2024-03-30T21:25:31.427+01:00" CHECKSUM="42704fd2cd8690af5bb7fc420263c55a" CHECKSUMTYPE="MD5">
                    <ns3:FLocat LOCTYPE="OTHER" OTHERLOCTYPE="FILE" ns2:type="simple" ns2:href="page/1416451_0007.xml"/>
                </ns3:file>
                <ns3:file ID="PAGEXML_8" SEQ="8" MIMETYPE="application/xml" CREATED="2024-03-30T21:25:32.171+01:00" CHECKSUM="6419badefe9045e6d804ac25e0e56046" CHECKSUMTYPE="MD5">
                    <ns3:FLocat LOCTYPE="OTHER" OTHERLOCTYPE="FILE" ns2:type="simple" ns2:href="page/1416451_0008.xml"/>
                </ns3:file>
                <ns3:file ID="PAGEXML_9" SEQ="9" MIMETYPE="application/xml" CREATED="2024-03-30T21:25:32.971+01:00" CHECKSUM="576c43646cb0c74a0c0168dda9d35020" CHECKSUMTYPE="MD5">
                    <ns3:FLocat LOCTYPE="OTHER" OTHERLOCTYPE="FILE" ns2:type="simple" ns2:href="page/1416451_0009.xml"/>
                </ns3:file>
                <ns3:file ID="PAGEXML_10" SEQ="10" MIMETYPE="application/xml" CREATED="2024-03-30T21:25:33.715+01:00" CHECKSUM="a5f53e2435a8a7dc7e8cdbedf04ffc9a" CHECKSUMTYPE="MD5">
                    <ns3:FLocat LOCTYPE="OTHER" OTHERLOCTYPE="FILE" ns2:type="simple" ns2:href="page/1416451_0010.xml"/>
                </ns3:file>
                <ns3:file ID="PAGEXML_11" SEQ="11" MIMETYPE="application/xml" CREATED="2024-03-30T21:25:34.447+01:00" CHECKSUM="b35fe1d10c2b67f71256bd058eb00e47" CHECKSUMTYPE="MD5">
                    <ns3:FLocat LOCTYPE="OTHER" OTHERLOCTYPE="FILE" ns2:type="simple" ns2:href="page/1416451_0011.xml"/>
                </ns3:file>
                <ns3:file ID="PAGEXML_12" SEQ="12" MIMETYPE="application/xml" CREATED="2024-03-30T21:25:35.183+01:00" CHECKSUM="8c6924a699d56b15dd85622e9c3dd2d4" CHECKSUMTYPE="MD5">
                    <ns3:FLocat LOCTYPE="OTHER" OTHERLOCTYPE="FILE" ns2:type="simple" ns2:href="page/1416451_0012.xml"/>
                </ns3:file>
                <ns3:file ID="PAGEXML_13" SEQ="13" MIMETYPE="application/xml" CREATED="2024-03-30T21:25:36.103+01:00" CHECKSUM="e625869f04712a3c1491d7d4a0922ce3" CHECKSUMTYPE="MD5">
                    <ns3:FLocat LOCTYPE="OTHER" OTHERLOCTYPE="FILE" ns2:type="simple" ns2:href="page/1416451_0013.xml"/>
                </ns3:file>
                <ns3:file ID="PAGEXML_14" SEQ="14" MIMETYPE="application/xml" CREATED="2024-03-30T21:25:36.831+01:00" CHECKSUM="61dcbab8acc55c5278b97f4a24999e0e" CHECKSUMTYPE="MD5">
                    <ns3:FLocat LOCTYPE="OTHER" OTHERLOCTYPE="FILE" ns2:type="simple" ns2:href="page/1416451_0014.xml"/>
                </ns3:file>
                <ns3:file ID="PAGEXML_15" SEQ="15" MIMETYPE="application/xml" CREATED="2024-03-30T21:25:37.615+01:00" CHECKSUM="99248e0cc40ba46fa7694ff924ffb10a" CHECKSUMTYPE="MD5">
                    <ns3:FLocat LOCTYPE="OTHER" OTHERLOCTYPE="FILE" ns2:type="simple" ns2:href="page/1416451_0015.xml"/>
                </ns3:file>
                <ns3:file ID="PAGEXML_16" SEQ="16" MIMETYPE="application/xml" CREATED="2024-03-30T21:25:38.363+01:00" CHECKSUM="31b3f033923ae93a57155c8b7493f7c6" CHECKSUMTYPE="MD5">
                    <ns3:FLocat LOCTYPE="OTHER" OTHERLOCTYPE="FILE" ns2:type="simple" ns2:href="page/1416451_0016.xml"/>
                </ns3:file>
                <ns3:file ID="PAGEXML_17" SEQ="17" MIMETYPE="application/xml" CREATED="2024-03-30T21:25:39.131+01:00" CHECKSUM="323313a10655b10e14e40b6ac016949a" CHECKSUMTYPE="MD5">
                    <ns3:FLocat LOCTYPE="OTHER" OTHERLOCTYPE="FILE" ns2:type="simple" ns2:href="page/1416451_0017.xml"/>
                </ns3:file>
                <ns3:file ID="PAGEXML_18" SEQ="18" MIMETYPE="application/xml" CREATED="2024-03-30T21:25:39.875+01:00" CHECKSUM="bb58faf235aa0dd5d636fca4d55a5903" CHECKSUMTYPE="MD5">
                    <ns3:FLocat LOCTYPE="OTHER" OTHERLOCTYPE="FILE" ns2:type="simple" ns2:href="page/1416451_0018.xml"/>
                </ns3:file>
                <ns3:file ID="PAGEXML_19" SEQ="19" MIMETYPE="application/xml" CREATED="2024-03-30T21:25:40.643+01:00" CHECKSUM="34224a23e475938d5803e7c293395102" CHECKSUMTYPE="MD5">
                    <ns3:FLocat LOCTYPE="OTHER" OTHERLOCTYPE="FILE" ns2:type="simple" ns2:href="page/1416451_0019.xml"/>
                </ns3:file>
                <ns3:file ID="PAGEXML_20" SEQ="20" MIMETYPE="application/xml" CREATED="2024-03-30T21:25:41.431+01:00" CHECKSUM="3cf75fb91797f84f3fd0a4d37c30d1a8" CHECKSUMTYPE="MD5">
                    <ns3:FLocat LOCTYPE="OTHER" OTHERLOCTYPE="FILE" ns2:type="simple" ns2:href="page/1416451_0020.xml"/>
                </ns3:file>
                <ns3:file ID="PAGEXML_21" SEQ="21" MIMETYPE="application/xml" CREATED="2024-03-30T21:25:42.239+01:00" CHECKSUM="30b6889adee2e86fcbfbdeebf97728b3" CHECKSUMTYPE="MD5">
                    <ns3:FLocat LOCTYPE="OTHER" OTHERLOCTYPE="FILE" ns2:type="simple" ns2:href="page/1416451_0021.xml"/>
                </ns3:file>
                <ns3:file ID="PAGEXML_22" SEQ="22" MIMETYPE="application/xml" CREATED="2024-03-30T21:25:43.011+01:00" CHECKSUM="c61bd915d201a6dfe0b7092d821cb59c" CHECKSUMTYPE="MD5">
                    <ns3:FLocat LOCTYPE="OTHER" OTHERLOCTYPE="FILE" ns2:type="simple" ns2:href="page/1416451_0022.xml"/>
                </ns3:file>
                <ns3:file ID="PAGEXML_23" SEQ="23" MIMETYPE="application/xml" CREATED="2024-03-30T21:25:43.743+01:00" CHECKSUM="357ede33c78e1703f5b3cb37974d7f5b" CHECKSUMTYPE="MD5">
                    <ns3:FLocat LOCTYPE="OTHER" OTHERLOCTYPE="FILE" ns2:type="simple" ns2:href="page/1416451_0023.xml"/>
                </ns3:file>
                <ns3:file ID="PAGEXML_24" SEQ="24" MIMETYPE="application/xml" CREATED="2024-03-30T21:25:44.511+01:00" CHECKSUM="c5b83702490c9b118e831c005575f217" CHECKSUMTYPE="MD5">
                    <ns3:FLocat LOCTYPE="OTHER" OTHERLOCTYPE="FILE" ns2:type="simple" ns2:href="page/1416451_0024.xml"/>
                </ns3:file>
            </ns3:fileGrp>
        </ns3:fileGrp>
    </ns3:fileSec>
    <ns3:structMap ID="TRP_STRUCTMAP" TYPE="MANUSCRIPT">
        <ns3:div ID="TRP_DOC_DIV" ADMID="MD_ORIG">
            <ns3:div ID="PAGE_1" ORDER="1" TYPE="SINGLE_PAGE">
                <ns3:fptr>
                    <ns3:area FILEID="IMG_1"/>
                </ns3:fptr>
                <ns3:fptr>
                    <ns3:area FILEID="PAGEXML_1"/>
                </ns3:fptr>
            </ns3:div>
            <ns3:div ID="PAGE_2" ORDER="2" TYPE="SINGLE_PAGE">
                <ns3:fptr>
                    <ns3:area FILEID="IMG_2"/>
                </ns3:fptr>
                <ns3:fptr>
                    <ns3:area FILEID="PAGEXML_2"/>
                </ns3:fptr>
            </ns3:div>
            <ns3:div ID="PAGE_3" ORDER="3" TYPE="SINGLE_PAGE">
                <ns3:fptr>
                    <ns3:area FILEID="IMG_3"/>
                </ns3:fptr>
                <ns3:fptr>
                    <ns3:area FILEID="PAGEXML_3"/>
                </ns3:fptr>
            </ns3:div>
            <ns3:div ID="PAGE_4" ORDER="4" TYPE="SINGLE_PAGE">
                <ns3:fptr>
                    <ns3:area FILEID="IMG_4"/>
                </ns3:fptr>
                <ns3:fptr>
                    <ns3:area FILEID="PAGEXML_4"/>
                </ns3:fptr>
            </ns3:div>
            <ns3:div ID="PAGE_5" ORDER="5" TYPE="SINGLE_PAGE">
                <ns3:fptr>
                    <ns3:area FILEID="IMG_5"/>
                </ns3:fptr>
                <ns3:fptr>
                    <ns3:area FILEID="PAGEXML_5"/>
                </ns3:fptr>
            </ns3:div>
            <ns3:div ID="PAGE_6" ORDER="6" TYPE="SINGLE_PAGE">
                <ns3:fptr>
                    <ns3:area FILEID="IMG_6"/>
                </ns3:fptr>
                <ns3:fptr>
                    <ns3:area FILEID="PAGEXML_6"/>
                </ns3:fptr>
            </ns3:div>
            <ns3:div ID="PAGE_7" ORDER="7" TYPE="SINGLE_PAGE">
                <ns3:fptr>
                    <ns3:area FILEID="IMG_7"/>
                </ns3:fptr>
                <ns3:fptr>
                    <ns3:area FILEID="PAGEXML_7"/>
                </ns3:fptr>
            </ns3:div>
            <ns3:div ID="PAGE_8" ORDER="8" TYPE="SINGLE_PAGE">
                <ns3:fptr>
                    <ns3:area FILEID="IMG_8"/>
                </ns3:fptr>
                <ns3:fptr>
                    <ns3:area FILEID="PAGEXML_8"/>
                </ns3:fptr>
            </ns3:div>
            <ns3:div ID="PAGE_9" ORDER="9" TYPE="SINGLE_PAGE">
                <ns3:fptr>
                    <ns3:area FILEID="IMG_9"/>
                </ns3:fptr>
                <ns3:fptr>
                    <ns3:area FILEID="PAGEXML_9"/>
                </ns3:fptr>
            </ns3:div>
            <ns3:div ID="PAGE_10" ORDER="10" TYPE="SINGLE_PAGE">
                <ns3:fptr>
                    <ns3:area FILEID="IMG_10"/>
                </ns3:fptr>
                <ns3:fptr>
                    <ns3:area FILEID="PAGEXML_10"/>
                </ns3:fptr>
            </ns3:div>
            <ns3:div ID="PAGE_11" ORDER="11" TYPE="SINGLE_PAGE">
                <ns3:fptr>
                    <ns3:area FILEID="IMG_11"/>
                </ns3:fptr>
                <ns3:fptr>
                    <ns3:area FILEID="PAGEXML_11"/>
                </ns3:fptr>
            </ns3:div>
            <ns3:div ID="PAGE_12" ORDER="12" TYPE="SINGLE_PAGE">
                <ns3:fptr>
                    <ns3:area FILEID="IMG_12"/>
                </ns3:fptr>
                <ns3:fptr>
                    <ns3:area FILEID="PAGEXML_12"/>
                </ns3:fptr>
            </ns3:div>
            <ns3:div ID="PAGE_13" ORDER="13" TYPE="SINGLE_PAGE">
                <ns3:fptr>
                    <ns3:area FILEID="IMG_13"/>
                </ns3:fptr>
                <ns3:fptr>
                    <ns3:area FILEID="PAGEXML_13"/>
                </ns3:fptr>
            </ns3:div>
            <ns3:div ID="PAGE_14" ORDER="14" TYPE="SINGLE_PAGE">
                <ns3:fptr>
                    <ns3:area FILEID="IMG_14"/>
                </ns3:fptr>
                <ns3:fptr>
                    <ns3:area FILEID="PAGEXML_14"/>
                </ns3:fptr>
            </ns3:div>
            <ns3:div ID="PAGE_15" ORDER="15" TYPE="SINGLE_PAGE">
                <ns3:fptr>
                    <ns3:area FILEID="IMG_15"/>
                </ns3:fptr>
                <ns3:fptr>
                    <ns3:area FILEID="PAGEXML_15"/>
                </ns3:fptr>
            </ns3:div>
            <ns3:div ID="PAGE_16" ORDER="16" TYPE="SINGLE_PAGE">
                <ns3:fptr>
                    <ns3:area FILEID="IMG_16"/>
                </ns3:fptr>
                <ns3:fptr>
                    <ns3:area FILEID="PAGEXML_16"/>
                </ns3:fptr>
            </ns3:div>
            <ns3:div ID="PAGE_17" ORDER="17" TYPE="SINGLE_PAGE">
                <ns3:fptr>
                    <ns3:area FILEID="IMG_17"/>
                </ns3:fptr>
                <ns3:fptr>
                    <ns3:area FILEID="PAGEXML_17"/>
                </ns3:fptr>
            </ns3:div>
            <ns3:div ID="PAGE_18" ORDER="18" TYPE="SINGLE_PAGE">
                <ns3:fptr>
                    <ns3:area FILEID="IMG_18"/>
                </ns3:fptr>
                <ns3:fptr>
                    <ns3:area FILEID="PAGEXML_18"/>
                </ns3:fptr>
            </ns3:div>
            <ns3:div ID="PAGE_19" ORDER="19" TYPE="SINGLE_PAGE">
                <ns3:fptr>
                    <ns3:area FILEID="IMG_19"/>
                </ns3:fptr>
                <ns3:fptr>
                    <ns3:area FILEID="PAGEXML_19"/>
                </ns3:fptr>
            </ns3:div>
            <ns3:div ID="PAGE_20" ORDER="20" TYPE="SINGLE_PAGE">
                <ns3:fptr>
                    <ns3:area FILEID="IMG_20"/>
                </ns3:fptr>
                <ns3:fptr>
                    <ns3:area FILEID="PAGEXML_20"/>
                </ns3:fptr>
            </ns3:div>
            <ns3:div ID="PAGE_21" ORDER="21" TYPE="SINGLE_PAGE">
                <ns3:fptr>
                    <ns3:area FILEID="IMG_21"/>
                </ns3:fptr>
                <ns3:fptr>
                    <ns3:area FILEID="PAGEXML_21"/>
                </ns3:fptr>
            </ns3:div>
            <ns3:div ID="PAGE_22" ORDER="22" TYPE="SINGLE_PAGE">
                <ns3:fptr>
                    <ns3:area FILEID="IMG_22"/>
                </ns3:fptr>
                <ns3:fptr>
                    <ns3:area FILEID="PAGEXML_22"/>
                </ns3:fptr>
            </ns3:div>
            <ns3:div ID="PAGE_23" ORDER="23" TYPE="SINGLE_PAGE">
                <ns3:fptr>
                    <ns3:area FILEID="IMG_23"/>
                </ns3:fptr>
                <ns3:fptr>
                    <ns3:area FILEID="PAGEXML_23"/>
                </ns3:fptr>
            </ns3:div>
            <ns3:div ID="PAGE_24" ORDER="24" TYPE="SINGLE_PAGE">
                <ns3:fptr>
                    <ns3:area FILEID="IMG_24"/>
                </ns3:fptr>
                <ns3:fptr>
                    <ns3:area FILEID="PAGEXML_24"/>
                </ns3:fptr>
            </ns3:div>
        </ns3:div>
    </ns3:structMap>
</ns3:mets>
