<?xml version="1.0" encoding="UTF-8" standalone="yes"?>
<ns3:mets xmlns:ns2="http://www.w3.org/1999/xlink" xmlns:ns3="http://www.loc.gov/METS/" xmlns:xsi="http://www.w3.org/2001/XMLSchema-instance" OBJID="1589050" LABEL="A021 Die beiden Künstler : Künstler" PROFILE="TRP_V1" xsi:schemaLocation="http://www.loc.gov/METS/ http://www.loc.gov/standards/mets/mets.xsd">
    <ns3:metsHdr CREATEDATE="2024-03-30T10:28:32.574+01:00" LASTMODDATE="2024-03-30T10:28:32.574+01:00" RECORDSTATUS="SUBMITTED">
        <ns3:agent ROLE="CREATOR" TYPE="ORGANIZATION">
            <ns3:name>UIBK</ns3:name>
            <ns3:note>This METS file was generated by Transkribus</ns3:note>
        </ns3:agent>
    </ns3:metsHdr>
    <ns3:amdSec ID="SOURCE">
        <ns3:sourceMD ID="MD_ORIG">
            <ns3:mdWrap ID="TRP_DOC_MD" MDTYPE="OTHER">
                <ns3:xmlData>
                    <trpDocMetadata>
                        <docId>1589050</docId>
                        <title>A021 Die beiden Künstler : Künstler</title>
                        <uploadTimestamp>1695818321360</uploadTimestamp>
                        <uploader>martin.anton.mueller@oeaw.ac.at</uploader>
                        <uploaderId>40391</uploaderId>
                        <nrOfPages>76</nrOfPages>
                        <pageId>60124851</pageId>
                        <url>https://files.transkribus.eu/Get?fileType=view&amp;id=EDBLIYEVXPXAHDHAVZKULPJL</url>
                        <thumbUrl>https://files.transkribus.eu/Get?fileType=thumb&amp;id=EDBLIYEVXPXAHDHAVZKULPJL</thumbUrl>
                        <status>0</status>
                        <fimgStoreColl>TrpDoc_DEA_1589050</fimgStoreColl>
                        <localFolder>/mnt/transkribus/export/TRP_EXPORT_10971393407279409760/1589050/A021_Die_beiden_Künstler___Künstler</localFolder>
                        <origDocId>0</origDocId>
                        <collectionList>
                            <colList>
<colId>200901</colId>
<colName>schnitzler-mikrofilme</colName>
<description>created by martin.anton.mueller@oeaw.ac.at</description>
<crowdsourcing>false</crowdsourcing>
<elearning>false</elearning>
<nrOfDocuments>0</nrOfDocuments>
                            </colList>
                        </collectionList>
                        <mainColId>200901</mainColId>
                    </trpDocMetadata>
                </ns3:xmlData>
            </ns3:mdWrap>
        </ns3:sourceMD>
    </ns3:amdSec>
    <ns3:fileSec>
        <ns3:fileGrp ID="MASTER">
            <ns3:fileGrp ID="IMG">
                <ns3:file ID="IMG_1" SEQ="1" MIMETYPE="image/jpeg" CREATED="2023-09-27T14:38:41.668+02:00" CHECKSUM="c1a03aa314fc6dd44dd13e08aad2bb9c" CHECKSUMTYPE="MD5">
                    <ns3:FLocat LOCTYPE="OTHER" OTHERLOCTYPE="FILE" ns2:type="simple" ns2:href="1589050_0001.jpg"/>
                </ns3:file>
                <ns3:file ID="IMG_2" SEQ="2" MIMETYPE="image/jpeg" CREATED="2023-09-27T14:38:42.123+02:00" CHECKSUM="ed99b18df7ebd0fb0c00205e40be972f" CHECKSUMTYPE="MD5">
                    <ns3:FLocat LOCTYPE="OTHER" OTHERLOCTYPE="FILE" ns2:type="simple" ns2:href="1589050_0002.jpg"/>
                </ns3:file>
                <ns3:file ID="IMG_3" SEQ="3" MIMETYPE="image/jpeg" CREATED="2023-09-27T14:38:42.817+02:00" CHECKSUM="25e44626d7ad15dc25b884b4dffbc663" CHECKSUMTYPE="MD5">
                    <ns3:FLocat LOCTYPE="OTHER" OTHERLOCTYPE="FILE" ns2:type="simple" ns2:href="1589050_0003.jpg"/>
                </ns3:file>
                <ns3:file ID="IMG_4" SEQ="4" MIMETYPE="image/jpeg" CREATED="2023-09-27T14:38:43.266+02:00" CHECKSUM="466d0eefcc68fea16ee14553c1f879e9" CHECKSUMTYPE="MD5">
                    <ns3:FLocat LOCTYPE="OTHER" OTHERLOCTYPE="FILE" ns2:type="simple" ns2:href="1589050_0004.jpg"/>
                </ns3:file>
                <ns3:file ID="IMG_5" SEQ="5" MIMETYPE="image/jpeg" CREATED="2023-09-27T14:38:43.665+02:00" CHECKSUM="2f4d333680db62c9d14ad40f269f0fa0" CHECKSUMTYPE="MD5">
                    <ns3:FLocat LOCTYPE="OTHER" OTHERLOCTYPE="FILE" ns2:type="simple" ns2:href="1589050_0005.jpg"/>
                </ns3:file>
                <ns3:file ID="IMG_6" SEQ="6" MIMETYPE="image/jpeg" CREATED="2023-09-27T14:38:44.155+02:00" CHECKSUM="2c0610c342d93b47beb632d8cf92a25c" CHECKSUMTYPE="MD5">
                    <ns3:FLocat LOCTYPE="OTHER" OTHERLOCTYPE="FILE" ns2:type="simple" ns2:href="1589050_0006.jpg"/>
                </ns3:file>
                <ns3:file ID="IMG_7" SEQ="7" MIMETYPE="image/jpeg" CREATED="2023-09-27T14:38:44.776+02:00" CHECKSUM="4d46943053fb6ead7a3f1e01278260e6" CHECKSUMTYPE="MD5">
                    <ns3:FLocat LOCTYPE="OTHER" OTHERLOCTYPE="FILE" ns2:type="simple" ns2:href="1589050_0007.jpg"/>
                </ns3:file>
                <ns3:file ID="IMG_8" SEQ="8" MIMETYPE="image/jpeg" CREATED="2023-09-27T14:38:45.829+02:00" CHECKSUM="86a7004e2b9262fbe38fc4949386afe1" CHECKSUMTYPE="MD5">
                    <ns3:FLocat LOCTYPE="OTHER" OTHERLOCTYPE="FILE" ns2:type="simple" ns2:href="1589050_0008.jpg"/>
                </ns3:file>
                <ns3:file ID="IMG_9" SEQ="9" MIMETYPE="image/jpeg" CREATED="2023-09-27T14:38:48.496+02:00" CHECKSUM="ca647f2f89fa5ce6a9fb6476eb36f702" CHECKSUMTYPE="MD5">
                    <ns3:FLocat LOCTYPE="OTHER" OTHERLOCTYPE="FILE" ns2:type="simple" ns2:href="1589050_0009.jpg"/>
                </ns3:file>
                <ns3:file ID="IMG_10" SEQ="10" MIMETYPE="image/jpeg" CREATED="2023-09-27T14:38:49.377+02:00" CHECKSUM="2b6219d8788470c5c9f17c956cbcc652" CHECKSUMTYPE="MD5">
                    <ns3:FLocat LOCTYPE="OTHER" OTHERLOCTYPE="FILE" ns2:type="simple" ns2:href="1589050_0010.jpg"/>
                </ns3:file>
                <ns3:file ID="IMG_11" SEQ="11" MIMETYPE="image/jpeg" CREATED="2023-09-27T14:38:49.865+02:00" CHECKSUM="606c52ea79f2f334c88bc83adcb4005b" CHECKSUMTYPE="MD5">
                    <ns3:FLocat LOCTYPE="OTHER" OTHERLOCTYPE="FILE" ns2:type="simple" ns2:href="1589050_0011.jpg"/>
                </ns3:file>
                <ns3:file ID="IMG_12" SEQ="12" MIMETYPE="image/jpeg" CREATED="2023-09-27T14:38:50.311+02:00" CHECKSUM="ab01c1524842cb86b1cdf1455ef65bd1" CHECKSUMTYPE="MD5">
                    <ns3:FLocat LOCTYPE="OTHER" OTHERLOCTYPE="FILE" ns2:type="simple" ns2:href="1589050_0012.jpg"/>
                </ns3:file>
                <ns3:file ID="IMG_13" SEQ="13" MIMETYPE="image/jpeg" CREATED="2023-09-27T14:38:50.782+02:00" CHECKSUM="8e685634ab7262fd8ab0c72f7a30d691" CHECKSUMTYPE="MD5">
                    <ns3:FLocat LOCTYPE="OTHER" OTHERLOCTYPE="FILE" ns2:type="simple" ns2:href="1589050_0013.jpg"/>
                </ns3:file>
                <ns3:file ID="IMG_14" SEQ="14" MIMETYPE="image/jpeg" CREATED="2023-09-27T14:38:51.315+02:00" CHECKSUM="46e27c07ffe37ce181fd3fcea90f800f" CHECKSUMTYPE="MD5">
                    <ns3:FLocat LOCTYPE="OTHER" OTHERLOCTYPE="FILE" ns2:type="simple" ns2:href="1589050_0014.jpg"/>
                </ns3:file>
                <ns3:file ID="IMG_15" SEQ="15" MIMETYPE="image/jpeg" CREATED="2023-09-27T14:38:53.069+02:00" CHECKSUM="8ac540df626b7cea70d01f52d8946742" CHECKSUMTYPE="MD5">
                    <ns3:FLocat LOCTYPE="OTHER" OTHERLOCTYPE="FILE" ns2:type="simple" ns2:href="1589050_0015.jpg"/>
                </ns3:file>
                <ns3:file ID="IMG_16" SEQ="16" MIMETYPE="image/jpeg" CREATED="2023-09-27T14:38:53.782+02:00" CHECKSUM="8b8a93932795a8dff504db0ea3e59767" CHECKSUMTYPE="MD5">
                    <ns3:FLocat LOCTYPE="OTHER" OTHERLOCTYPE="FILE" ns2:type="simple" ns2:href="1589050_0016.jpg"/>
                </ns3:file>
                <ns3:file ID="IMG_17" SEQ="17" MIMETYPE="image/jpeg" CREATED="2023-09-27T14:38:54.216+02:00" CHECKSUM="47efa0a2fd0f919d749bad6fa654ff54" CHECKSUMTYPE="MD5">
                    <ns3:FLocat LOCTYPE="OTHER" OTHERLOCTYPE="FILE" ns2:type="simple" ns2:href="1589050_0017.jpg"/>
                </ns3:file>
                <ns3:file ID="IMG_18" SEQ="18" MIMETYPE="image/jpeg" CREATED="2023-09-27T14:38:54.766+02:00" CHECKSUM="631778d90093db53f1a8f603c95e8b03" CHECKSUMTYPE="MD5">
                    <ns3:FLocat LOCTYPE="OTHER" OTHERLOCTYPE="FILE" ns2:type="simple" ns2:href="1589050_0018.jpg"/>
                </ns3:file>
                <ns3:file ID="IMG_19" SEQ="19" MIMETYPE="image/jpeg" CREATED="2023-09-27T14:38:55.468+02:00" CHECKSUM="300f1100d721c27f51439318ddf8bbd7" CHECKSUMTYPE="MD5">
                    <ns3:FLocat LOCTYPE="OTHER" OTHERLOCTYPE="FILE" ns2:type="simple" ns2:href="1589050_0019.jpg"/>
                </ns3:file>
                <ns3:file ID="IMG_20" SEQ="20" MIMETYPE="image/jpeg" CREATED="2023-09-27T14:38:55.925+02:00" CHECKSUM="646f7e1726f12cc67ebbef44213b918c" CHECKSUMTYPE="MD5">
                    <ns3:FLocat LOCTYPE="OTHER" OTHERLOCTYPE="FILE" ns2:type="simple" ns2:href="1589050_0020.jpg"/>
                </ns3:file>
                <ns3:file ID="IMG_21" SEQ="21" MIMETYPE="image/jpeg" CREATED="2023-09-27T14:38:56.495+02:00" CHECKSUM="a7d7b18c7b28beeea96976545f5a0157" CHECKSUMTYPE="MD5">
                    <ns3:FLocat LOCTYPE="OTHER" OTHERLOCTYPE="FILE" ns2:type="simple" ns2:href="1589050_0021.jpg"/>
                </ns3:file>
                <ns3:file ID="IMG_22" SEQ="22" MIMETYPE="image/jpeg" CREATED="2023-09-27T14:38:57.007+02:00" CHECKSUM="c8c69f96feb5b162158777e3e24759c5" CHECKSUMTYPE="MD5">
                    <ns3:FLocat LOCTYPE="OTHER" OTHERLOCTYPE="FILE" ns2:type="simple" ns2:href="1589050_0022.jpg"/>
                </ns3:file>
                <ns3:file ID="IMG_23" SEQ="23" MIMETYPE="image/jpeg" CREATED="2023-09-27T14:38:57.537+02:00" CHECKSUM="84c9d8a24d96aa4f45c130a167fde8de" CHECKSUMTYPE="MD5">
                    <ns3:FLocat LOCTYPE="OTHER" OTHERLOCTYPE="FILE" ns2:type="simple" ns2:href="1589050_0023.jpg"/>
                </ns3:file>
                <ns3:file ID="IMG_24" SEQ="24" MIMETYPE="image/jpeg" CREATED="2023-09-27T14:38:58.095+02:00" CHECKSUM="edfdf77467f1ce15dc8827ac7965069b" CHECKSUMTYPE="MD5">
                    <ns3:FLocat LOCTYPE="OTHER" OTHERLOCTYPE="FILE" ns2:type="simple" ns2:href="1589050_0024.jpg"/>
                </ns3:file>
                <ns3:file ID="IMG_25" SEQ="25" MIMETYPE="image/jpeg" CREATED="2023-09-27T14:38:58.611+02:00" CHECKSUM="e8d98a0a7368cee74488bdbc8719bcf8" CHECKSUMTYPE="MD5">
                    <ns3:FLocat LOCTYPE="OTHER" OTHERLOCTYPE="FILE" ns2:type="simple" ns2:href="1589050_0025.jpg"/>
                </ns3:file>
                <ns3:file ID="IMG_26" SEQ="26" MIMETYPE="image/jpeg" CREATED="2023-09-27T14:38:59.055+02:00" CHECKSUM="00a7de92d19c487ebb9633e2513b0b5d" CHECKSUMTYPE="MD5">
                    <ns3:FLocat LOCTYPE="OTHER" OTHERLOCTYPE="FILE" ns2:type="simple" ns2:href="1589050_0026.jpg"/>
                </ns3:file>
                <ns3:file ID="IMG_27" SEQ="27" MIMETYPE="image/jpeg" CREATED="2023-09-27T14:38:59.636+02:00" CHECKSUM="9fb6b21f6b201bd6d09e248d6259f193" CHECKSUMTYPE="MD5">
                    <ns3:FLocat LOCTYPE="OTHER" OTHERLOCTYPE="FILE" ns2:type="simple" ns2:href="1589050_0027.jpg"/>
                </ns3:file>
                <ns3:file ID="IMG_28" SEQ="28" MIMETYPE="image/jpeg" CREATED="2023-09-27T14:39:00.048+02:00" CHECKSUM="f8b5f11ee3487f081962687a71c23c6e" CHECKSUMTYPE="MD5">
                    <ns3:FLocat LOCTYPE="OTHER" OTHERLOCTYPE="FILE" ns2:type="simple" ns2:href="1589050_0028.jpg"/>
                </ns3:file>
                <ns3:file ID="IMG_29" SEQ="29" MIMETYPE="image/jpeg" CREATED="2023-09-27T14:39:00.563+02:00" CHECKSUM="35c226dce59cffced20470c071daaba6" CHECKSUMTYPE="MD5">
                    <ns3:FLocat LOCTYPE="OTHER" OTHERLOCTYPE="FILE" ns2:type="simple" ns2:href="1589050_0029.jpg"/>
                </ns3:file>
                <ns3:file ID="IMG_30" SEQ="30" MIMETYPE="image/jpeg" CREATED="2023-09-27T14:39:01.186+02:00" CHECKSUM="08e3ef3c8eb404d3ff8ef018ee7cf6cb" CHECKSUMTYPE="MD5">
                    <ns3:FLocat LOCTYPE="OTHER" OTHERLOCTYPE="FILE" ns2:type="simple" ns2:href="1589050_0030.jpg"/>
                </ns3:file>
                <ns3:file ID="IMG_31" SEQ="31" MIMETYPE="image/jpeg" CREATED="2023-09-27T14:39:01.658+02:00" CHECKSUM="9920f1d4bb22475c8b98e42c4f2b9801" CHECKSUMTYPE="MD5">
                    <ns3:FLocat LOCTYPE="OTHER" OTHERLOCTYPE="FILE" ns2:type="simple" ns2:href="1589050_0031.jpg"/>
                </ns3:file>
                <ns3:file ID="IMG_32" SEQ="32" MIMETYPE="image/jpeg" CREATED="2023-09-27T14:39:02.090+02:00" CHECKSUM="1bba9d3cd167981e6d8ba358617d2bcd" CHECKSUMTYPE="MD5">
                    <ns3:FLocat LOCTYPE="OTHER" OTHERLOCTYPE="FILE" ns2:type="simple" ns2:href="1589050_0032.jpg"/>
                </ns3:file>
                <ns3:file ID="IMG_33" SEQ="33" MIMETYPE="image/jpeg" CREATED="2023-09-27T14:39:02.567+02:00" CHECKSUM="731ba1369ba42271d7e21801ab485a9b" CHECKSUMTYPE="MD5">
                    <ns3:FLocat LOCTYPE="OTHER" OTHERLOCTYPE="FILE" ns2:type="simple" ns2:href="1589050_0033.jpg"/>
                </ns3:file>
                <ns3:file ID="IMG_34" SEQ="34" MIMETYPE="image/jpeg" CREATED="2023-09-27T14:39:03.116+02:00" CHECKSUM="b14cce03163d8ad333d023d3337338a2" CHECKSUMTYPE="MD5">
                    <ns3:FLocat LOCTYPE="OTHER" OTHERLOCTYPE="FILE" ns2:type="simple" ns2:href="1589050_0034.jpg"/>
                </ns3:file>
                <ns3:file ID="IMG_35" SEQ="35" MIMETYPE="image/jpeg" CREATED="2023-09-27T14:39:03.893+02:00" CHECKSUM="3076864f0176ad0da8235e1b1a2d7fa1" CHECKSUMTYPE="MD5">
                    <ns3:FLocat LOCTYPE="OTHER" OTHERLOCTYPE="FILE" ns2:type="simple" ns2:href="1589050_0035.jpg"/>
                </ns3:file>
                <ns3:file ID="IMG_36" SEQ="36" MIMETYPE="image/jpeg" CREATED="2023-09-27T14:39:04.358+02:00" CHECKSUM="2724b743d27aa1683a58a4a4b56c172d" CHECKSUMTYPE="MD5">
                    <ns3:FLocat LOCTYPE="OTHER" OTHERLOCTYPE="FILE" ns2:type="simple" ns2:href="1589050_0036.jpg"/>
                </ns3:file>
                <ns3:file ID="IMG_37" SEQ="37" MIMETYPE="image/jpeg" CREATED="2023-09-27T14:39:04.859+02:00" CHECKSUM="5e042159d272959716c2af125acc6cd6" CHECKSUMTYPE="MD5">
                    <ns3:FLocat LOCTYPE="OTHER" OTHERLOCTYPE="FILE" ns2:type="simple" ns2:href="1589050_0037.jpg"/>
                </ns3:file>
                <ns3:file ID="IMG_38" SEQ="38" MIMETYPE="image/jpeg" CREATED="2023-09-27T14:39:05.392+02:00" CHECKSUM="dd4d9e43780772ae58a48ce8040e704f" CHECKSUMTYPE="MD5">
                    <ns3:FLocat LOCTYPE="OTHER" OTHERLOCTYPE="FILE" ns2:type="simple" ns2:href="1589050_0038.jpg"/>
                </ns3:file>
                <ns3:file ID="IMG_39" SEQ="39" MIMETYPE="image/jpeg" CREATED="2023-09-27T14:39:05.956+02:00" CHECKSUM="4b7f7cc824a54d90c13ac0be6f1a29bd" CHECKSUMTYPE="MD5">
                    <ns3:FLocat LOCTYPE="OTHER" OTHERLOCTYPE="FILE" ns2:type="simple" ns2:href="1589050_0039.jpg"/>
                </ns3:file>
                <ns3:file ID="IMG_40" SEQ="40" MIMETYPE="image/jpeg" CREATED="2023-09-27T14:39:06.461+02:00" CHECKSUM="5c24bd0c0135d2d13ce54a07e36040f7" CHECKSUMTYPE="MD5">
                    <ns3:FLocat LOCTYPE="OTHER" OTHERLOCTYPE="FILE" ns2:type="simple" ns2:href="1589050_0040.jpg"/>
                </ns3:file>
                <ns3:file ID="IMG_41" SEQ="41" MIMETYPE="image/jpeg" CREATED="2023-09-27T14:39:06.935+02:00" CHECKSUM="fef92348be43006fd1a72bb08b8b28d1" CHECKSUMTYPE="MD5">
                    <ns3:FLocat LOCTYPE="OTHER" OTHERLOCTYPE="FILE" ns2:type="simple" ns2:href="1589050_0041.jpg"/>
                </ns3:file>
                <ns3:file ID="IMG_42" SEQ="42" MIMETYPE="image/jpeg" CREATED="2023-09-27T14:39:07.431+02:00" CHECKSUM="a87ac6e18281f7716d3c49798f5390ac" CHECKSUMTYPE="MD5">
                    <ns3:FLocat LOCTYPE="OTHER" OTHERLOCTYPE="FILE" ns2:type="simple" ns2:href="1589050_0042.jpg"/>
                </ns3:file>
                <ns3:file ID="IMG_43" SEQ="43" MIMETYPE="image/jpeg" CREATED="2023-09-27T14:39:08.009+02:00" CHECKSUM="af3fd072e78b01445c6b3403e224926f" CHECKSUMTYPE="MD5">
                    <ns3:FLocat LOCTYPE="OTHER" OTHERLOCTYPE="FILE" ns2:type="simple" ns2:href="1589050_0043.jpg"/>
                </ns3:file>
                <ns3:file ID="IMG_44" SEQ="44" MIMETYPE="image/jpeg" CREATED="2023-09-27T14:39:08.524+02:00" CHECKSUM="338aad4e225769c23aec47c260a53517" CHECKSUMTYPE="MD5">
                    <ns3:FLocat LOCTYPE="OTHER" OTHERLOCTYPE="FILE" ns2:type="simple" ns2:href="1589050_0044.jpg"/>
                </ns3:file>
                <ns3:file ID="IMG_45" SEQ="45" MIMETYPE="image/jpeg" CREATED="2023-09-27T14:39:09.102+02:00" CHECKSUM="7a50c7888c07a97f8be26656d69967f0" CHECKSUMTYPE="MD5">
                    <ns3:FLocat LOCTYPE="OTHER" OTHERLOCTYPE="FILE" ns2:type="simple" ns2:href="1589050_0045.jpg"/>
                </ns3:file>
                <ns3:file ID="IMG_46" SEQ="46" MIMETYPE="image/jpeg" CREATED="2023-09-27T14:39:09.586+02:00" CHECKSUM="9bf69221253e5b68b2044c228184ccb3" CHECKSUMTYPE="MD5">
                    <ns3:FLocat LOCTYPE="OTHER" OTHERLOCTYPE="FILE" ns2:type="simple" ns2:href="1589050_0046.jpg"/>
                </ns3:file>
                <ns3:file ID="IMG_47" SEQ="47" MIMETYPE="image/jpeg" CREATED="2023-09-27T14:39:10.082+02:00" CHECKSUM="914602277d4d399e1cc42dcc29f9e273" CHECKSUMTYPE="MD5">
                    <ns3:FLocat LOCTYPE="OTHER" OTHERLOCTYPE="FILE" ns2:type="simple" ns2:href="1589050_0047.jpg"/>
                </ns3:file>
                <ns3:file ID="IMG_48" SEQ="48" MIMETYPE="image/jpeg" CREATED="2023-09-27T14:39:10.475+02:00" CHECKSUM="0fd226ae0dba7d5b707ad2373b6ff67c" CHECKSUMTYPE="MD5">
                    <ns3:FLocat LOCTYPE="OTHER" OTHERLOCTYPE="FILE" ns2:type="simple" ns2:href="1589050_0048.jpg"/>
                </ns3:file>
                <ns3:file ID="IMG_49" SEQ="49" MIMETYPE="image/jpeg" CREATED="2023-09-27T14:39:11.089+02:00" CHECKSUM="928d7ac423f82ae0b99cacd976d66a71" CHECKSUMTYPE="MD5">
                    <ns3:FLocat LOCTYPE="OTHER" OTHERLOCTYPE="FILE" ns2:type="simple" ns2:href="1589050_0049.jpg"/>
                </ns3:file>
                <ns3:file ID="IMG_50" SEQ="50" MIMETYPE="image/jpeg" CREATED="2023-09-27T14:39:11.554+02:00" CHECKSUM="410d9da71bda262e7a6e0b6290120a68" CHECKSUMTYPE="MD5">
                    <ns3:FLocat LOCTYPE="OTHER" OTHERLOCTYPE="FILE" ns2:type="simple" ns2:href="1589050_0050.jpg"/>
                </ns3:file>
                <ns3:file ID="IMG_51" SEQ="51" MIMETYPE="image/jpeg" CREATED="2023-09-27T14:39:12.188+02:00" CHECKSUM="df16e6ab73e585dc08fe0274ca702c5a" CHECKSUMTYPE="MD5">
                    <ns3:FLocat LOCTYPE="OTHER" OTHERLOCTYPE="FILE" ns2:type="simple" ns2:href="1589050_0051.jpg"/>
                </ns3:file>
                <ns3:file ID="IMG_52" SEQ="52" MIMETYPE="image/jpeg" CREATED="2023-09-27T14:39:12.833+02:00" CHECKSUM="6a7f6a5ff348314cfcc4b40a6be796f0" CHECKSUMTYPE="MD5">
                    <ns3:FLocat LOCTYPE="OTHER" OTHERLOCTYPE="FILE" ns2:type="simple" ns2:href="1589050_0052.jpg"/>
                </ns3:file>
                <ns3:file ID="IMG_53" SEQ="53" MIMETYPE="image/jpeg" CREATED="2023-09-27T14:39:13.539+02:00" CHECKSUM="13d550ec7f09de5ca8487223477a7b79" CHECKSUMTYPE="MD5">
                    <ns3:FLocat LOCTYPE="OTHER" OTHERLOCTYPE="FILE" ns2:type="simple" ns2:href="1589050_0053.jpg"/>
                </ns3:file>
                <ns3:file ID="IMG_54" SEQ="54" MIMETYPE="image/jpeg" CREATED="2023-09-27T14:39:13.992+02:00" CHECKSUM="9c7597a5c65fe98bd7b9c1826e81802c" CHECKSUMTYPE="MD5">
                    <ns3:FLocat LOCTYPE="OTHER" OTHERLOCTYPE="FILE" ns2:type="simple" ns2:href="1589050_0054.jpg"/>
                </ns3:file>
                <ns3:file ID="IMG_55" SEQ="55" MIMETYPE="image/jpeg" CREATED="2023-09-27T14:39:14.577+02:00" CHECKSUM="34ac70015bbc397321ab5da6cd66f7ef" CHECKSUMTYPE="MD5">
                    <ns3:FLocat LOCTYPE="OTHER" OTHERLOCTYPE="FILE" ns2:type="simple" ns2:href="1589050_0055.jpg"/>
                </ns3:file>
                <ns3:file ID="IMG_56" SEQ="56" MIMETYPE="image/jpeg" CREATED="2023-09-27T14:39:14.979+02:00" CHECKSUM="bbc0b98299278c028beb9a71340c2899" CHECKSUMTYPE="MD5">
                    <ns3:FLocat LOCTYPE="OTHER" OTHERLOCTYPE="FILE" ns2:type="simple" ns2:href="1589050_0056.jpg"/>
                </ns3:file>
                <ns3:file ID="IMG_57" SEQ="57" MIMETYPE="image/jpeg" CREATED="2023-09-27T14:39:15.432+02:00" CHECKSUM="5bd429f5fc86f47a274b1031b2273996" CHECKSUMTYPE="MD5">
                    <ns3:FLocat LOCTYPE="OTHER" OTHERLOCTYPE="FILE" ns2:type="simple" ns2:href="1589050_0057.jpg"/>
                </ns3:file>
                <ns3:file ID="IMG_58" SEQ="58" MIMETYPE="image/jpeg" CREATED="2023-09-27T14:39:15.997+02:00" CHECKSUM="d7ea1aadaec6b992f3a1ff900841e99a" CHECKSUMTYPE="MD5">
                    <ns3:FLocat LOCTYPE="OTHER" OTHERLOCTYPE="FILE" ns2:type="simple" ns2:href="1589050_0058.jpg"/>
                </ns3:file>
                <ns3:file ID="IMG_59" SEQ="59" MIMETYPE="image/jpeg" CREATED="2023-09-27T14:39:16.454+02:00" CHECKSUM="8e2509fe1b9694d26a0fabd04505b4aa" CHECKSUMTYPE="MD5">
                    <ns3:FLocat LOCTYPE="OTHER" OTHERLOCTYPE="FILE" ns2:type="simple" ns2:href="1589050_0059.jpg"/>
                </ns3:file>
                <ns3:file ID="IMG_60" SEQ="60" MIMETYPE="image/jpeg" CREATED="2023-09-27T14:39:16.916+02:00" CHECKSUM="4f94f3a576945a4264dff09ccdd5b7d9" CHECKSUMTYPE="MD5">
                    <ns3:FLocat LOCTYPE="OTHER" OTHERLOCTYPE="FILE" ns2:type="simple" ns2:href="1589050_0060.jpg"/>
                </ns3:file>
                <ns3:file ID="IMG_61" SEQ="61" MIMETYPE="image/jpeg" CREATED="2023-09-27T14:39:17.394+02:00" CHECKSUM="07f09d3938fe4917553fa5555ecaf0ec" CHECKSUMTYPE="MD5">
                    <ns3:FLocat LOCTYPE="OTHER" OTHERLOCTYPE="FILE" ns2:type="simple" ns2:href="1589050_0061.jpg"/>
                </ns3:file>
                <ns3:file ID="IMG_62" SEQ="62" MIMETYPE="image/jpeg" CREATED="2023-09-27T14:39:17.802+02:00" CHECKSUM="923f84e8788e8d197d1d2ac6747adc94" CHECKSUMTYPE="MD5">
                    <ns3:FLocat LOCTYPE="OTHER" OTHERLOCTYPE="FILE" ns2:type="simple" ns2:href="1589050_0062.jpg"/>
                </ns3:file>
                <ns3:file ID="IMG_63" SEQ="63" MIMETYPE="image/jpeg" CREATED="2023-09-27T14:39:18.287+02:00" CHECKSUM="b015de128be8261a6ee6a388135324ca" CHECKSUMTYPE="MD5">
                    <ns3:FLocat LOCTYPE="OTHER" OTHERLOCTYPE="FILE" ns2:type="simple" ns2:href="1589050_0063.jpg"/>
                </ns3:file>
                <ns3:file ID="IMG_64" SEQ="64" MIMETYPE="image/jpeg" CREATED="2023-09-27T14:39:18.708+02:00" CHECKSUM="600277c718895c34fd169de68f092751" CHECKSUMTYPE="MD5">
                    <ns3:FLocat LOCTYPE="OTHER" OTHERLOCTYPE="FILE" ns2:type="simple" ns2:href="1589050_0064.jpg"/>
                </ns3:file>
                <ns3:file ID="IMG_65" SEQ="65" MIMETYPE="image/jpeg" CREATED="2023-09-27T14:39:19.141+02:00" CHECKSUM="4a18460db3f07e088bcbd8e4c14f2b32" CHECKSUMTYPE="MD5">
                    <ns3:FLocat LOCTYPE="OTHER" OTHERLOCTYPE="FILE" ns2:type="simple" ns2:href="1589050_0065.jpg"/>
                </ns3:file>
                <ns3:file ID="IMG_66" SEQ="66" MIMETYPE="image/jpeg" CREATED="2023-09-27T14:39:19.526+02:00" CHECKSUM="d1432212c29072d095f43e71549939d1" CHECKSUMTYPE="MD5">
                    <ns3:FLocat LOCTYPE="OTHER" OTHERLOCTYPE="FILE" ns2:type="simple" ns2:href="1589050_0066.jpg"/>
                </ns3:file>
                <ns3:file ID="IMG_67" SEQ="67" MIMETYPE="image/jpeg" CREATED="2023-09-27T14:39:20.002+02:00" CHECKSUM="ce7da2583c615c6b3964852e0532c23c" CHECKSUMTYPE="MD5">
                    <ns3:FLocat LOCTYPE="OTHER" OTHERLOCTYPE="FILE" ns2:type="simple" ns2:href="1589050_0067.jpg"/>
                </ns3:file>
                <ns3:file ID="IMG_68" SEQ="68" MIMETYPE="image/jpeg" CREATED="2023-09-27T14:39:20.428+02:00" CHECKSUM="b159d7698a8b597c148dc638dc25a2d1" CHECKSUMTYPE="MD5">
                    <ns3:FLocat LOCTYPE="OTHER" OTHERLOCTYPE="FILE" ns2:type="simple" ns2:href="1589050_0068.jpg"/>
                </ns3:file>
                <ns3:file ID="IMG_69" SEQ="69" MIMETYPE="image/jpeg" CREATED="2023-09-27T14:39:20.941+02:00" CHECKSUM="6b507982ea389598e28524dae723df06" CHECKSUMTYPE="MD5">
                    <ns3:FLocat LOCTYPE="OTHER" OTHERLOCTYPE="FILE" ns2:type="simple" ns2:href="1589050_0069.jpg"/>
                </ns3:file>
                <ns3:file ID="IMG_70" SEQ="70" MIMETYPE="image/jpeg" CREATED="2023-09-27T14:39:21.364+02:00" CHECKSUM="abc60a9d42883b955006fc60e66fc490" CHECKSUMTYPE="MD5">
                    <ns3:FLocat LOCTYPE="OTHER" OTHERLOCTYPE="FILE" ns2:type="simple" ns2:href="1589050_0070.jpg"/>
                </ns3:file>
                <ns3:file ID="IMG_71" SEQ="71" MIMETYPE="image/jpeg" CREATED="2023-09-27T14:39:21.836+02:00" CHECKSUM="0b72dcd0d16fe3d5aadacb748c1a7dd9" CHECKSUMTYPE="MD5">
                    <ns3:FLocat LOCTYPE="OTHER" OTHERLOCTYPE="FILE" ns2:type="simple" ns2:href="1589050_0071.jpg"/>
                </ns3:file>
                <ns3:file ID="IMG_72" SEQ="72" MIMETYPE="image/jpeg" CREATED="2023-09-27T14:39:22.235+02:00" CHECKSUM="508c0684d720a4f697c5f193f7c9160e" CHECKSUMTYPE="MD5">
                    <ns3:FLocat LOCTYPE="OTHER" OTHERLOCTYPE="FILE" ns2:type="simple" ns2:href="1589050_0072.jpg"/>
                </ns3:file>
                <ns3:file ID="IMG_73" SEQ="73" MIMETYPE="image/jpeg" CREATED="2023-09-27T14:39:22.610+02:00" CHECKSUM="6fedc66abd58fa4e27720a672fad27ab" CHECKSUMTYPE="MD5">
                    <ns3:FLocat LOCTYPE="OTHER" OTHERLOCTYPE="FILE" ns2:type="simple" ns2:href="1589050_0073.jpg"/>
                </ns3:file>
                <ns3:file ID="IMG_74" SEQ="74" MIMETYPE="image/jpeg" CREATED="2023-09-27T14:39:23.152+02:00" CHECKSUM="75b882402624307350273920b8ff08a1" CHECKSUMTYPE="MD5">
                    <ns3:FLocat LOCTYPE="OTHER" OTHERLOCTYPE="FILE" ns2:type="simple" ns2:href="1589050_0074.jpg"/>
                </ns3:file>
                <ns3:file ID="IMG_75" SEQ="75" MIMETYPE="image/jpeg" CREATED="2023-09-27T14:39:23.663+02:00" CHECKSUM="31941f55ce2dad5ca40911226f154cf2" CHECKSUMTYPE="MD5">
                    <ns3:FLocat LOCTYPE="OTHER" OTHERLOCTYPE="FILE" ns2:type="simple" ns2:href="1589050_0075.jpg"/>
                </ns3:file>
                <ns3:file ID="IMG_76" SEQ="76" MIMETYPE="image/jpeg" CREATED="2023-09-27T14:39:24.081+02:00" CHECKSUM="a15d771ab9bdcd8139222b6c3608b50f" CHECKSUMTYPE="MD5">
                    <ns3:FLocat LOCTYPE="OTHER" OTHERLOCTYPE="FILE" ns2:type="simple" ns2:href="1589050_0076.jpg"/>
                </ns3:file>
            </ns3:fileGrp>
            <ns3:fileGrp ID="PAGEXML">
                <ns3:file ID="PAGEXML_1" SEQ="1" MIMETYPE="application/xml" CREATED="2024-03-30T10:27:11.113+01:00" CHECKSUM="24b72ff2b784760accf2bd27b3a7fba4" CHECKSUMTYPE="MD5">
                    <ns3:FLocat LOCTYPE="OTHER" OTHERLOCTYPE="FILE" ns2:type="simple" ns2:href="page/1589050_0001.xml"/>
                </ns3:file>
                <ns3:file ID="PAGEXML_2" SEQ="2" MIMETYPE="application/xml" CREATED="2024-03-30T10:27:11.561+01:00" CHECKSUM="42d478c9cd1773976c075b35f0117cbb" CHECKSUMTYPE="MD5">
                    <ns3:FLocat LOCTYPE="OTHER" OTHERLOCTYPE="FILE" ns2:type="simple" ns2:href="page/1589050_0002.xml"/>
                </ns3:file>
                <ns3:file ID="PAGEXML_3" SEQ="3" MIMETYPE="application/xml" CREATED="2024-03-30T10:27:11.957+01:00" CHECKSUM="a71284ae84928e93f569f078d066b36a" CHECKSUMTYPE="MD5">
                    <ns3:FLocat LOCTYPE="OTHER" OTHERLOCTYPE="FILE" ns2:type="simple" ns2:href="page/1589050_0003.xml"/>
                </ns3:file>
                <ns3:file ID="PAGEXML_4" SEQ="4" MIMETYPE="application/xml" CREATED="2024-03-30T10:27:12.413+01:00" CHECKSUM="9e759ad49da4dcd63c5e29cfc48276b7" CHECKSUMTYPE="MD5">
                    <ns3:FLocat LOCTYPE="OTHER" OTHERLOCTYPE="FILE" ns2:type="simple" ns2:href="page/1589050_0004.xml"/>
                </ns3:file>
                <ns3:file ID="PAGEXML_5" SEQ="5" MIMETYPE="application/xml" CREATED="2024-03-30T10:27:12.833+01:00" CHECKSUM="6fe567e73cb38124fa017feb0abd9618" CHECKSUMTYPE="MD5">
                    <ns3:FLocat LOCTYPE="OTHER" OTHERLOCTYPE="FILE" ns2:type="simple" ns2:href="page/1589050_0005.xml"/>
                </ns3:file>
                <ns3:file ID="PAGEXML_6" SEQ="6" MIMETYPE="application/xml" CREATED="2024-03-30T10:27:13.717+01:00" CHECKSUM="865f8bc1489575d6bb2d7140c6dd081d" CHECKSUMTYPE="MD5">
                    <ns3:FLocat LOCTYPE="OTHER" OTHERLOCTYPE="FILE" ns2:type="simple" ns2:href="page/1589050_0006.xml"/>
                </ns3:file>
                <ns3:file ID="PAGEXML_7" SEQ="7" MIMETYPE="application/xml" CREATED="2024-03-30T10:27:14.785+01:00" CHECKSUM="6d0fb53c3286203a5fb455fa008042a2" CHECKSUMTYPE="MD5">
                    <ns3:FLocat LOCTYPE="OTHER" OTHERLOCTYPE="FILE" ns2:type="simple" ns2:href="page/1589050_0007.xml"/>
                </ns3:file>
                <ns3:file ID="PAGEXML_8" SEQ="8" MIMETYPE="application/xml" CREATED="2024-03-30T10:27:15.805+01:00" CHECKSUM="c1282e8264a0d990951e6d0cc86026ad" CHECKSUMTYPE="MD5">
                    <ns3:FLocat LOCTYPE="OTHER" OTHERLOCTYPE="FILE" ns2:type="simple" ns2:href="page/1589050_0008.xml"/>
                </ns3:file>
                <ns3:file ID="PAGEXML_9" SEQ="9" MIMETYPE="application/xml" CREATED="2024-03-30T10:27:17.073+01:00" CHECKSUM="d8501a25353dce604ba41dd71d8c09e0" CHECKSUMTYPE="MD5">
                    <ns3:FLocat LOCTYPE="OTHER" OTHERLOCTYPE="FILE" ns2:type="simple" ns2:href="page/1589050_0009.xml"/>
                </ns3:file>
                <ns3:file ID="PAGEXML_10" SEQ="10" MIMETYPE="application/xml" CREATED="2024-03-30T10:27:18.297+01:00" CHECKSUM="d2e3ebdbcae81bb9aa3f9cfd501b16bd" CHECKSUMTYPE="MD5">
                    <ns3:FLocat LOCTYPE="OTHER" OTHERLOCTYPE="FILE" ns2:type="simple" ns2:href="page/1589050_0010.xml"/>
                </ns3:file>
                <ns3:file ID="PAGEXML_11" SEQ="11" MIMETYPE="application/xml" CREATED="2024-03-30T10:27:19.469+01:00" CHECKSUM="e2e9d3a67160aa17c3dfeb354819ef04" CHECKSUMTYPE="MD5">
                    <ns3:FLocat LOCTYPE="OTHER" OTHERLOCTYPE="FILE" ns2:type="simple" ns2:href="page/1589050_0011.xml"/>
                </ns3:file>
                <ns3:file ID="PAGEXML_12" SEQ="12" MIMETYPE="application/xml" CREATED="2024-03-30T10:27:20.617+01:00" CHECKSUM="36bb8675717e8924c3c84f9a5e2dadba" CHECKSUMTYPE="MD5">
                    <ns3:FLocat LOCTYPE="OTHER" OTHERLOCTYPE="FILE" ns2:type="simple" ns2:href="page/1589050_0012.xml"/>
                </ns3:file>
                <ns3:file ID="PAGEXML_13" SEQ="13" MIMETYPE="application/xml" CREATED="2024-03-30T10:27:21.685+01:00" CHECKSUM="d075fb029783c1c75e2a24737adb7f57" CHECKSUMTYPE="MD5">
                    <ns3:FLocat LOCTYPE="OTHER" OTHERLOCTYPE="FILE" ns2:type="simple" ns2:href="page/1589050_0013.xml"/>
                </ns3:file>
                <ns3:file ID="PAGEXML_14" SEQ="14" MIMETYPE="application/xml" CREATED="2024-03-30T10:27:22.773+01:00" CHECKSUM="7f64cac2fa35527aa271e5a112862739" CHECKSUMTYPE="MD5">
                    <ns3:FLocat LOCTYPE="OTHER" OTHERLOCTYPE="FILE" ns2:type="simple" ns2:href="page/1589050_0014.xml"/>
                </ns3:file>
                <ns3:file ID="PAGEXML_15" SEQ="15" MIMETYPE="application/xml" CREATED="2024-03-30T10:27:23.941+01:00" CHECKSUM="b22c13f4410dbe5b5d801f0e73603bd2" CHECKSUMTYPE="MD5">
                    <ns3:FLocat LOCTYPE="OTHER" OTHERLOCTYPE="FILE" ns2:type="simple" ns2:href="page/1589050_0015.xml"/>
                </ns3:file>
                <ns3:file ID="PAGEXML_16" SEQ="16" MIMETYPE="application/xml" CREATED="2024-03-30T10:27:25.057+01:00" CHECKSUM="836821e1328abe8fff1a99d9ebc5d458" CHECKSUMTYPE="MD5">
                    <ns3:FLocat LOCTYPE="OTHER" OTHERLOCTYPE="FILE" ns2:type="simple" ns2:href="page/1589050_0016.xml"/>
                </ns3:file>
                <ns3:file ID="PAGEXML_17" SEQ="17" MIMETYPE="application/xml" CREATED="2024-03-30T10:27:26.253+01:00" CHECKSUM="fcfcbe49595fbc394453fbfa689056d0" CHECKSUMTYPE="MD5">
                    <ns3:FLocat LOCTYPE="OTHER" OTHERLOCTYPE="FILE" ns2:type="simple" ns2:href="page/1589050_0017.xml"/>
                </ns3:file>
                <ns3:file ID="PAGEXML_18" SEQ="18" MIMETYPE="application/xml" CREATED="2024-03-30T10:27:27.373+01:00" CHECKSUM="054ae717143f49112c64377856c836dd" CHECKSUMTYPE="MD5">
                    <ns3:FLocat LOCTYPE="OTHER" OTHERLOCTYPE="FILE" ns2:type="simple" ns2:href="page/1589050_0018.xml"/>
                </ns3:file>
                <ns3:file ID="PAGEXML_19" SEQ="19" MIMETYPE="application/xml" CREATED="2024-03-30T10:27:28.493+01:00" CHECKSUM="63022ce95def0a6d85a1fb9aee6ea45f" CHECKSUMTYPE="MD5">
                    <ns3:FLocat LOCTYPE="OTHER" OTHERLOCTYPE="FILE" ns2:type="simple" ns2:href="page/1589050_0019.xml"/>
                </ns3:file>
                <ns3:file ID="PAGEXML_20" SEQ="20" MIMETYPE="application/xml" CREATED="2024-03-30T10:27:29.557+01:00" CHECKSUM="a6d6edec46dd05cd582e0f82c5892b7e" CHECKSUMTYPE="MD5">
                    <ns3:FLocat LOCTYPE="OTHER" OTHERLOCTYPE="FILE" ns2:type="simple" ns2:href="page/1589050_0020.xml"/>
                </ns3:file>
                <ns3:file ID="PAGEXML_21" SEQ="21" MIMETYPE="application/xml" CREATED="2024-03-30T10:27:30.625+01:00" CHECKSUM="f284c0d72d87cdc93f1d9d788deb9c8a" CHECKSUMTYPE="MD5">
                    <ns3:FLocat LOCTYPE="OTHER" OTHERLOCTYPE="FILE" ns2:type="simple" ns2:href="page/1589050_0021.xml"/>
                </ns3:file>
                <ns3:file ID="PAGEXML_22" SEQ="22" MIMETYPE="application/xml" CREATED="2024-03-30T10:27:31.833+01:00" CHECKSUM="823ba79d91f53d6353a4506d97e1b522" CHECKSUMTYPE="MD5">
                    <ns3:FLocat LOCTYPE="OTHER" OTHERLOCTYPE="FILE" ns2:type="simple" ns2:href="page/1589050_0022.xml"/>
                </ns3:file>
                <ns3:file ID="PAGEXML_23" SEQ="23" MIMETYPE="application/xml" CREATED="2024-03-30T10:27:32.893+01:00" CHECKSUM="a315e8fe122edd51f60e7fba5f32be9e" CHECKSUMTYPE="MD5">
                    <ns3:FLocat LOCTYPE="OTHER" OTHERLOCTYPE="FILE" ns2:type="simple" ns2:href="page/1589050_0023.xml"/>
                </ns3:file>
                <ns3:file ID="PAGEXML_24" SEQ="24" MIMETYPE="application/xml" CREATED="2024-03-30T10:27:33.993+01:00" CHECKSUM="b10c5188b075227bafc3adb92ac901f3" CHECKSUMTYPE="MD5">
                    <ns3:FLocat LOCTYPE="OTHER" OTHERLOCTYPE="FILE" ns2:type="simple" ns2:href="page/1589050_0024.xml"/>
                </ns3:file>
                <ns3:file ID="PAGEXML_25" SEQ="25" MIMETYPE="application/xml" CREATED="2024-03-30T10:27:35.089+01:00" CHECKSUM="e1f8fc6c3738bb20a38145acfc21b575" CHECKSUMTYPE="MD5">
                    <ns3:FLocat LOCTYPE="OTHER" OTHERLOCTYPE="FILE" ns2:type="simple" ns2:href="page/1589050_0025.xml"/>
                </ns3:file>
                <ns3:file ID="PAGEXML_26" SEQ="26" MIMETYPE="application/xml" CREATED="2024-03-30T10:27:36.153+01:00" CHECKSUM="9e01b0c2445063ff23483bf036f6cf1c" CHECKSUMTYPE="MD5">
                    <ns3:FLocat LOCTYPE="OTHER" OTHERLOCTYPE="FILE" ns2:type="simple" ns2:href="page/1589050_0026.xml"/>
                </ns3:file>
                <ns3:file ID="PAGEXML_27" SEQ="27" MIMETYPE="application/xml" CREATED="2024-03-30T10:27:37.253+01:00" CHECKSUM="3e6a4059bdb050dc65ee2999b5fea637" CHECKSUMTYPE="MD5">
                    <ns3:FLocat LOCTYPE="OTHER" OTHERLOCTYPE="FILE" ns2:type="simple" ns2:href="page/1589050_0027.xml"/>
                </ns3:file>
                <ns3:file ID="PAGEXML_28" SEQ="28" MIMETYPE="application/xml" CREATED="2024-03-30T10:27:38.445+01:00" CHECKSUM="8c8b93b09412f2ef7acfe2ccd8eb4e91" CHECKSUMTYPE="MD5">
                    <ns3:FLocat LOCTYPE="OTHER" OTHERLOCTYPE="FILE" ns2:type="simple" ns2:href="page/1589050_0028.xml"/>
                </ns3:file>
                <ns3:file ID="PAGEXML_29" SEQ="29" MIMETYPE="application/xml" CREATED="2024-03-30T10:27:39.453+01:00" CHECKSUM="1bb08d7a6c940ec56c72a3a2549e2629" CHECKSUMTYPE="MD5">
                    <ns3:FLocat LOCTYPE="OTHER" OTHERLOCTYPE="FILE" ns2:type="simple" ns2:href="page/1589050_0029.xml"/>
                </ns3:file>
                <ns3:file ID="PAGEXML_30" SEQ="30" MIMETYPE="application/xml" CREATED="2024-03-30T10:27:40.485+01:00" CHECKSUM="ef2b1985dd0636e2b458a543fd9a37bd" CHECKSUMTYPE="MD5">
                    <ns3:FLocat LOCTYPE="OTHER" OTHERLOCTYPE="FILE" ns2:type="simple" ns2:href="page/1589050_0030.xml"/>
                </ns3:file>
                <ns3:file ID="PAGEXML_31" SEQ="31" MIMETYPE="application/xml" CREATED="2024-03-30T10:27:41.633+01:00" CHECKSUM="d7ebfd592f12249b6c64f9bc5afb8fbf" CHECKSUMTYPE="MD5">
                    <ns3:FLocat LOCTYPE="OTHER" OTHERLOCTYPE="FILE" ns2:type="simple" ns2:href="page/1589050_0031.xml"/>
                </ns3:file>
                <ns3:file ID="PAGEXML_32" SEQ="32" MIMETYPE="application/xml" CREATED="2024-03-30T10:27:42.741+01:00" CHECKSUM="ffa4cdcd5daddf56614255647004196b" CHECKSUMTYPE="MD5">
                    <ns3:FLocat LOCTYPE="OTHER" OTHERLOCTYPE="FILE" ns2:type="simple" ns2:href="page/1589050_0032.xml"/>
                </ns3:file>
                <ns3:file ID="PAGEXML_33" SEQ="33" MIMETYPE="application/xml" CREATED="2024-03-30T10:27:44.273+01:00" CHECKSUM="d5d99276ef383420f285f04d6e297791" CHECKSUMTYPE="MD5">
                    <ns3:FLocat LOCTYPE="OTHER" OTHERLOCTYPE="FILE" ns2:type="simple" ns2:href="page/1589050_0033.xml"/>
                </ns3:file>
                <ns3:file ID="PAGEXML_34" SEQ="34" MIMETYPE="application/xml" CREATED="2024-03-30T10:27:45.769+01:00" CHECKSUM="f4e682cafe8d2940d7716175139ed8ff" CHECKSUMTYPE="MD5">
                    <ns3:FLocat LOCTYPE="OTHER" OTHERLOCTYPE="FILE" ns2:type="simple" ns2:href="page/1589050_0034.xml"/>
                </ns3:file>
                <ns3:file ID="PAGEXML_35" SEQ="35" MIMETYPE="application/xml" CREATED="2024-03-30T10:27:47.173+01:00" CHECKSUM="4e104992ebfa40319317dcb3cd512f77" CHECKSUMTYPE="MD5">
                    <ns3:FLocat LOCTYPE="OTHER" OTHERLOCTYPE="FILE" ns2:type="simple" ns2:href="page/1589050_0035.xml"/>
                </ns3:file>
                <ns3:file ID="PAGEXML_36" SEQ="36" MIMETYPE="application/xml" CREATED="2024-03-30T10:27:48.469+01:00" CHECKSUM="aeb6f1cbcd82459f77390bfce92fd90e" CHECKSUMTYPE="MD5">
                    <ns3:FLocat LOCTYPE="OTHER" OTHERLOCTYPE="FILE" ns2:type="simple" ns2:href="page/1589050_0036.xml"/>
                </ns3:file>
                <ns3:file ID="PAGEXML_37" SEQ="37" MIMETYPE="application/xml" CREATED="2024-03-30T10:27:49.829+01:00" CHECKSUM="476f2e3590282f1d71d88a8e92046a7f" CHECKSUMTYPE="MD5">
                    <ns3:FLocat LOCTYPE="OTHER" OTHERLOCTYPE="FILE" ns2:type="simple" ns2:href="page/1589050_0037.xml"/>
                </ns3:file>
                <ns3:file ID="PAGEXML_38" SEQ="38" MIMETYPE="application/xml" CREATED="2024-03-30T10:27:51.233+01:00" CHECKSUM="196a38790ac81a2bbe6efbf346c09e00" CHECKSUMTYPE="MD5">
                    <ns3:FLocat LOCTYPE="OTHER" OTHERLOCTYPE="FILE" ns2:type="simple" ns2:href="page/1589050_0038.xml"/>
                </ns3:file>
                <ns3:file ID="PAGEXML_39" SEQ="39" MIMETYPE="application/xml" CREATED="2024-03-30T10:27:52.725+01:00" CHECKSUM="68593219181fd00ca98d09b3d5678f79" CHECKSUMTYPE="MD5">
                    <ns3:FLocat LOCTYPE="OTHER" OTHERLOCTYPE="FILE" ns2:type="simple" ns2:href="page/1589050_0039.xml"/>
                </ns3:file>
                <ns3:file ID="PAGEXML_40" SEQ="40" MIMETYPE="application/xml" CREATED="2024-03-30T10:27:54.256+01:00" CHECKSUM="858aeacb0c6cf96b65fa7f7d8c30ef56" CHECKSUMTYPE="MD5">
                    <ns3:FLocat LOCTYPE="OTHER" OTHERLOCTYPE="FILE" ns2:type="simple" ns2:href="page/1589050_0040.xml"/>
                </ns3:file>
                <ns3:file ID="PAGEXML_41" SEQ="41" MIMETYPE="application/xml" CREATED="2024-03-30T10:27:55.168+01:00" CHECKSUM="1873f74e110784028e4fd10dbc4d294d" CHECKSUMTYPE="MD5">
                    <ns3:FLocat LOCTYPE="OTHER" OTHERLOCTYPE="FILE" ns2:type="simple" ns2:href="page/1589050_0041.xml"/>
                </ns3:file>
                <ns3:file ID="PAGEXML_42" SEQ="42" MIMETYPE="application/xml" CREATED="2024-03-30T10:27:56.228+01:00" CHECKSUM="e70980708fea4cff5777ffa705fbd9b7" CHECKSUMTYPE="MD5">
                    <ns3:FLocat LOCTYPE="OTHER" OTHERLOCTYPE="FILE" ns2:type="simple" ns2:href="page/1589050_0042.xml"/>
                </ns3:file>
                <ns3:file ID="PAGEXML_43" SEQ="43" MIMETYPE="application/xml" CREATED="2024-03-30T10:27:57.272+01:00" CHECKSUM="644ede7a5e0df77902b01e2273fe695e" CHECKSUMTYPE="MD5">
                    <ns3:FLocat LOCTYPE="OTHER" OTHERLOCTYPE="FILE" ns2:type="simple" ns2:href="page/1589050_0043.xml"/>
                </ns3:file>
                <ns3:file ID="PAGEXML_44" SEQ="44" MIMETYPE="application/xml" CREATED="2024-03-30T10:27:58.336+01:00" CHECKSUM="d27956955f027db20d6554b6e724018a" CHECKSUMTYPE="MD5">
                    <ns3:FLocat LOCTYPE="OTHER" OTHERLOCTYPE="FILE" ns2:type="simple" ns2:href="page/1589050_0044.xml"/>
                </ns3:file>
                <ns3:file ID="PAGEXML_45" SEQ="45" MIMETYPE="application/xml" CREATED="2024-03-30T10:27:59.456+01:00" CHECKSUM="1125e871b18e33aef314d000a084d586" CHECKSUMTYPE="MD5">
                    <ns3:FLocat LOCTYPE="OTHER" OTHERLOCTYPE="FILE" ns2:type="simple" ns2:href="page/1589050_0045.xml"/>
                </ns3:file>
                <ns3:file ID="PAGEXML_46" SEQ="46" MIMETYPE="application/xml" CREATED="2024-03-30T10:28:00.604+01:00" CHECKSUM="1b94bb92f3741bd0732b2296b6addc69" CHECKSUMTYPE="MD5">
                    <ns3:FLocat LOCTYPE="OTHER" OTHERLOCTYPE="FILE" ns2:type="simple" ns2:href="page/1589050_0046.xml"/>
                </ns3:file>
                <ns3:file ID="PAGEXML_47" SEQ="47" MIMETYPE="application/xml" CREATED="2024-03-30T10:28:01.684+01:00" CHECKSUM="45e19dfe4b00c540e0c852a4402c2efe" CHECKSUMTYPE="MD5">
                    <ns3:FLocat LOCTYPE="OTHER" OTHERLOCTYPE="FILE" ns2:type="simple" ns2:href="page/1589050_0047.xml"/>
                </ns3:file>
                <ns3:file ID="PAGEXML_48" SEQ="48" MIMETYPE="application/xml" CREATED="2024-03-30T10:28:02.752+01:00" CHECKSUM="ed7f46aa2fabff8d13183913eecd717f" CHECKSUMTYPE="MD5">
                    <ns3:FLocat LOCTYPE="OTHER" OTHERLOCTYPE="FILE" ns2:type="simple" ns2:href="page/1589050_0048.xml"/>
                </ns3:file>
                <ns3:file ID="PAGEXML_49" SEQ="49" MIMETYPE="application/xml" CREATED="2024-03-30T10:28:03.776+01:00" CHECKSUM="d4ac76822d5d19cf0ebf3ec18b69a9ab" CHECKSUMTYPE="MD5">
                    <ns3:FLocat LOCTYPE="OTHER" OTHERLOCTYPE="FILE" ns2:type="simple" ns2:href="page/1589050_0049.xml"/>
                </ns3:file>
                <ns3:file ID="PAGEXML_50" SEQ="50" MIMETYPE="application/xml" CREATED="2024-03-30T10:28:04.880+01:00" CHECKSUM="13630f4022c9b73b1e4ac3c56905aa17" CHECKSUMTYPE="MD5">
                    <ns3:FLocat LOCTYPE="OTHER" OTHERLOCTYPE="FILE" ns2:type="simple" ns2:href="page/1589050_0050.xml"/>
                </ns3:file>
                <ns3:file ID="PAGEXML_51" SEQ="51" MIMETYPE="application/xml" CREATED="2024-03-30T10:28:05.948+01:00" CHECKSUM="affb76a62050afcaacbf11cde2e700fc" CHECKSUMTYPE="MD5">
                    <ns3:FLocat LOCTYPE="OTHER" OTHERLOCTYPE="FILE" ns2:type="simple" ns2:href="page/1589050_0051.xml"/>
                </ns3:file>
                <ns3:file ID="PAGEXML_52" SEQ="52" MIMETYPE="application/xml" CREATED="2024-03-30T10:28:06.992+01:00" CHECKSUM="9cd36b4d45e89d97b8fd16261dfb8765" CHECKSUMTYPE="MD5">
                    <ns3:FLocat LOCTYPE="OTHER" OTHERLOCTYPE="FILE" ns2:type="simple" ns2:href="page/1589050_0052.xml"/>
                </ns3:file>
                <ns3:file ID="PAGEXML_53" SEQ="53" MIMETYPE="application/xml" CREATED="2024-03-30T10:28:08.084+01:00" CHECKSUM="a6798ded0cb3324e78e799c12c40276c" CHECKSUMTYPE="MD5">
                    <ns3:FLocat LOCTYPE="OTHER" OTHERLOCTYPE="FILE" ns2:type="simple" ns2:href="page/1589050_0053.xml"/>
                </ns3:file>
                <ns3:file ID="PAGEXML_54" SEQ="54" MIMETYPE="application/xml" CREATED="2024-03-30T10:28:09.116+01:00" CHECKSUM="c775512df421068caef9ef56a2d5e0c6" CHECKSUMTYPE="MD5">
                    <ns3:FLocat LOCTYPE="OTHER" OTHERLOCTYPE="FILE" ns2:type="simple" ns2:href="page/1589050_0054.xml"/>
                </ns3:file>
                <ns3:file ID="PAGEXML_55" SEQ="55" MIMETYPE="application/xml" CREATED="2024-03-30T10:28:10.160+01:00" CHECKSUM="b4ec53543726b1279cc5a51c38b2cb37" CHECKSUMTYPE="MD5">
                    <ns3:FLocat LOCTYPE="OTHER" OTHERLOCTYPE="FILE" ns2:type="simple" ns2:href="page/1589050_0055.xml"/>
                </ns3:file>
                <ns3:file ID="PAGEXML_56" SEQ="56" MIMETYPE="application/xml" CREATED="2024-03-30T10:28:11.292+01:00" CHECKSUM="6f4ede449106c6b8c63a26a0a1f7ef80" CHECKSUMTYPE="MD5">
                    <ns3:FLocat LOCTYPE="OTHER" OTHERLOCTYPE="FILE" ns2:type="simple" ns2:href="page/1589050_0056.xml"/>
                </ns3:file>
                <ns3:file ID="PAGEXML_57" SEQ="57" MIMETYPE="application/xml" CREATED="2024-03-30T10:28:12.404+01:00" CHECKSUM="c79eb2b72ed38205410f51c86daa010f" CHECKSUMTYPE="MD5">
                    <ns3:FLocat LOCTYPE="OTHER" OTHERLOCTYPE="FILE" ns2:type="simple" ns2:href="page/1589050_0057.xml"/>
                </ns3:file>
                <ns3:file ID="PAGEXML_58" SEQ="58" MIMETYPE="application/xml" CREATED="2024-03-30T10:28:13.472+01:00" CHECKSUM="b1250b75ed4e33acf8ba2a06f3e367ad" CHECKSUMTYPE="MD5">
                    <ns3:FLocat LOCTYPE="OTHER" OTHERLOCTYPE="FILE" ns2:type="simple" ns2:href="page/1589050_0058.xml"/>
                </ns3:file>
                <ns3:file ID="PAGEXML_59" SEQ="59" MIMETYPE="application/xml" CREATED="2024-03-30T10:28:14.612+01:00" CHECKSUM="1ccf4f14ac6090779763211333d66cae" CHECKSUMTYPE="MD5">
                    <ns3:FLocat LOCTYPE="OTHER" OTHERLOCTYPE="FILE" ns2:type="simple" ns2:href="page/1589050_0059.xml"/>
                </ns3:file>
                <ns3:file ID="PAGEXML_60" SEQ="60" MIMETYPE="application/xml" CREATED="2024-03-30T10:28:15.724+01:00" CHECKSUM="55e6eabc9dccbe723b91553e97dc9025" CHECKSUMTYPE="MD5">
                    <ns3:FLocat LOCTYPE="OTHER" OTHERLOCTYPE="FILE" ns2:type="simple" ns2:href="page/1589050_0060.xml"/>
                </ns3:file>
                <ns3:file ID="PAGEXML_61" SEQ="61" MIMETYPE="application/xml" CREATED="2024-03-30T10:28:16.780+01:00" CHECKSUM="521af4a0ae4a78ed22363574e2920e28" CHECKSUMTYPE="MD5">
                    <ns3:FLocat LOCTYPE="OTHER" OTHERLOCTYPE="FILE" ns2:type="simple" ns2:href="page/1589050_0061.xml"/>
                </ns3:file>
                <ns3:file ID="PAGEXML_62" SEQ="62" MIMETYPE="application/xml" CREATED="2024-03-30T10:28:17.924+01:00" CHECKSUM="62150bb38f9d1ac241cb5f879fe34c29" CHECKSUMTYPE="MD5">
                    <ns3:FLocat LOCTYPE="OTHER" OTHERLOCTYPE="FILE" ns2:type="simple" ns2:href="page/1589050_0062.xml"/>
                </ns3:file>
                <ns3:file ID="PAGEXML_63" SEQ="63" MIMETYPE="application/xml" CREATED="2024-03-30T10:28:19.020+01:00" CHECKSUM="7408dea2d64087df4ce7e7284598f3fe" CHECKSUMTYPE="MD5">
                    <ns3:FLocat LOCTYPE="OTHER" OTHERLOCTYPE="FILE" ns2:type="simple" ns2:href="page/1589050_0063.xml"/>
                </ns3:file>
                <ns3:file ID="PAGEXML_64" SEQ="64" MIMETYPE="application/xml" CREATED="2024-03-30T10:28:20.036+01:00" CHECKSUM="0b6137669176cfcacca615b5da82ca4e" CHECKSUMTYPE="MD5">
                    <ns3:FLocat LOCTYPE="OTHER" OTHERLOCTYPE="FILE" ns2:type="simple" ns2:href="page/1589050_0064.xml"/>
                </ns3:file>
                <ns3:file ID="PAGEXML_65" SEQ="65" MIMETYPE="application/xml" CREATED="2024-03-30T10:28:21.028+01:00" CHECKSUM="f75c0c6500327f97f6fdbcf4de9dd960" CHECKSUMTYPE="MD5">
                    <ns3:FLocat LOCTYPE="OTHER" OTHERLOCTYPE="FILE" ns2:type="simple" ns2:href="page/1589050_0065.xml"/>
                </ns3:file>
                <ns3:file ID="PAGEXML_66" SEQ="66" MIMETYPE="application/xml" CREATED="2024-03-30T10:28:22.088+01:00" CHECKSUM="aca5819cf3dbae0c9a22c2f3ca26d52e" CHECKSUMTYPE="MD5">
                    <ns3:FLocat LOCTYPE="OTHER" OTHERLOCTYPE="FILE" ns2:type="simple" ns2:href="page/1589050_0066.xml"/>
                </ns3:file>
                <ns3:file ID="PAGEXML_67" SEQ="67" MIMETYPE="application/xml" CREATED="2024-03-30T10:28:23.164+01:00" CHECKSUM="0fbb731c82173069e3e26f3f3adc6539" CHECKSUMTYPE="MD5">
                    <ns3:FLocat LOCTYPE="OTHER" OTHERLOCTYPE="FILE" ns2:type="simple" ns2:href="page/1589050_0067.xml"/>
                </ns3:file>
                <ns3:file ID="PAGEXML_68" SEQ="68" MIMETYPE="application/xml" CREATED="2024-03-30T10:28:24.192+01:00" CHECKSUM="9da15512a180b7c3b6297aa58d250e0c" CHECKSUMTYPE="MD5">
                    <ns3:FLocat LOCTYPE="OTHER" OTHERLOCTYPE="FILE" ns2:type="simple" ns2:href="page/1589050_0068.xml"/>
                </ns3:file>
                <ns3:file ID="PAGEXML_69" SEQ="69" MIMETYPE="application/xml" CREATED="2024-03-30T10:28:25.316+01:00" CHECKSUM="d3a0f678db7ef087306c3753ff338195" CHECKSUMTYPE="MD5">
                    <ns3:FLocat LOCTYPE="OTHER" OTHERLOCTYPE="FILE" ns2:type="simple" ns2:href="page/1589050_0069.xml"/>
                </ns3:file>
                <ns3:file ID="PAGEXML_70" SEQ="70" MIMETYPE="application/xml" CREATED="2024-03-30T10:28:26.312+01:00" CHECKSUM="d987819757b8c297e5af592276aaeb81" CHECKSUMTYPE="MD5">
                    <ns3:FLocat LOCTYPE="OTHER" OTHERLOCTYPE="FILE" ns2:type="simple" ns2:href="page/1589050_0070.xml"/>
                </ns3:file>
                <ns3:file ID="PAGEXML_71" SEQ="71" MIMETYPE="application/xml" CREATED="2024-03-30T10:28:27.284+01:00" CHECKSUM="26983a7d95e1a6ddc9fa9a809bf127f0" CHECKSUMTYPE="MD5">
                    <ns3:FLocat LOCTYPE="OTHER" OTHERLOCTYPE="FILE" ns2:type="simple" ns2:href="page/1589050_0071.xml"/>
                </ns3:file>
                <ns3:file ID="PAGEXML_72" SEQ="72" MIMETYPE="application/xml" CREATED="2024-03-30T10:28:28.360+01:00" CHECKSUM="b7266a7d297732a11bb962f2e95bd438" CHECKSUMTYPE="MD5">
                    <ns3:FLocat LOCTYPE="OTHER" OTHERLOCTYPE="FILE" ns2:type="simple" ns2:href="page/1589050_0072.xml"/>
                </ns3:file>
                <ns3:file ID="PAGEXML_73" SEQ="73" MIMETYPE="application/xml" CREATED="2024-03-30T10:28:29.440+01:00" CHECKSUM="eca907dc198f488c0d230a39310e9da4" CHECKSUMTYPE="MD5">
                    <ns3:FLocat LOCTYPE="OTHER" OTHERLOCTYPE="FILE" ns2:type="simple" ns2:href="page/1589050_0073.xml"/>
                </ns3:file>
                <ns3:file ID="PAGEXML_74" SEQ="74" MIMETYPE="application/xml" CREATED="2024-03-30T10:28:30.456+01:00" CHECKSUM="15be2e7023524c280a98252aa48debdc" CHECKSUMTYPE="MD5">
                    <ns3:FLocat LOCTYPE="OTHER" OTHERLOCTYPE="FILE" ns2:type="simple" ns2:href="page/1589050_0074.xml"/>
                </ns3:file>
                <ns3:file ID="PAGEXML_75" SEQ="75" MIMETYPE="application/xml" CREATED="2024-03-30T10:28:31.516+01:00" CHECKSUM="eb8979c3db208fd6e831bd098010796c" CHECKSUMTYPE="MD5">
                    <ns3:FLocat LOCTYPE="OTHER" OTHERLOCTYPE="FILE" ns2:type="simple" ns2:href="page/1589050_0075.xml"/>
                </ns3:file>
                <ns3:file ID="PAGEXML_76" SEQ="76" MIMETYPE="application/xml" CREATED="2024-03-30T10:28:32.560+01:00" CHECKSUM="d805593f54b16b221804139d1d46dbc2" CHECKSUMTYPE="MD5">
                    <ns3:FLocat LOCTYPE="OTHER" OTHERLOCTYPE="FILE" ns2:type="simple" ns2:href="page/1589050_0076.xml"/>
                </ns3:file>
            </ns3:fileGrp>
        </ns3:fileGrp>
    </ns3:fileSec>
    <ns3:structMap ID="TRP_STRUCTMAP" TYPE="MANUSCRIPT">
        <ns3:div ID="TRP_DOC_DIV" ADMID="MD_ORIG">
            <ns3:div ID="PAGE_1" ORDER="1" TYPE="SINGLE_PAGE">
                <ns3:fptr>
                    <ns3:area FILEID="IMG_1"/>
                </ns3:fptr>
                <ns3:fptr>
                    <ns3:area FILEID="PAGEXML_1"/>
                </ns3:fptr>
            </ns3:div>
            <ns3:div ID="PAGE_2" ORDER="2" TYPE="SINGLE_PAGE">
                <ns3:fptr>
                    <ns3:area FILEID="IMG_2"/>
                </ns3:fptr>
                <ns3:fptr>
                    <ns3:area FILEID="PAGEXML_2"/>
                </ns3:fptr>
            </ns3:div>
            <ns3:div ID="PAGE_3" ORDER="3" TYPE="SINGLE_PAGE">
                <ns3:fptr>
                    <ns3:area FILEID="IMG_3"/>
                </ns3:fptr>
                <ns3:fptr>
                    <ns3:area FILEID="PAGEXML_3"/>
                </ns3:fptr>
            </ns3:div>
            <ns3:div ID="PAGE_4" ORDER="4" TYPE="SINGLE_PAGE">
                <ns3:fptr>
                    <ns3:area FILEID="IMG_4"/>
                </ns3:fptr>
                <ns3:fptr>
                    <ns3:area FILEID="PAGEXML_4"/>
                </ns3:fptr>
            </ns3:div>
            <ns3:div ID="PAGE_5" ORDER="5" TYPE="SINGLE_PAGE">
                <ns3:fptr>
                    <ns3:area FILEID="IMG_5"/>
                </ns3:fptr>
                <ns3:fptr>
                    <ns3:area FILEID="PAGEXML_5"/>
                </ns3:fptr>
            </ns3:div>
            <ns3:div ID="PAGE_6" ORDER="6" TYPE="SINGLE_PAGE">
                <ns3:fptr>
                    <ns3:area FILEID="IMG_6"/>
                </ns3:fptr>
                <ns3:fptr>
                    <ns3:area FILEID="PAGEXML_6"/>
                </ns3:fptr>
            </ns3:div>
            <ns3:div ID="PAGE_7" ORDER="7" TYPE="SINGLE_PAGE">
                <ns3:fptr>
                    <ns3:area FILEID="IMG_7"/>
                </ns3:fptr>
                <ns3:fptr>
                    <ns3:area FILEID="PAGEXML_7"/>
                </ns3:fptr>
            </ns3:div>
            <ns3:div ID="PAGE_8" ORDER="8" TYPE="SINGLE_PAGE">
                <ns3:fptr>
                    <ns3:area FILEID="IMG_8"/>
                </ns3:fptr>
                <ns3:fptr>
                    <ns3:area FILEID="PAGEXML_8"/>
                </ns3:fptr>
            </ns3:div>
            <ns3:div ID="PAGE_9" ORDER="9" TYPE="SINGLE_PAGE">
                <ns3:fptr>
                    <ns3:area FILEID="IMG_9"/>
                </ns3:fptr>
                <ns3:fptr>
                    <ns3:area FILEID="PAGEXML_9"/>
                </ns3:fptr>
            </ns3:div>
            <ns3:div ID="PAGE_10" ORDER="10" TYPE="SINGLE_PAGE">
                <ns3:fptr>
                    <ns3:area FILEID="IMG_10"/>
                </ns3:fptr>
                <ns3:fptr>
                    <ns3:area FILEID="PAGEXML_10"/>
                </ns3:fptr>
            </ns3:div>
            <ns3:div ID="PAGE_11" ORDER="11" TYPE="SINGLE_PAGE">
                <ns3:fptr>
                    <ns3:area FILEID="IMG_11"/>
                </ns3:fptr>
                <ns3:fptr>
                    <ns3:area FILEID="PAGEXML_11"/>
                </ns3:fptr>
            </ns3:div>
            <ns3:div ID="PAGE_12" ORDER="12" TYPE="SINGLE_PAGE">
                <ns3:fptr>
                    <ns3:area FILEID="IMG_12"/>
                </ns3:fptr>
                <ns3:fptr>
                    <ns3:area FILEID="PAGEXML_12"/>
                </ns3:fptr>
            </ns3:div>
            <ns3:div ID="PAGE_13" ORDER="13" TYPE="SINGLE_PAGE">
                <ns3:fptr>
                    <ns3:area FILEID="IMG_13"/>
                </ns3:fptr>
                <ns3:fptr>
                    <ns3:area FILEID="PAGEXML_13"/>
                </ns3:fptr>
            </ns3:div>
            <ns3:div ID="PAGE_14" ORDER="14" TYPE="SINGLE_PAGE">
                <ns3:fptr>
                    <ns3:area FILEID="IMG_14"/>
                </ns3:fptr>
                <ns3:fptr>
                    <ns3:area FILEID="PAGEXML_14"/>
                </ns3:fptr>
            </ns3:div>
            <ns3:div ID="PAGE_15" ORDER="15" TYPE="SINGLE_PAGE">
                <ns3:fptr>
                    <ns3:area FILEID="IMG_15"/>
                </ns3:fptr>
                <ns3:fptr>
                    <ns3:area FILEID="PAGEXML_15"/>
                </ns3:fptr>
            </ns3:div>
            <ns3:div ID="PAGE_16" ORDER="16" TYPE="SINGLE_PAGE">
                <ns3:fptr>
                    <ns3:area FILEID="IMG_16"/>
                </ns3:fptr>
                <ns3:fptr>
                    <ns3:area FILEID="PAGEXML_16"/>
                </ns3:fptr>
            </ns3:div>
            <ns3:div ID="PAGE_17" ORDER="17" TYPE="SINGLE_PAGE">
                <ns3:fptr>
                    <ns3:area FILEID="IMG_17"/>
                </ns3:fptr>
                <ns3:fptr>
                    <ns3:area FILEID="PAGEXML_17"/>
                </ns3:fptr>
            </ns3:div>
            <ns3:div ID="PAGE_18" ORDER="18" TYPE="SINGLE_PAGE">
                <ns3:fptr>
                    <ns3:area FILEID="IMG_18"/>
                </ns3:fptr>
                <ns3:fptr>
                    <ns3:area FILEID="PAGEXML_18"/>
                </ns3:fptr>
            </ns3:div>
            <ns3:div ID="PAGE_19" ORDER="19" TYPE="SINGLE_PAGE">
                <ns3:fptr>
                    <ns3:area FILEID="IMG_19"/>
                </ns3:fptr>
                <ns3:fptr>
                    <ns3:area FILEID="PAGEXML_19"/>
                </ns3:fptr>
            </ns3:div>
            <ns3:div ID="PAGE_20" ORDER="20" TYPE="SINGLE_PAGE">
                <ns3:fptr>
                    <ns3:area FILEID="IMG_20"/>
                </ns3:fptr>
                <ns3:fptr>
                    <ns3:area FILEID="PAGEXML_20"/>
                </ns3:fptr>
            </ns3:div>
            <ns3:div ID="PAGE_21" ORDER="21" TYPE="SINGLE_PAGE">
                <ns3:fptr>
                    <ns3:area FILEID="IMG_21"/>
                </ns3:fptr>
                <ns3:fptr>
                    <ns3:area FILEID="PAGEXML_21"/>
                </ns3:fptr>
            </ns3:div>
            <ns3:div ID="PAGE_22" ORDER="22" TYPE="SINGLE_PAGE">
                <ns3:fptr>
                    <ns3:area FILEID="IMG_22"/>
                </ns3:fptr>
                <ns3:fptr>
                    <ns3:area FILEID="PAGEXML_22"/>
                </ns3:fptr>
            </ns3:div>
            <ns3:div ID="PAGE_23" ORDER="23" TYPE="SINGLE_PAGE">
                <ns3:fptr>
                    <ns3:area FILEID="IMG_23"/>
                </ns3:fptr>
                <ns3:fptr>
                    <ns3:area FILEID="PAGEXML_23"/>
                </ns3:fptr>
            </ns3:div>
            <ns3:div ID="PAGE_24" ORDER="24" TYPE="SINGLE_PAGE">
                <ns3:fptr>
                    <ns3:area FILEID="IMG_24"/>
                </ns3:fptr>
                <ns3:fptr>
                    <ns3:area FILEID="PAGEXML_24"/>
                </ns3:fptr>
            </ns3:div>
            <ns3:div ID="PAGE_25" ORDER="25" TYPE="SINGLE_PAGE">
                <ns3:fptr>
                    <ns3:area FILEID="IMG_25"/>
                </ns3:fptr>
                <ns3:fptr>
                    <ns3:area FILEID="PAGEXML_25"/>
                </ns3:fptr>
            </ns3:div>
            <ns3:div ID="PAGE_26" ORDER="26" TYPE="SINGLE_PAGE">
                <ns3:fptr>
                    <ns3:area FILEID="IMG_26"/>
                </ns3:fptr>
                <ns3:fptr>
                    <ns3:area FILEID="PAGEXML_26"/>
                </ns3:fptr>
            </ns3:div>
            <ns3:div ID="PAGE_27" ORDER="27" TYPE="SINGLE_PAGE">
                <ns3:fptr>
                    <ns3:area FILEID="IMG_27"/>
                </ns3:fptr>
                <ns3:fptr>
                    <ns3:area FILEID="PAGEXML_27"/>
                </ns3:fptr>
            </ns3:div>
            <ns3:div ID="PAGE_28" ORDER="28" TYPE="SINGLE_PAGE">
                <ns3:fptr>
                    <ns3:area FILEID="IMG_28"/>
                </ns3:fptr>
                <ns3:fptr>
                    <ns3:area FILEID="PAGEXML_28"/>
                </ns3:fptr>
            </ns3:div>
            <ns3:div ID="PAGE_29" ORDER="29" TYPE="SINGLE_PAGE">
                <ns3:fptr>
                    <ns3:area FILEID="IMG_29"/>
                </ns3:fptr>
                <ns3:fptr>
                    <ns3:area FILEID="PAGEXML_29"/>
                </ns3:fptr>
            </ns3:div>
            <ns3:div ID="PAGE_30" ORDER="30" TYPE="SINGLE_PAGE">
                <ns3:fptr>
                    <ns3:area FILEID="IMG_30"/>
                </ns3:fptr>
                <ns3:fptr>
                    <ns3:area FILEID="PAGEXML_30"/>
                </ns3:fptr>
            </ns3:div>
            <ns3:div ID="PAGE_31" ORDER="31" TYPE="SINGLE_PAGE">
                <ns3:fptr>
                    <ns3:area FILEID="IMG_31"/>
                </ns3:fptr>
                <ns3:fptr>
                    <ns3:area FILEID="PAGEXML_31"/>
                </ns3:fptr>
            </ns3:div>
            <ns3:div ID="PAGE_32" ORDER="32" TYPE="SINGLE_PAGE">
                <ns3:fptr>
                    <ns3:area FILEID="IMG_32"/>
                </ns3:fptr>
                <ns3:fptr>
                    <ns3:area FILEID="PAGEXML_32"/>
                </ns3:fptr>
            </ns3:div>
            <ns3:div ID="PAGE_33" ORDER="33" TYPE="SINGLE_PAGE">
                <ns3:fptr>
                    <ns3:area FILEID="IMG_33"/>
                </ns3:fptr>
                <ns3:fptr>
                    <ns3:area FILEID="PAGEXML_33"/>
                </ns3:fptr>
            </ns3:div>
            <ns3:div ID="PAGE_34" ORDER="34" TYPE="SINGLE_PAGE">
                <ns3:fptr>
                    <ns3:area FILEID="IMG_34"/>
                </ns3:fptr>
                <ns3:fptr>
                    <ns3:area FILEID="PAGEXML_34"/>
                </ns3:fptr>
            </ns3:div>
            <ns3:div ID="PAGE_35" ORDER="35" TYPE="SINGLE_PAGE">
                <ns3:fptr>
                    <ns3:area FILEID="IMG_35"/>
                </ns3:fptr>
                <ns3:fptr>
                    <ns3:area FILEID="PAGEXML_35"/>
                </ns3:fptr>
            </ns3:div>
            <ns3:div ID="PAGE_36" ORDER="36" TYPE="SINGLE_PAGE">
                <ns3:fptr>
                    <ns3:area FILEID="IMG_36"/>
                </ns3:fptr>
                <ns3:fptr>
                    <ns3:area FILEID="PAGEXML_36"/>
                </ns3:fptr>
            </ns3:div>
            <ns3:div ID="PAGE_37" ORDER="37" TYPE="SINGLE_PAGE">
                <ns3:fptr>
                    <ns3:area FILEID="IMG_37"/>
                </ns3:fptr>
                <ns3:fptr>
                    <ns3:area FILEID="PAGEXML_37"/>
                </ns3:fptr>
            </ns3:div>
            <ns3:div ID="PAGE_38" ORDER="38" TYPE="SINGLE_PAGE">
                <ns3:fptr>
                    <ns3:area FILEID="IMG_38"/>
                </ns3:fptr>
                <ns3:fptr>
                    <ns3:area FILEID="PAGEXML_38"/>
                </ns3:fptr>
            </ns3:div>
            <ns3:div ID="PAGE_39" ORDER="39" TYPE="SINGLE_PAGE">
                <ns3:fptr>
                    <ns3:area FILEID="IMG_39"/>
                </ns3:fptr>
                <ns3:fptr>
                    <ns3:area FILEID="PAGEXML_39"/>
                </ns3:fptr>
            </ns3:div>
            <ns3:div ID="PAGE_40" ORDER="40" TYPE="SINGLE_PAGE">
                <ns3:fptr>
                    <ns3:area FILEID="IMG_40"/>
                </ns3:fptr>
                <ns3:fptr>
                    <ns3:area FILEID="PAGEXML_40"/>
                </ns3:fptr>
            </ns3:div>
            <ns3:div ID="PAGE_41" ORDER="41" TYPE="SINGLE_PAGE">
                <ns3:fptr>
                    <ns3:area FILEID="IMG_41"/>
                </ns3:fptr>
                <ns3:fptr>
                    <ns3:area FILEID="PAGEXML_41"/>
                </ns3:fptr>
            </ns3:div>
            <ns3:div ID="PAGE_42" ORDER="42" TYPE="SINGLE_PAGE">
                <ns3:fptr>
                    <ns3:area FILEID="IMG_42"/>
                </ns3:fptr>
                <ns3:fptr>
                    <ns3:area FILEID="PAGEXML_42"/>
                </ns3:fptr>
            </ns3:div>
            <ns3:div ID="PAGE_43" ORDER="43" TYPE="SINGLE_PAGE">
                <ns3:fptr>
                    <ns3:area FILEID="IMG_43"/>
                </ns3:fptr>
                <ns3:fptr>
                    <ns3:area FILEID="PAGEXML_43"/>
                </ns3:fptr>
            </ns3:div>
            <ns3:div ID="PAGE_44" ORDER="44" TYPE="SINGLE_PAGE">
                <ns3:fptr>
                    <ns3:area FILEID="IMG_44"/>
                </ns3:fptr>
                <ns3:fptr>
                    <ns3:area FILEID="PAGEXML_44"/>
                </ns3:fptr>
            </ns3:div>
            <ns3:div ID="PAGE_45" ORDER="45" TYPE="SINGLE_PAGE">
                <ns3:fptr>
                    <ns3:area FILEID="IMG_45"/>
                </ns3:fptr>
                <ns3:fptr>
                    <ns3:area FILEID="PAGEXML_45"/>
                </ns3:fptr>
            </ns3:div>
            <ns3:div ID="PAGE_46" ORDER="46" TYPE="SINGLE_PAGE">
                <ns3:fptr>
                    <ns3:area FILEID="IMG_46"/>
                </ns3:fptr>
                <ns3:fptr>
                    <ns3:area FILEID="PAGEXML_46"/>
                </ns3:fptr>
            </ns3:div>
            <ns3:div ID="PAGE_47" ORDER="47" TYPE="SINGLE_PAGE">
                <ns3:fptr>
                    <ns3:area FILEID="IMG_47"/>
                </ns3:fptr>
                <ns3:fptr>
                    <ns3:area FILEID="PAGEXML_47"/>
                </ns3:fptr>
            </ns3:div>
            <ns3:div ID="PAGE_48" ORDER="48" TYPE="SINGLE_PAGE">
                <ns3:fptr>
                    <ns3:area FILEID="IMG_48"/>
                </ns3:fptr>
                <ns3:fptr>
                    <ns3:area FILEID="PAGEXML_48"/>
                </ns3:fptr>
            </ns3:div>
            <ns3:div ID="PAGE_49" ORDER="49" TYPE="SINGLE_PAGE">
                <ns3:fptr>
                    <ns3:area FILEID="IMG_49"/>
                </ns3:fptr>
                <ns3:fptr>
                    <ns3:area FILEID="PAGEXML_49"/>
                </ns3:fptr>
            </ns3:div>
            <ns3:div ID="PAGE_50" ORDER="50" TYPE="SINGLE_PAGE">
                <ns3:fptr>
                    <ns3:area FILEID="IMG_50"/>
                </ns3:fptr>
                <ns3:fptr>
                    <ns3:area FILEID="PAGEXML_50"/>
                </ns3:fptr>
            </ns3:div>
            <ns3:div ID="PAGE_51" ORDER="51" TYPE="SINGLE_PAGE">
                <ns3:fptr>
                    <ns3:area FILEID="IMG_51"/>
                </ns3:fptr>
                <ns3:fptr>
                    <ns3:area FILEID="PAGEXML_51"/>
                </ns3:fptr>
            </ns3:div>
            <ns3:div ID="PAGE_52" ORDER="52" TYPE="SINGLE_PAGE">
                <ns3:fptr>
                    <ns3:area FILEID="IMG_52"/>
                </ns3:fptr>
                <ns3:fptr>
                    <ns3:area FILEID="PAGEXML_52"/>
                </ns3:fptr>
            </ns3:div>
            <ns3:div ID="PAGE_53" ORDER="53" TYPE="SINGLE_PAGE">
                <ns3:fptr>
                    <ns3:area FILEID="IMG_53"/>
                </ns3:fptr>
                <ns3:fptr>
                    <ns3:area FILEID="PAGEXML_53"/>
                </ns3:fptr>
            </ns3:div>
            <ns3:div ID="PAGE_54" ORDER="54" TYPE="SINGLE_PAGE">
                <ns3:fptr>
                    <ns3:area FILEID="IMG_54"/>
                </ns3:fptr>
                <ns3:fptr>
                    <ns3:area FILEID="PAGEXML_54"/>
                </ns3:fptr>
            </ns3:div>
            <ns3:div ID="PAGE_55" ORDER="55" TYPE="SINGLE_PAGE">
                <ns3:fptr>
                    <ns3:area FILEID="IMG_55"/>
                </ns3:fptr>
                <ns3:fptr>
                    <ns3:area FILEID="PAGEXML_55"/>
                </ns3:fptr>
            </ns3:div>
            <ns3:div ID="PAGE_56" ORDER="56" TYPE="SINGLE_PAGE">
                <ns3:fptr>
                    <ns3:area FILEID="IMG_56"/>
                </ns3:fptr>
                <ns3:fptr>
                    <ns3:area FILEID="PAGEXML_56"/>
                </ns3:fptr>
            </ns3:div>
            <ns3:div ID="PAGE_57" ORDER="57" TYPE="SINGLE_PAGE">
                <ns3:fptr>
                    <ns3:area FILEID="IMG_57"/>
                </ns3:fptr>
                <ns3:fptr>
                    <ns3:area FILEID="PAGEXML_57"/>
                </ns3:fptr>
            </ns3:div>
            <ns3:div ID="PAGE_58" ORDER="58" TYPE="SINGLE_PAGE">
                <ns3:fptr>
                    <ns3:area FILEID="IMG_58"/>
                </ns3:fptr>
                <ns3:fptr>
                    <ns3:area FILEID="PAGEXML_58"/>
                </ns3:fptr>
            </ns3:div>
            <ns3:div ID="PAGE_59" ORDER="59" TYPE="SINGLE_PAGE">
                <ns3:fptr>
                    <ns3:area FILEID="IMG_59"/>
                </ns3:fptr>
                <ns3:fptr>
                    <ns3:area FILEID="PAGEXML_59"/>
                </ns3:fptr>
            </ns3:div>
            <ns3:div ID="PAGE_60" ORDER="60" TYPE="SINGLE_PAGE">
                <ns3:fptr>
                    <ns3:area FILEID="IMG_60"/>
                </ns3:fptr>
                <ns3:fptr>
                    <ns3:area FILEID="PAGEXML_60"/>
                </ns3:fptr>
            </ns3:div>
            <ns3:div ID="PAGE_61" ORDER="61" TYPE="SINGLE_PAGE">
                <ns3:fptr>
                    <ns3:area FILEID="IMG_61"/>
                </ns3:fptr>
                <ns3:fptr>
                    <ns3:area FILEID="PAGEXML_61"/>
                </ns3:fptr>
            </ns3:div>
            <ns3:div ID="PAGE_62" ORDER="62" TYPE="SINGLE_PAGE">
                <ns3:fptr>
                    <ns3:area FILEID="IMG_62"/>
                </ns3:fptr>
                <ns3:fptr>
                    <ns3:area FILEID="PAGEXML_62"/>
                </ns3:fptr>
            </ns3:div>
            <ns3:div ID="PAGE_63" ORDER="63" TYPE="SINGLE_PAGE">
                <ns3:fptr>
                    <ns3:area FILEID="IMG_63"/>
                </ns3:fptr>
                <ns3:fptr>
                    <ns3:area FILEID="PAGEXML_63"/>
                </ns3:fptr>
            </ns3:div>
            <ns3:div ID="PAGE_64" ORDER="64" TYPE="SINGLE_PAGE">
                <ns3:fptr>
                    <ns3:area FILEID="IMG_64"/>
                </ns3:fptr>
                <ns3:fptr>
                    <ns3:area FILEID="PAGEXML_64"/>
                </ns3:fptr>
            </ns3:div>
            <ns3:div ID="PAGE_65" ORDER="65" TYPE="SINGLE_PAGE">
                <ns3:fptr>
                    <ns3:area FILEID="IMG_65"/>
                </ns3:fptr>
                <ns3:fptr>
                    <ns3:area FILEID="PAGEXML_65"/>
                </ns3:fptr>
            </ns3:div>
            <ns3:div ID="PAGE_66" ORDER="66" TYPE="SINGLE_PAGE">
                <ns3:fptr>
                    <ns3:area FILEID="IMG_66"/>
                </ns3:fptr>
                <ns3:fptr>
                    <ns3:area FILEID="PAGEXML_66"/>
                </ns3:fptr>
            </ns3:div>
            <ns3:div ID="PAGE_67" ORDER="67" TYPE="SINGLE_PAGE">
                <ns3:fptr>
                    <ns3:area FILEID="IMG_67"/>
                </ns3:fptr>
                <ns3:fptr>
                    <ns3:area FILEID="PAGEXML_67"/>
                </ns3:fptr>
            </ns3:div>
            <ns3:div ID="PAGE_68" ORDER="68" TYPE="SINGLE_PAGE">
                <ns3:fptr>
                    <ns3:area FILEID="IMG_68"/>
                </ns3:fptr>
                <ns3:fptr>
                    <ns3:area FILEID="PAGEXML_68"/>
                </ns3:fptr>
            </ns3:div>
            <ns3:div ID="PAGE_69" ORDER="69" TYPE="SINGLE_PAGE">
                <ns3:fptr>
                    <ns3:area FILEID="IMG_69"/>
                </ns3:fptr>
                <ns3:fptr>
                    <ns3:area FILEID="PAGEXML_69"/>
                </ns3:fptr>
            </ns3:div>
            <ns3:div ID="PAGE_70" ORDER="70" TYPE="SINGLE_PAGE">
                <ns3:fptr>
                    <ns3:area FILEID="IMG_70"/>
                </ns3:fptr>
                <ns3:fptr>
                    <ns3:area FILEID="PAGEXML_70"/>
                </ns3:fptr>
            </ns3:div>
            <ns3:div ID="PAGE_71" ORDER="71" TYPE="SINGLE_PAGE">
                <ns3:fptr>
                    <ns3:area FILEID="IMG_71"/>
                </ns3:fptr>
                <ns3:fptr>
                    <ns3:area FILEID="PAGEXML_71"/>
                </ns3:fptr>
            </ns3:div>
            <ns3:div ID="PAGE_72" ORDER="72" TYPE="SINGLE_PAGE">
                <ns3:fptr>
                    <ns3:area FILEID="IMG_72"/>
                </ns3:fptr>
                <ns3:fptr>
                    <ns3:area FILEID="PAGEXML_72"/>
                </ns3:fptr>
            </ns3:div>
            <ns3:div ID="PAGE_73" ORDER="73" TYPE="SINGLE_PAGE">
                <ns3:fptr>
                    <ns3:area FILEID="IMG_73"/>
                </ns3:fptr>
                <ns3:fptr>
                    <ns3:area FILEID="PAGEXML_73"/>
                </ns3:fptr>
            </ns3:div>
            <ns3:div ID="PAGE_74" ORDER="74" TYPE="SINGLE_PAGE">
                <ns3:fptr>
                    <ns3:area FILEID="IMG_74"/>
                </ns3:fptr>
                <ns3:fptr>
                    <ns3:area FILEID="PAGEXML_74"/>
                </ns3:fptr>
            </ns3:div>
            <ns3:div ID="PAGE_75" ORDER="75" TYPE="SINGLE_PAGE">
                <ns3:fptr>
                    <ns3:area FILEID="IMG_75"/>
                </ns3:fptr>
                <ns3:fptr>
                    <ns3:area FILEID="PAGEXML_75"/>
                </ns3:fptr>
            </ns3:div>
            <ns3:div ID="PAGE_76" ORDER="76" TYPE="SINGLE_PAGE">
                <ns3:fptr>
                    <ns3:area FILEID="IMG_76"/>
                </ns3:fptr>
                <ns3:fptr>
                    <ns3:area FILEID="PAGEXML_76"/>
                </ns3:fptr>
            </ns3:div>
        </ns3:div>
    </ns3:structMap>
</ns3:mets>
