<?xml version="1.0" encoding="UTF-8" standalone="yes"?>
<ns3:mets xmlns:ns2="http://www.w3.org/1999/xlink" xmlns:ns3="http://www.loc.gov/METS/" xmlns:xsi="http://www.w3.org/2001/XMLSchema-instance" OBJID="1416473" LABEL="B0082b Reinhardt, Max (Holländer u.a.) Deutsches Theater u.a. 1920–1928" PROFILE="TRP_V1" xsi:schemaLocation="http://www.loc.gov/METS/ http://www.loc.gov/standards/mets/mets.xsd">
    <ns3:metsHdr CREATEDATE="2024-03-30T21:19:39.676+01:00" LASTMODDATE="2024-03-30T21:19:39.676+01:00" RECORDSTATUS="SUBMITTED">
        <ns3:agent ROLE="CREATOR" TYPE="ORGANIZATION">
            <ns3:name>UIBK</ns3:name>
            <ns3:note>This METS file was generated by Transkribus</ns3:note>
        </ns3:agent>
    </ns3:metsHdr>
    <ns3:amdSec ID="SOURCE">
        <ns3:sourceMD ID="MD_ORIG">
            <ns3:mdWrap ID="TRP_DOC_MD" MDTYPE="OTHER">
                <ns3:xmlData>
                    <trpDocMetadata>
                        <docId>1416473</docId>
                        <title>B0082b Reinhardt, Max (Holländer u.a.) Deutsches Theater u.a. 1920–1928</title>
                        <uploadTimestamp>1682971571849</uploadTimestamp>
                        <uploader>martin.anton.mueller@oeaw.ac.at</uploader>
                        <uploaderId>40391</uploaderId>
                        <nrOfPages>71</nrOfPages>
                        <pageId>54948048</pageId>
                        <url>https://files.transkribus.eu/Get?fileType=view&amp;id=RCIQZOONSERFZEVJJCFWBIDX</url>
                        <thumbUrl>https://files.transkribus.eu/Get?fileType=thumb&amp;id=RCIQZOONSERFZEVJJCFWBIDX</thumbUrl>
                        <status>0</status>
                        <fimgStoreColl>TrpDoc_DEA_1416473</fimgStoreColl>
                        <localFolder>/mnt/transkribus/export/TRP_EXPORT_3710928009986880300/1416473/B0082b_Reinhardt,_Max_(Holländer_u_a_)_Deutsches_Theater_u_a__1920–1928</localFolder>
                        <origDocId>0</origDocId>
                        <collectionList>
                            <colList>
<colId>200901</colId>
<colName>schnitzler-mikrofilme</colName>
<description>created by martin.anton.mueller@oeaw.ac.at</description>
<crowdsourcing>false</crowdsourcing>
<elearning>false</elearning>
<nrOfDocuments>0</nrOfDocuments>
                            </colList>
                        </collectionList>
                        <mainColId>200901</mainColId>
                    </trpDocMetadata>
                </ns3:xmlData>
            </ns3:mdWrap>
        </ns3:sourceMD>
    </ns3:amdSec>
    <ns3:fileSec>
        <ns3:fileGrp ID="MASTER">
            <ns3:fileGrp ID="IMG">
                <ns3:file ID="IMG_1" SEQ="1" MIMETYPE="image/jpeg" CREATED="2023-05-01T22:06:12.544+02:00" CHECKSUM="5df599aafc3aca03cec019219fd3c9de" CHECKSUMTYPE="MD5">
                    <ns3:FLocat LOCTYPE="OTHER" OTHERLOCTYPE="FILE" ns2:type="simple" ns2:href="1416473_0001.jpg"/>
                </ns3:file>
                <ns3:file ID="IMG_2" SEQ="2" MIMETYPE="image/jpeg" CREATED="2023-05-01T22:06:13.332+02:00" CHECKSUM="b00192131c86ca427975d96cb08f0cfb" CHECKSUMTYPE="MD5">
                    <ns3:FLocat LOCTYPE="OTHER" OTHERLOCTYPE="FILE" ns2:type="simple" ns2:href="1416473_0002.jpg"/>
                </ns3:file>
                <ns3:file ID="IMG_3" SEQ="3" MIMETYPE="image/jpeg" CREATED="2023-05-01T22:06:14.166+02:00" CHECKSUM="49c4e7ac4b4809672e784134992578a1" CHECKSUMTYPE="MD5">
                    <ns3:FLocat LOCTYPE="OTHER" OTHERLOCTYPE="FILE" ns2:type="simple" ns2:href="1416473_0003.jpg"/>
                </ns3:file>
                <ns3:file ID="IMG_4" SEQ="4" MIMETYPE="image/jpeg" CREATED="2023-05-01T22:06:15.566+02:00" CHECKSUM="085835dc7b52c66a7fa7e681456037f4" CHECKSUMTYPE="MD5">
                    <ns3:FLocat LOCTYPE="OTHER" OTHERLOCTYPE="FILE" ns2:type="simple" ns2:href="1416473_0004.jpg"/>
                </ns3:file>
                <ns3:file ID="IMG_5" SEQ="5" MIMETYPE="image/jpeg" CREATED="2023-05-01T22:06:16.165+02:00" CHECKSUM="d6737006d025bcf279e21449ff404892" CHECKSUMTYPE="MD5">
                    <ns3:FLocat LOCTYPE="OTHER" OTHERLOCTYPE="FILE" ns2:type="simple" ns2:href="1416473_0005.jpg"/>
                </ns3:file>
                <ns3:file ID="IMG_6" SEQ="6" MIMETYPE="image/jpeg" CREATED="2023-05-01T22:06:16.891+02:00" CHECKSUM="2371287bce34bfe58ad285adcb00712d" CHECKSUMTYPE="MD5">
                    <ns3:FLocat LOCTYPE="OTHER" OTHERLOCTYPE="FILE" ns2:type="simple" ns2:href="1416473_0006.jpg"/>
                </ns3:file>
                <ns3:file ID="IMG_7" SEQ="7" MIMETYPE="image/jpeg" CREATED="2023-05-01T22:06:17.459+02:00" CHECKSUM="728bd6f1e8c0110a5de19b26a51172e9" CHECKSUMTYPE="MD5">
                    <ns3:FLocat LOCTYPE="OTHER" OTHERLOCTYPE="FILE" ns2:type="simple" ns2:href="1416473_0007.jpg"/>
                </ns3:file>
                <ns3:file ID="IMG_8" SEQ="8" MIMETYPE="image/jpeg" CREATED="2023-05-01T22:06:18.088+02:00" CHECKSUM="593ee74e66627e7190c186b095a3f2c8" CHECKSUMTYPE="MD5">
                    <ns3:FLocat LOCTYPE="OTHER" OTHERLOCTYPE="FILE" ns2:type="simple" ns2:href="1416473_0008.jpg"/>
                </ns3:file>
                <ns3:file ID="IMG_9" SEQ="9" MIMETYPE="image/jpeg" CREATED="2023-05-01T22:06:18.699+02:00" CHECKSUM="a19547470588cb93e4344cc26ba28bfa" CHECKSUMTYPE="MD5">
                    <ns3:FLocat LOCTYPE="OTHER" OTHERLOCTYPE="FILE" ns2:type="simple" ns2:href="1416473_0009.jpg"/>
                </ns3:file>
                <ns3:file ID="IMG_10" SEQ="10" MIMETYPE="image/jpeg" CREATED="2023-05-01T22:06:19.302+02:00" CHECKSUM="0963dc9d467e001e6afb89670888963d" CHECKSUMTYPE="MD5">
                    <ns3:FLocat LOCTYPE="OTHER" OTHERLOCTYPE="FILE" ns2:type="simple" ns2:href="1416473_0010.jpg"/>
                </ns3:file>
                <ns3:file ID="IMG_11" SEQ="11" MIMETYPE="image/jpeg" CREATED="2023-05-01T22:06:19.997+02:00" CHECKSUM="e85a82b6963eab95cdbd0dfad56be7a6" CHECKSUMTYPE="MD5">
                    <ns3:FLocat LOCTYPE="OTHER" OTHERLOCTYPE="FILE" ns2:type="simple" ns2:href="1416473_0011.jpg"/>
                </ns3:file>
                <ns3:file ID="IMG_12" SEQ="12" MIMETYPE="image/jpeg" CREATED="2023-05-01T22:06:20.611+02:00" CHECKSUM="3bddfb2ff6637dc9ecb9b3b9677fdf1c" CHECKSUMTYPE="MD5">
                    <ns3:FLocat LOCTYPE="OTHER" OTHERLOCTYPE="FILE" ns2:type="simple" ns2:href="1416473_0012.jpg"/>
                </ns3:file>
                <ns3:file ID="IMG_13" SEQ="13" MIMETYPE="image/jpeg" CREATED="2023-05-01T22:06:21.292+02:00" CHECKSUM="ba48da6d16c487f812d5c4305615e168" CHECKSUMTYPE="MD5">
                    <ns3:FLocat LOCTYPE="OTHER" OTHERLOCTYPE="FILE" ns2:type="simple" ns2:href="1416473_0013.jpg"/>
                </ns3:file>
                <ns3:file ID="IMG_14" SEQ="14" MIMETYPE="image/jpeg" CREATED="2023-05-01T22:06:22.117+02:00" CHECKSUM="62d60136f0cfed57c4f3dac829ecbd2f" CHECKSUMTYPE="MD5">
                    <ns3:FLocat LOCTYPE="OTHER" OTHERLOCTYPE="FILE" ns2:type="simple" ns2:href="1416473_0014.jpg"/>
                </ns3:file>
                <ns3:file ID="IMG_15" SEQ="15" MIMETYPE="image/jpeg" CREATED="2023-05-01T22:06:22.830+02:00" CHECKSUM="1999baab8e14ce7dd66b3775cea19011" CHECKSUMTYPE="MD5">
                    <ns3:FLocat LOCTYPE="OTHER" OTHERLOCTYPE="FILE" ns2:type="simple" ns2:href="1416473_0015.jpg"/>
                </ns3:file>
                <ns3:file ID="IMG_16" SEQ="16" MIMETYPE="image/jpeg" CREATED="2023-05-01T22:06:28.204+02:00" CHECKSUM="c5135f913add9378b7f4e01fcf8a4402" CHECKSUMTYPE="MD5">
                    <ns3:FLocat LOCTYPE="OTHER" OTHERLOCTYPE="FILE" ns2:type="simple" ns2:href="1416473_0016.jpg"/>
                </ns3:file>
                <ns3:file ID="IMG_17" SEQ="17" MIMETYPE="image/jpeg" CREATED="2023-05-01T22:06:29.013+02:00" CHECKSUM="d86adbe057351036a0218e498773722c" CHECKSUMTYPE="MD5">
                    <ns3:FLocat LOCTYPE="OTHER" OTHERLOCTYPE="FILE" ns2:type="simple" ns2:href="1416473_0017.jpg"/>
                </ns3:file>
                <ns3:file ID="IMG_18" SEQ="18" MIMETYPE="image/jpeg" CREATED="2023-05-01T22:06:29.567+02:00" CHECKSUM="a93789c7fe7278d2e1d7e406cbf87737" CHECKSUMTYPE="MD5">
                    <ns3:FLocat LOCTYPE="OTHER" OTHERLOCTYPE="FILE" ns2:type="simple" ns2:href="1416473_0018.jpg"/>
                </ns3:file>
                <ns3:file ID="IMG_19" SEQ="19" MIMETYPE="image/jpeg" CREATED="2023-05-01T22:06:30.145+02:00" CHECKSUM="4f8584001725c26f921657228c2334e6" CHECKSUMTYPE="MD5">
                    <ns3:FLocat LOCTYPE="OTHER" OTHERLOCTYPE="FILE" ns2:type="simple" ns2:href="1416473_0019.jpg"/>
                </ns3:file>
                <ns3:file ID="IMG_20" SEQ="20" MIMETYPE="image/jpeg" CREATED="2023-05-01T22:06:31.160+02:00" CHECKSUM="d8b5f0eeaebd688e9678515bbdc206b8" CHECKSUMTYPE="MD5">
                    <ns3:FLocat LOCTYPE="OTHER" OTHERLOCTYPE="FILE" ns2:type="simple" ns2:href="1416473_0020.jpg"/>
                </ns3:file>
                <ns3:file ID="IMG_21" SEQ="21" MIMETYPE="image/jpeg" CREATED="2023-05-01T22:06:31.891+02:00" CHECKSUM="c8473986537104b5096c60785d0fd934" CHECKSUMTYPE="MD5">
                    <ns3:FLocat LOCTYPE="OTHER" OTHERLOCTYPE="FILE" ns2:type="simple" ns2:href="1416473_0021.jpg"/>
                </ns3:file>
                <ns3:file ID="IMG_22" SEQ="22" MIMETYPE="image/jpeg" CREATED="2023-05-01T22:06:32.776+02:00" CHECKSUM="80a568a220bffff333970c9b614dac6f" CHECKSUMTYPE="MD5">
                    <ns3:FLocat LOCTYPE="OTHER" OTHERLOCTYPE="FILE" ns2:type="simple" ns2:href="1416473_0022.jpg"/>
                </ns3:file>
                <ns3:file ID="IMG_23" SEQ="23" MIMETYPE="image/jpeg" CREATED="2023-05-01T22:06:33.368+02:00" CHECKSUM="2ee3ccc229f5ffc9956f7e666c52b915" CHECKSUMTYPE="MD5">
                    <ns3:FLocat LOCTYPE="OTHER" OTHERLOCTYPE="FILE" ns2:type="simple" ns2:href="1416473_0023.jpg"/>
                </ns3:file>
                <ns3:file ID="IMG_24" SEQ="24" MIMETYPE="image/jpeg" CREATED="2023-05-01T22:06:34.021+02:00" CHECKSUM="6adf0cbfaf70f5c0a2ebfbad80eefa4d" CHECKSUMTYPE="MD5">
                    <ns3:FLocat LOCTYPE="OTHER" OTHERLOCTYPE="FILE" ns2:type="simple" ns2:href="1416473_0024.jpg"/>
                </ns3:file>
                <ns3:file ID="IMG_25" SEQ="25" MIMETYPE="image/jpeg" CREATED="2023-05-01T22:06:34.898+02:00" CHECKSUM="6db300de9871ddb05908fb9699ce9307" CHECKSUMTYPE="MD5">
                    <ns3:FLocat LOCTYPE="OTHER" OTHERLOCTYPE="FILE" ns2:type="simple" ns2:href="1416473_0025.jpg"/>
                </ns3:file>
                <ns3:file ID="IMG_26" SEQ="26" MIMETYPE="image/jpeg" CREATED="2023-05-01T22:06:35.761+02:00" CHECKSUM="d22ee938472265fa7dd50054c6842f98" CHECKSUMTYPE="MD5">
                    <ns3:FLocat LOCTYPE="OTHER" OTHERLOCTYPE="FILE" ns2:type="simple" ns2:href="1416473_0026.jpg"/>
                </ns3:file>
                <ns3:file ID="IMG_27" SEQ="27" MIMETYPE="image/jpeg" CREATED="2023-05-01T22:06:36.492+02:00" CHECKSUM="8c5eb0863955821a8207e83a1f1fc33c" CHECKSUMTYPE="MD5">
                    <ns3:FLocat LOCTYPE="OTHER" OTHERLOCTYPE="FILE" ns2:type="simple" ns2:href="1416473_0027.jpg"/>
                </ns3:file>
                <ns3:file ID="IMG_28" SEQ="28" MIMETYPE="image/jpeg" CREATED="2023-05-01T22:06:37.440+02:00" CHECKSUM="594239486792c3dfe39ff30d5a5fa7d0" CHECKSUMTYPE="MD5">
                    <ns3:FLocat LOCTYPE="OTHER" OTHERLOCTYPE="FILE" ns2:type="simple" ns2:href="1416473_0028.jpg"/>
                </ns3:file>
                <ns3:file ID="IMG_29" SEQ="29" MIMETYPE="image/jpeg" CREATED="2023-05-01T22:06:38.519+02:00" CHECKSUM="f8d6cd39fbe7009028567410e2488c77" CHECKSUMTYPE="MD5">
                    <ns3:FLocat LOCTYPE="OTHER" OTHERLOCTYPE="FILE" ns2:type="simple" ns2:href="1416473_0029.jpg"/>
                </ns3:file>
                <ns3:file ID="IMG_30" SEQ="30" MIMETYPE="image/jpeg" CREATED="2023-05-01T22:06:39.251+02:00" CHECKSUM="54205b9a6805ab6449d95960e716e23c" CHECKSUMTYPE="MD5">
                    <ns3:FLocat LOCTYPE="OTHER" OTHERLOCTYPE="FILE" ns2:type="simple" ns2:href="1416473_0030.jpg"/>
                </ns3:file>
                <ns3:file ID="IMG_31" SEQ="31" MIMETYPE="image/jpeg" CREATED="2023-05-01T22:06:39.985+02:00" CHECKSUM="1d48b5e033626e671f4394dd541526f9" CHECKSUMTYPE="MD5">
                    <ns3:FLocat LOCTYPE="OTHER" OTHERLOCTYPE="FILE" ns2:type="simple" ns2:href="1416473_0031.jpg"/>
                </ns3:file>
                <ns3:file ID="IMG_32" SEQ="32" MIMETYPE="image/jpeg" CREATED="2023-05-01T22:06:40.627+02:00" CHECKSUM="8aec40b14a0fc50fd3d0a610fc735584" CHECKSUMTYPE="MD5">
                    <ns3:FLocat LOCTYPE="OTHER" OTHERLOCTYPE="FILE" ns2:type="simple" ns2:href="1416473_0032.jpg"/>
                </ns3:file>
                <ns3:file ID="IMG_33" SEQ="33" MIMETYPE="image/jpeg" CREATED="2023-05-01T22:06:41.791+02:00" CHECKSUM="2627e0d8a82c8ab44d6c46848d5e3890" CHECKSUMTYPE="MD5">
                    <ns3:FLocat LOCTYPE="OTHER" OTHERLOCTYPE="FILE" ns2:type="simple" ns2:href="1416473_0033.jpg"/>
                </ns3:file>
                <ns3:file ID="IMG_34" SEQ="34" MIMETYPE="image/jpeg" CREATED="2023-05-01T22:06:42.368+02:00" CHECKSUM="4d970fad8f9d6ec26bed6894a5a7d7be" CHECKSUMTYPE="MD5">
                    <ns3:FLocat LOCTYPE="OTHER" OTHERLOCTYPE="FILE" ns2:type="simple" ns2:href="1416473_0034.jpg"/>
                </ns3:file>
                <ns3:file ID="IMG_35" SEQ="35" MIMETYPE="image/jpeg" CREATED="2023-05-01T22:06:43.022+02:00" CHECKSUM="4487fa6fd56141c563707d806d427867" CHECKSUMTYPE="MD5">
                    <ns3:FLocat LOCTYPE="OTHER" OTHERLOCTYPE="FILE" ns2:type="simple" ns2:href="1416473_0035.jpg"/>
                </ns3:file>
                <ns3:file ID="IMG_36" SEQ="36" MIMETYPE="image/jpeg" CREATED="2023-05-01T22:06:46.195+02:00" CHECKSUM="ff8d97f03718d082b2a91d158986fad6" CHECKSUMTYPE="MD5">
                    <ns3:FLocat LOCTYPE="OTHER" OTHERLOCTYPE="FILE" ns2:type="simple" ns2:href="1416473_0036.jpg"/>
                </ns3:file>
                <ns3:file ID="IMG_37" SEQ="37" MIMETYPE="image/jpeg" CREATED="2023-05-01T22:06:46.783+02:00" CHECKSUM="d2ffb66aeb00a8d7234b855b676363a4" CHECKSUMTYPE="MD5">
                    <ns3:FLocat LOCTYPE="OTHER" OTHERLOCTYPE="FILE" ns2:type="simple" ns2:href="1416473_0037.jpg"/>
                </ns3:file>
                <ns3:file ID="IMG_38" SEQ="38" MIMETYPE="image/jpeg" CREATED="2023-05-01T22:06:47.369+02:00" CHECKSUM="624bc7fd5c6cb0cbdefe13fe627b043a" CHECKSUMTYPE="MD5">
                    <ns3:FLocat LOCTYPE="OTHER" OTHERLOCTYPE="FILE" ns2:type="simple" ns2:href="1416473_0038.jpg"/>
                </ns3:file>
                <ns3:file ID="IMG_39" SEQ="39" MIMETYPE="image/jpeg" CREATED="2023-05-01T22:06:48.037+02:00" CHECKSUM="e000115e52cc2b51909c0f06d4f380cf" CHECKSUMTYPE="MD5">
                    <ns3:FLocat LOCTYPE="OTHER" OTHERLOCTYPE="FILE" ns2:type="simple" ns2:href="1416473_0039.jpg"/>
                </ns3:file>
                <ns3:file ID="IMG_40" SEQ="40" MIMETYPE="image/jpeg" CREATED="2023-05-01T22:06:48.910+02:00" CHECKSUM="e6d612f343938f2999b885b677804095" CHECKSUMTYPE="MD5">
                    <ns3:FLocat LOCTYPE="OTHER" OTHERLOCTYPE="FILE" ns2:type="simple" ns2:href="1416473_0040.jpg"/>
                </ns3:file>
                <ns3:file ID="IMG_41" SEQ="41" MIMETYPE="image/jpeg" CREATED="2023-05-01T22:06:49.807+02:00" CHECKSUM="1c94f453c049541490a9060c882f65b7" CHECKSUMTYPE="MD5">
                    <ns3:FLocat LOCTYPE="OTHER" OTHERLOCTYPE="FILE" ns2:type="simple" ns2:href="1416473_0041.jpg"/>
                </ns3:file>
                <ns3:file ID="IMG_42" SEQ="42" MIMETYPE="image/jpeg" CREATED="2023-05-01T22:06:50.443+02:00" CHECKSUM="a64b0f782d45c2a1be0cee4c0db3f31c" CHECKSUMTYPE="MD5">
                    <ns3:FLocat LOCTYPE="OTHER" OTHERLOCTYPE="FILE" ns2:type="simple" ns2:href="1416473_0042.jpg"/>
                </ns3:file>
                <ns3:file ID="IMG_43" SEQ="43" MIMETYPE="image/jpeg" CREATED="2023-05-01T22:06:51.088+02:00" CHECKSUM="11bdc9c61a08ad4c15a693f3b527c844" CHECKSUMTYPE="MD5">
                    <ns3:FLocat LOCTYPE="OTHER" OTHERLOCTYPE="FILE" ns2:type="simple" ns2:href="1416473_0043.jpg"/>
                </ns3:file>
                <ns3:file ID="IMG_44" SEQ="44" MIMETYPE="image/jpeg" CREATED="2023-05-01T22:06:51.711+02:00" CHECKSUM="c44144a4e2b5aff6aa31d3b6814c8bf7" CHECKSUMTYPE="MD5">
                    <ns3:FLocat LOCTYPE="OTHER" OTHERLOCTYPE="FILE" ns2:type="simple" ns2:href="1416473_0044.jpg"/>
                </ns3:file>
                <ns3:file ID="IMG_45" SEQ="45" MIMETYPE="image/jpeg" CREATED="2023-05-01T22:06:52.320+02:00" CHECKSUM="2b505dfb73a7fb0b73de37f8d6258c04" CHECKSUMTYPE="MD5">
                    <ns3:FLocat LOCTYPE="OTHER" OTHERLOCTYPE="FILE" ns2:type="simple" ns2:href="1416473_0045.jpg"/>
                </ns3:file>
                <ns3:file ID="IMG_46" SEQ="46" MIMETYPE="image/jpeg" CREATED="2023-05-01T22:06:52.893+02:00" CHECKSUM="dab92e5f64f1bc1e84ae4693b339a4dc" CHECKSUMTYPE="MD5">
                    <ns3:FLocat LOCTYPE="OTHER" OTHERLOCTYPE="FILE" ns2:type="simple" ns2:href="1416473_0046.jpg"/>
                </ns3:file>
                <ns3:file ID="IMG_47" SEQ="47" MIMETYPE="image/jpeg" CREATED="2023-05-01T22:06:53.671+02:00" CHECKSUM="37336ab86558f12a7aeb3abac762fad2" CHECKSUMTYPE="MD5">
                    <ns3:FLocat LOCTYPE="OTHER" OTHERLOCTYPE="FILE" ns2:type="simple" ns2:href="1416473_0047.jpg"/>
                </ns3:file>
                <ns3:file ID="IMG_48" SEQ="48" MIMETYPE="image/jpeg" CREATED="2023-05-01T22:06:55.552+02:00" CHECKSUM="c170d0af6a84b59df5fa52a600671075" CHECKSUMTYPE="MD5">
                    <ns3:FLocat LOCTYPE="OTHER" OTHERLOCTYPE="FILE" ns2:type="simple" ns2:href="1416473_0048.jpg"/>
                </ns3:file>
                <ns3:file ID="IMG_49" SEQ="49" MIMETYPE="image/jpeg" CREATED="2023-05-01T22:06:56.359+02:00" CHECKSUM="e2385b1ac1a193f9e536c50433eb5403" CHECKSUMTYPE="MD5">
                    <ns3:FLocat LOCTYPE="OTHER" OTHERLOCTYPE="FILE" ns2:type="simple" ns2:href="1416473_0049.jpg"/>
                </ns3:file>
                <ns3:file ID="IMG_50" SEQ="50" MIMETYPE="image/jpeg" CREATED="2023-05-01T22:07:00.647+02:00" CHECKSUM="af7d0d42db8366520086508e56e2df2b" CHECKSUMTYPE="MD5">
                    <ns3:FLocat LOCTYPE="OTHER" OTHERLOCTYPE="FILE" ns2:type="simple" ns2:href="1416473_0050.jpg"/>
                </ns3:file>
                <ns3:file ID="IMG_51" SEQ="51" MIMETYPE="image/jpeg" CREATED="2023-05-01T22:07:01.780+02:00" CHECKSUM="f12e81d79b78cd24feeaa0009f0aeb5c" CHECKSUMTYPE="MD5">
                    <ns3:FLocat LOCTYPE="OTHER" OTHERLOCTYPE="FILE" ns2:type="simple" ns2:href="1416473_0051.jpg"/>
                </ns3:file>
                <ns3:file ID="IMG_52" SEQ="52" MIMETYPE="image/jpeg" CREATED="2023-05-01T22:07:04.582+02:00" CHECKSUM="103eced43e1daf8144fe80fa937339e3" CHECKSUMTYPE="MD5">
                    <ns3:FLocat LOCTYPE="OTHER" OTHERLOCTYPE="FILE" ns2:type="simple" ns2:href="1416473_0052.jpg"/>
                </ns3:file>
                <ns3:file ID="IMG_53" SEQ="53" MIMETYPE="image/jpeg" CREATED="2023-05-01T22:07:05.217+02:00" CHECKSUM="1d3095fbe5c546f7819584cb6b23f0e2" CHECKSUMTYPE="MD5">
                    <ns3:FLocat LOCTYPE="OTHER" OTHERLOCTYPE="FILE" ns2:type="simple" ns2:href="1416473_0053.jpg"/>
                </ns3:file>
                <ns3:file ID="IMG_54" SEQ="54" MIMETYPE="image/jpeg" CREATED="2023-05-01T22:07:05.901+02:00" CHECKSUM="805a485c0ededec879cd81f5dcd89f3e" CHECKSUMTYPE="MD5">
                    <ns3:FLocat LOCTYPE="OTHER" OTHERLOCTYPE="FILE" ns2:type="simple" ns2:href="1416473_0054.jpg"/>
                </ns3:file>
                <ns3:file ID="IMG_55" SEQ="55" MIMETYPE="image/jpeg" CREATED="2023-05-01T22:07:07.526+02:00" CHECKSUM="3eb2ac792b97702112992ec1bab8a553" CHECKSUMTYPE="MD5">
                    <ns3:FLocat LOCTYPE="OTHER" OTHERLOCTYPE="FILE" ns2:type="simple" ns2:href="1416473_0055.jpg"/>
                </ns3:file>
                <ns3:file ID="IMG_56" SEQ="56" MIMETYPE="image/jpeg" CREATED="2023-05-01T22:07:10.026+02:00" CHECKSUM="98179d3c0ea7642aa09d84d1d5fcf763" CHECKSUMTYPE="MD5">
                    <ns3:FLocat LOCTYPE="OTHER" OTHERLOCTYPE="FILE" ns2:type="simple" ns2:href="1416473_0056.jpg"/>
                </ns3:file>
                <ns3:file ID="IMG_57" SEQ="57" MIMETYPE="image/jpeg" CREATED="2023-05-01T22:07:10.636+02:00" CHECKSUM="7659eff22258f453da37afe666fc2674" CHECKSUMTYPE="MD5">
                    <ns3:FLocat LOCTYPE="OTHER" OTHERLOCTYPE="FILE" ns2:type="simple" ns2:href="1416473_0057.jpg"/>
                </ns3:file>
                <ns3:file ID="IMG_58" SEQ="58" MIMETYPE="image/jpeg" CREATED="2023-05-01T22:07:11.241+02:00" CHECKSUM="dbba1fa7e89bb7b6daec7e9ab7bef8be" CHECKSUMTYPE="MD5">
                    <ns3:FLocat LOCTYPE="OTHER" OTHERLOCTYPE="FILE" ns2:type="simple" ns2:href="1416473_0058.jpg"/>
                </ns3:file>
                <ns3:file ID="IMG_59" SEQ="59" MIMETYPE="image/jpeg" CREATED="2023-05-01T22:07:11.887+02:00" CHECKSUM="a65975c8e0669ea391e0dac2a76d8a18" CHECKSUMTYPE="MD5">
                    <ns3:FLocat LOCTYPE="OTHER" OTHERLOCTYPE="FILE" ns2:type="simple" ns2:href="1416473_0059.jpg"/>
                </ns3:file>
                <ns3:file ID="IMG_60" SEQ="60" MIMETYPE="image/jpeg" CREATED="2023-05-01T22:07:12.753+02:00" CHECKSUM="105202b57fe9cd2b3056bf912639ec4f" CHECKSUMTYPE="MD5">
                    <ns3:FLocat LOCTYPE="OTHER" OTHERLOCTYPE="FILE" ns2:type="simple" ns2:href="1416473_0060.jpg"/>
                </ns3:file>
                <ns3:file ID="IMG_61" SEQ="61" MIMETYPE="image/jpeg" CREATED="2023-05-01T22:07:13.397+02:00" CHECKSUM="42d8be5e0e790c4dbeb4fe72f48c3051" CHECKSUMTYPE="MD5">
                    <ns3:FLocat LOCTYPE="OTHER" OTHERLOCTYPE="FILE" ns2:type="simple" ns2:href="1416473_0061.jpg"/>
                </ns3:file>
                <ns3:file ID="IMG_62" SEQ="62" MIMETYPE="image/jpeg" CREATED="2023-05-01T22:07:14.108+02:00" CHECKSUM="c7dc6ea5561768d944615eeb02281703" CHECKSUMTYPE="MD5">
                    <ns3:FLocat LOCTYPE="OTHER" OTHERLOCTYPE="FILE" ns2:type="simple" ns2:href="1416473_0062.jpg"/>
                </ns3:file>
                <ns3:file ID="IMG_63" SEQ="63" MIMETYPE="image/jpeg" CREATED="2023-05-01T22:07:14.722+02:00" CHECKSUM="878bf857b3efdb36a1255656e202c2b1" CHECKSUMTYPE="MD5">
                    <ns3:FLocat LOCTYPE="OTHER" OTHERLOCTYPE="FILE" ns2:type="simple" ns2:href="1416473_0063.jpg"/>
                </ns3:file>
                <ns3:file ID="IMG_64" SEQ="64" MIMETYPE="image/jpeg" CREATED="2023-05-01T22:07:15.591+02:00" CHECKSUM="966645844aaef9fc2b72e6cd78746e7f" CHECKSUMTYPE="MD5">
                    <ns3:FLocat LOCTYPE="OTHER" OTHERLOCTYPE="FILE" ns2:type="simple" ns2:href="1416473_0064.jpg"/>
                </ns3:file>
                <ns3:file ID="IMG_65" SEQ="65" MIMETYPE="image/jpeg" CREATED="2023-05-01T22:07:16.706+02:00" CHECKSUM="a58bba5368739c28f548c8a788d2a576" CHECKSUMTYPE="MD5">
                    <ns3:FLocat LOCTYPE="OTHER" OTHERLOCTYPE="FILE" ns2:type="simple" ns2:href="1416473_0065.jpg"/>
                </ns3:file>
                <ns3:file ID="IMG_66" SEQ="66" MIMETYPE="image/jpeg" CREATED="2023-05-01T22:07:17.706+02:00" CHECKSUM="c8d13160c5bba97a124fc30f8d372e5b" CHECKSUMTYPE="MD5">
                    <ns3:FLocat LOCTYPE="OTHER" OTHERLOCTYPE="FILE" ns2:type="simple" ns2:href="1416473_0066.jpg"/>
                </ns3:file>
                <ns3:file ID="IMG_67" SEQ="67" MIMETYPE="image/jpeg" CREATED="2023-05-01T22:07:18.461+02:00" CHECKSUM="65c6b373aae0c8c09864b3131581d32a" CHECKSUMTYPE="MD5">
                    <ns3:FLocat LOCTYPE="OTHER" OTHERLOCTYPE="FILE" ns2:type="simple" ns2:href="1416473_0067.jpg"/>
                </ns3:file>
                <ns3:file ID="IMG_68" SEQ="68" MIMETYPE="image/jpeg" CREATED="2023-05-01T22:07:19.106+02:00" CHECKSUM="a476864d539f3435228c549f49512e6f" CHECKSUMTYPE="MD5">
                    <ns3:FLocat LOCTYPE="OTHER" OTHERLOCTYPE="FILE" ns2:type="simple" ns2:href="1416473_0068.jpg"/>
                </ns3:file>
                <ns3:file ID="IMG_69" SEQ="69" MIMETYPE="image/jpeg" CREATED="2023-05-01T22:07:19.707+02:00" CHECKSUM="550c2bb2ac7b5d279443c4297833b635" CHECKSUMTYPE="MD5">
                    <ns3:FLocat LOCTYPE="OTHER" OTHERLOCTYPE="FILE" ns2:type="simple" ns2:href="1416473_0069.jpg"/>
                </ns3:file>
                <ns3:file ID="IMG_70" SEQ="70" MIMETYPE="image/jpeg" CREATED="2023-05-01T22:07:20.425+02:00" CHECKSUM="6cf3763c993f14dd496003fe83bbb71e" CHECKSUMTYPE="MD5">
                    <ns3:FLocat LOCTYPE="OTHER" OTHERLOCTYPE="FILE" ns2:type="simple" ns2:href="1416473_0070.jpg"/>
                </ns3:file>
                <ns3:file ID="IMG_71" SEQ="71" MIMETYPE="image/jpeg" CREATED="2023-05-01T22:07:21.151+02:00" CHECKSUM="54089c32cfed9d43b92296d0e4cf5ec6" CHECKSUMTYPE="MD5">
                    <ns3:FLocat LOCTYPE="OTHER" OTHERLOCTYPE="FILE" ns2:type="simple" ns2:href="1416473_0071.jpg"/>
                </ns3:file>
            </ns3:fileGrp>
            <ns3:fileGrp ID="PAGEXML">
                <ns3:file ID="PAGEXML_1" SEQ="1" MIMETYPE="application/xml" CREATED="2024-03-30T21:18:45.542+01:00" CHECKSUM="259955c9ed6e5140e9f80ac22354f01a" CHECKSUMTYPE="MD5">
                    <ns3:FLocat LOCTYPE="OTHER" OTHERLOCTYPE="FILE" ns2:type="simple" ns2:href="page/1416473_0001.xml"/>
                </ns3:file>
                <ns3:file ID="PAGEXML_2" SEQ="2" MIMETYPE="application/xml" CREATED="2024-03-30T21:18:46.302+01:00" CHECKSUM="d980a1df9fe09e3a833dfa4fa9348087" CHECKSUMTYPE="MD5">
                    <ns3:FLocat LOCTYPE="OTHER" OTHERLOCTYPE="FILE" ns2:type="simple" ns2:href="page/1416473_0002.xml"/>
                </ns3:file>
                <ns3:file ID="PAGEXML_3" SEQ="3" MIMETYPE="application/xml" CREATED="2024-03-30T21:18:47.018+01:00" CHECKSUM="4abf63994582cb02b88edc37166ae60f" CHECKSUMTYPE="MD5">
                    <ns3:FLocat LOCTYPE="OTHER" OTHERLOCTYPE="FILE" ns2:type="simple" ns2:href="page/1416473_0003.xml"/>
                </ns3:file>
                <ns3:file ID="PAGEXML_4" SEQ="4" MIMETYPE="application/xml" CREATED="2024-03-30T21:18:47.758+01:00" CHECKSUM="7530dd3adf2f4d67244f6417b5763c58" CHECKSUMTYPE="MD5">
                    <ns3:FLocat LOCTYPE="OTHER" OTHERLOCTYPE="FILE" ns2:type="simple" ns2:href="page/1416473_0004.xml"/>
                </ns3:file>
                <ns3:file ID="PAGEXML_5" SEQ="5" MIMETYPE="application/xml" CREATED="2024-03-30T21:18:48.502+01:00" CHECKSUM="c6215694eba664b910684b3e68229d31" CHECKSUMTYPE="MD5">
                    <ns3:FLocat LOCTYPE="OTHER" OTHERLOCTYPE="FILE" ns2:type="simple" ns2:href="page/1416473_0005.xml"/>
                </ns3:file>
                <ns3:file ID="PAGEXML_6" SEQ="6" MIMETYPE="application/xml" CREATED="2024-03-30T21:18:49.230+01:00" CHECKSUM="07d77134d6b0be9add8046ce5a8bf515" CHECKSUMTYPE="MD5">
                    <ns3:FLocat LOCTYPE="OTHER" OTHERLOCTYPE="FILE" ns2:type="simple" ns2:href="page/1416473_0006.xml"/>
                </ns3:file>
                <ns3:file ID="PAGEXML_7" SEQ="7" MIMETYPE="application/xml" CREATED="2024-03-30T21:18:49.962+01:00" CHECKSUM="793e4e0735878ebe87e08d6fb73fc76c" CHECKSUMTYPE="MD5">
                    <ns3:FLocat LOCTYPE="OTHER" OTHERLOCTYPE="FILE" ns2:type="simple" ns2:href="page/1416473_0007.xml"/>
                </ns3:file>
                <ns3:file ID="PAGEXML_8" SEQ="8" MIMETYPE="application/xml" CREATED="2024-03-30T21:18:50.690+01:00" CHECKSUM="bacda91a625773106995f24da9bfc2fe" CHECKSUMTYPE="MD5">
                    <ns3:FLocat LOCTYPE="OTHER" OTHERLOCTYPE="FILE" ns2:type="simple" ns2:href="page/1416473_0008.xml"/>
                </ns3:file>
                <ns3:file ID="PAGEXML_9" SEQ="9" MIMETYPE="application/xml" CREATED="2024-03-30T21:18:51.414+01:00" CHECKSUM="ec4f0516af9c374fe4e958515c2f905a" CHECKSUMTYPE="MD5">
                    <ns3:FLocat LOCTYPE="OTHER" OTHERLOCTYPE="FILE" ns2:type="simple" ns2:href="page/1416473_0009.xml"/>
                </ns3:file>
                <ns3:file ID="PAGEXML_10" SEQ="10" MIMETYPE="application/xml" CREATED="2024-03-30T21:18:52.134+01:00" CHECKSUM="7af34bb40e0fa815d434adc1ef006491" CHECKSUMTYPE="MD5">
                    <ns3:FLocat LOCTYPE="OTHER" OTHERLOCTYPE="FILE" ns2:type="simple" ns2:href="page/1416473_0010.xml"/>
                </ns3:file>
                <ns3:file ID="PAGEXML_11" SEQ="11" MIMETYPE="application/xml" CREATED="2024-03-30T21:18:52.878+01:00" CHECKSUM="126397e9deb5307306bd870cd011da28" CHECKSUMTYPE="MD5">
                    <ns3:FLocat LOCTYPE="OTHER" OTHERLOCTYPE="FILE" ns2:type="simple" ns2:href="page/1416473_0011.xml"/>
                </ns3:file>
                <ns3:file ID="PAGEXML_12" SEQ="12" MIMETYPE="application/xml" CREATED="2024-03-30T21:18:53.614+01:00" CHECKSUM="a87bc4279d26d5a864c1214980a03996" CHECKSUMTYPE="MD5">
                    <ns3:FLocat LOCTYPE="OTHER" OTHERLOCTYPE="FILE" ns2:type="simple" ns2:href="page/1416473_0012.xml"/>
                </ns3:file>
                <ns3:file ID="PAGEXML_13" SEQ="13" MIMETYPE="application/xml" CREATED="2024-03-30T21:18:54.338+01:00" CHECKSUM="d6dcb9c08b4a7c77b373bc555c6b4515" CHECKSUMTYPE="MD5">
                    <ns3:FLocat LOCTYPE="OTHER" OTHERLOCTYPE="FILE" ns2:type="simple" ns2:href="page/1416473_0013.xml"/>
                </ns3:file>
                <ns3:file ID="PAGEXML_14" SEQ="14" MIMETYPE="application/xml" CREATED="2024-03-30T21:18:55.090+01:00" CHECKSUM="83e493a35eb496cdcbff46e6763bc728" CHECKSUMTYPE="MD5">
                    <ns3:FLocat LOCTYPE="OTHER" OTHERLOCTYPE="FILE" ns2:type="simple" ns2:href="page/1416473_0014.xml"/>
                </ns3:file>
                <ns3:file ID="PAGEXML_15" SEQ="15" MIMETYPE="application/xml" CREATED="2024-03-30T21:18:56.234+01:00" CHECKSUM="36d5cb30ab8ce345c53de1d260f84ab6" CHECKSUMTYPE="MD5">
                    <ns3:FLocat LOCTYPE="OTHER" OTHERLOCTYPE="FILE" ns2:type="simple" ns2:href="page/1416473_0015.xml"/>
                </ns3:file>
                <ns3:file ID="PAGEXML_16" SEQ="16" MIMETYPE="application/xml" CREATED="2024-03-30T21:18:57.218+01:00" CHECKSUM="23c3102a432915a0582de2fe239e957a" CHECKSUMTYPE="MD5">
                    <ns3:FLocat LOCTYPE="OTHER" OTHERLOCTYPE="FILE" ns2:type="simple" ns2:href="page/1416473_0016.xml"/>
                </ns3:file>
                <ns3:file ID="PAGEXML_17" SEQ="17" MIMETYPE="application/xml" CREATED="2024-03-30T21:18:57.974+01:00" CHECKSUM="30dea72973d3660fba3a49840723205a" CHECKSUMTYPE="MD5">
                    <ns3:FLocat LOCTYPE="OTHER" OTHERLOCTYPE="FILE" ns2:type="simple" ns2:href="page/1416473_0017.xml"/>
                </ns3:file>
                <ns3:file ID="PAGEXML_18" SEQ="18" MIMETYPE="application/xml" CREATED="2024-03-30T21:18:58.706+01:00" CHECKSUM="fdb621b241f8cd7bfa4d8ad4944839c7" CHECKSUMTYPE="MD5">
                    <ns3:FLocat LOCTYPE="OTHER" OTHERLOCTYPE="FILE" ns2:type="simple" ns2:href="page/1416473_0018.xml"/>
                </ns3:file>
                <ns3:file ID="PAGEXML_19" SEQ="19" MIMETYPE="application/xml" CREATED="2024-03-30T21:18:59.442+01:00" CHECKSUM="a9f39d1f491b942c447043fed30757aa" CHECKSUMTYPE="MD5">
                    <ns3:FLocat LOCTYPE="OTHER" OTHERLOCTYPE="FILE" ns2:type="simple" ns2:href="page/1416473_0019.xml"/>
                </ns3:file>
                <ns3:file ID="PAGEXML_20" SEQ="20" MIMETYPE="application/xml" CREATED="2024-03-30T21:19:00.210+01:00" CHECKSUM="b183a35ab16c306ec5e1c1b9131b4832" CHECKSUMTYPE="MD5">
                    <ns3:FLocat LOCTYPE="OTHER" OTHERLOCTYPE="FILE" ns2:type="simple" ns2:href="page/1416473_0020.xml"/>
                </ns3:file>
                <ns3:file ID="PAGEXML_21" SEQ="21" MIMETYPE="application/xml" CREATED="2024-03-30T21:19:01.006+01:00" CHECKSUM="38c251325a50aad7a8abba44da3ce206" CHECKSUMTYPE="MD5">
                    <ns3:FLocat LOCTYPE="OTHER" OTHERLOCTYPE="FILE" ns2:type="simple" ns2:href="page/1416473_0021.xml"/>
                </ns3:file>
                <ns3:file ID="PAGEXML_22" SEQ="22" MIMETYPE="application/xml" CREATED="2024-03-30T21:19:01.750+01:00" CHECKSUM="7a11260a799fa9c82e5ba1d31cc60c0a" CHECKSUMTYPE="MD5">
                    <ns3:FLocat LOCTYPE="OTHER" OTHERLOCTYPE="FILE" ns2:type="simple" ns2:href="page/1416473_0022.xml"/>
                </ns3:file>
                <ns3:file ID="PAGEXML_23" SEQ="23" MIMETYPE="application/xml" CREATED="2024-03-30T21:19:02.482+01:00" CHECKSUM="a11ef1a8b8398434b526b9b4a6bdc67f" CHECKSUMTYPE="MD5">
                    <ns3:FLocat LOCTYPE="OTHER" OTHERLOCTYPE="FILE" ns2:type="simple" ns2:href="page/1416473_0023.xml"/>
                </ns3:file>
                <ns3:file ID="PAGEXML_24" SEQ="24" MIMETYPE="application/xml" CREATED="2024-03-30T21:19:03.270+01:00" CHECKSUM="5bc3dcf64e3156e96d1a2ef92d2f2c05" CHECKSUMTYPE="MD5">
                    <ns3:FLocat LOCTYPE="OTHER" OTHERLOCTYPE="FILE" ns2:type="simple" ns2:href="page/1416473_0024.xml"/>
                </ns3:file>
                <ns3:file ID="PAGEXML_25" SEQ="25" MIMETYPE="application/xml" CREATED="2024-03-30T21:19:04.034+01:00" CHECKSUM="2d2f844cc5a4e8eb1185b5dd688a5c0b" CHECKSUMTYPE="MD5">
                    <ns3:FLocat LOCTYPE="OTHER" OTHERLOCTYPE="FILE" ns2:type="simple" ns2:href="page/1416473_0025.xml"/>
                </ns3:file>
                <ns3:file ID="PAGEXML_26" SEQ="26" MIMETYPE="application/xml" CREATED="2024-03-30T21:19:04.730+01:00" CHECKSUM="fa7fdd6118bc9bb6936ec69784fa0433" CHECKSUMTYPE="MD5">
                    <ns3:FLocat LOCTYPE="OTHER" OTHERLOCTYPE="FILE" ns2:type="simple" ns2:href="page/1416473_0026.xml"/>
                </ns3:file>
                <ns3:file ID="PAGEXML_27" SEQ="27" MIMETYPE="application/xml" CREATED="2024-03-30T21:19:05.454+01:00" CHECKSUM="1dadf51cbd3425dbc86dd8c7bc2e2b78" CHECKSUMTYPE="MD5">
                    <ns3:FLocat LOCTYPE="OTHER" OTHERLOCTYPE="FILE" ns2:type="simple" ns2:href="page/1416473_0027.xml"/>
                </ns3:file>
                <ns3:file ID="PAGEXML_28" SEQ="28" MIMETYPE="application/xml" CREATED="2024-03-30T21:19:06.210+01:00" CHECKSUM="6a5f43ef684afdbb85cbbaae0702b06f" CHECKSUMTYPE="MD5">
                    <ns3:FLocat LOCTYPE="OTHER" OTHERLOCTYPE="FILE" ns2:type="simple" ns2:href="page/1416473_0028.xml"/>
                </ns3:file>
                <ns3:file ID="PAGEXML_29" SEQ="29" MIMETYPE="application/xml" CREATED="2024-03-30T21:19:06.918+01:00" CHECKSUM="089fca3d2f0ad3cf709c90e81b8bbe6b" CHECKSUMTYPE="MD5">
                    <ns3:FLocat LOCTYPE="OTHER" OTHERLOCTYPE="FILE" ns2:type="simple" ns2:href="page/1416473_0029.xml"/>
                </ns3:file>
                <ns3:file ID="PAGEXML_30" SEQ="30" MIMETYPE="application/xml" CREATED="2024-03-30T21:19:07.698+01:00" CHECKSUM="ec5a878622e6b50589805fd2a2a3ee02" CHECKSUMTYPE="MD5">
                    <ns3:FLocat LOCTYPE="OTHER" OTHERLOCTYPE="FILE" ns2:type="simple" ns2:href="page/1416473_0030.xml"/>
                </ns3:file>
                <ns3:file ID="PAGEXML_31" SEQ="31" MIMETYPE="application/xml" CREATED="2024-03-30T21:19:08.446+01:00" CHECKSUM="5a1cf8efcbbcfaed43f774e540cd1c90" CHECKSUMTYPE="MD5">
                    <ns3:FLocat LOCTYPE="OTHER" OTHERLOCTYPE="FILE" ns2:type="simple" ns2:href="page/1416473_0031.xml"/>
                </ns3:file>
                <ns3:file ID="PAGEXML_32" SEQ="32" MIMETYPE="application/xml" CREATED="2024-03-30T21:19:09.186+01:00" CHECKSUM="5eb849691fd374b7326a524eda265972" CHECKSUMTYPE="MD5">
                    <ns3:FLocat LOCTYPE="OTHER" OTHERLOCTYPE="FILE" ns2:type="simple" ns2:href="page/1416473_0032.xml"/>
                </ns3:file>
                <ns3:file ID="PAGEXML_33" SEQ="33" MIMETYPE="application/xml" CREATED="2024-03-30T21:19:09.922+01:00" CHECKSUM="fba8ec555007e4a119aa83cda6e335e7" CHECKSUMTYPE="MD5">
                    <ns3:FLocat LOCTYPE="OTHER" OTHERLOCTYPE="FILE" ns2:type="simple" ns2:href="page/1416473_0033.xml"/>
                </ns3:file>
                <ns3:file ID="PAGEXML_34" SEQ="34" MIMETYPE="application/xml" CREATED="2024-03-30T21:19:11.390+01:00" CHECKSUM="f9d0459dd44576161ada86126e8ed9da" CHECKSUMTYPE="MD5">
                    <ns3:FLocat LOCTYPE="OTHER" OTHERLOCTYPE="FILE" ns2:type="simple" ns2:href="page/1416473_0034.xml"/>
                </ns3:file>
                <ns3:file ID="PAGEXML_35" SEQ="35" MIMETYPE="application/xml" CREATED="2024-03-30T21:19:12.162+01:00" CHECKSUM="c9361d87cae79f8af8164afa490584b1" CHECKSUMTYPE="MD5">
                    <ns3:FLocat LOCTYPE="OTHER" OTHERLOCTYPE="FILE" ns2:type="simple" ns2:href="page/1416473_0035.xml"/>
                </ns3:file>
                <ns3:file ID="PAGEXML_36" SEQ="36" MIMETYPE="application/xml" CREATED="2024-03-30T21:19:12.902+01:00" CHECKSUM="19c3cc8c47fcf78f84e466d5fa8e1e79" CHECKSUMTYPE="MD5">
                    <ns3:FLocat LOCTYPE="OTHER" OTHERLOCTYPE="FILE" ns2:type="simple" ns2:href="page/1416473_0036.xml"/>
                </ns3:file>
                <ns3:file ID="PAGEXML_37" SEQ="37" MIMETYPE="application/xml" CREATED="2024-03-30T21:19:13.666+01:00" CHECKSUM="c893d42998476d9e150393a27f23d87a" CHECKSUMTYPE="MD5">
                    <ns3:FLocat LOCTYPE="OTHER" OTHERLOCTYPE="FILE" ns2:type="simple" ns2:href="page/1416473_0037.xml"/>
                </ns3:file>
                <ns3:file ID="PAGEXML_38" SEQ="38" MIMETYPE="application/xml" CREATED="2024-03-30T21:19:14.426+01:00" CHECKSUM="8de9472653667126f25ad959f1fe2b93" CHECKSUMTYPE="MD5">
                    <ns3:FLocat LOCTYPE="OTHER" OTHERLOCTYPE="FILE" ns2:type="simple" ns2:href="page/1416473_0038.xml"/>
                </ns3:file>
                <ns3:file ID="PAGEXML_39" SEQ="39" MIMETYPE="application/xml" CREATED="2024-03-30T21:19:15.162+01:00" CHECKSUM="ca48a7ca83a9a0d7ad646d2a553d6b49" CHECKSUMTYPE="MD5">
                    <ns3:FLocat LOCTYPE="OTHER" OTHERLOCTYPE="FILE" ns2:type="simple" ns2:href="page/1416473_0039.xml"/>
                </ns3:file>
                <ns3:file ID="PAGEXML_40" SEQ="40" MIMETYPE="application/xml" CREATED="2024-03-30T21:19:15.922+01:00" CHECKSUM="6f383f48a70f1246476c94a5cf9e065d" CHECKSUMTYPE="MD5">
                    <ns3:FLocat LOCTYPE="OTHER" OTHERLOCTYPE="FILE" ns2:type="simple" ns2:href="page/1416473_0040.xml"/>
                </ns3:file>
                <ns3:file ID="PAGEXML_41" SEQ="41" MIMETYPE="application/xml" CREATED="2024-03-30T21:19:16.662+01:00" CHECKSUM="de2c9000944635b7a6cc54af8ea2d431" CHECKSUMTYPE="MD5">
                    <ns3:FLocat LOCTYPE="OTHER" OTHERLOCTYPE="FILE" ns2:type="simple" ns2:href="page/1416473_0041.xml"/>
                </ns3:file>
                <ns3:file ID="PAGEXML_42" SEQ="42" MIMETYPE="application/xml" CREATED="2024-03-30T21:19:17.462+01:00" CHECKSUM="824879890d772c106520fcdbcaa25164" CHECKSUMTYPE="MD5">
                    <ns3:FLocat LOCTYPE="OTHER" OTHERLOCTYPE="FILE" ns2:type="simple" ns2:href="page/1416473_0042.xml"/>
                </ns3:file>
                <ns3:file ID="PAGEXML_43" SEQ="43" MIMETYPE="application/xml" CREATED="2024-03-30T21:19:18.202+01:00" CHECKSUM="83d308d1b48b79eb693ab4053e404c9d" CHECKSUMTYPE="MD5">
                    <ns3:FLocat LOCTYPE="OTHER" OTHERLOCTYPE="FILE" ns2:type="simple" ns2:href="page/1416473_0043.xml"/>
                </ns3:file>
                <ns3:file ID="PAGEXML_44" SEQ="44" MIMETYPE="application/xml" CREATED="2024-03-30T21:19:18.922+01:00" CHECKSUM="027d248d833172cb6bf303e1d281273f" CHECKSUMTYPE="MD5">
                    <ns3:FLocat LOCTYPE="OTHER" OTHERLOCTYPE="FILE" ns2:type="simple" ns2:href="page/1416473_0044.xml"/>
                </ns3:file>
                <ns3:file ID="PAGEXML_45" SEQ="45" MIMETYPE="application/xml" CREATED="2024-03-30T21:19:19.662+01:00" CHECKSUM="f80f5727b95a061f8a8815bc5606db8e" CHECKSUMTYPE="MD5">
                    <ns3:FLocat LOCTYPE="OTHER" OTHERLOCTYPE="FILE" ns2:type="simple" ns2:href="page/1416473_0045.xml"/>
                </ns3:file>
                <ns3:file ID="PAGEXML_46" SEQ="46" MIMETYPE="application/xml" CREATED="2024-03-30T21:19:20.414+01:00" CHECKSUM="3734af4c7147454f8c3e9e2abb773e0a" CHECKSUMTYPE="MD5">
                    <ns3:FLocat LOCTYPE="OTHER" OTHERLOCTYPE="FILE" ns2:type="simple" ns2:href="page/1416473_0046.xml"/>
                </ns3:file>
                <ns3:file ID="PAGEXML_47" SEQ="47" MIMETYPE="application/xml" CREATED="2024-03-30T21:19:21.142+01:00" CHECKSUM="81c0f349b72addee30a673fc983573fd" CHECKSUMTYPE="MD5">
                    <ns3:FLocat LOCTYPE="OTHER" OTHERLOCTYPE="FILE" ns2:type="simple" ns2:href="page/1416473_0047.xml"/>
                </ns3:file>
                <ns3:file ID="PAGEXML_48" SEQ="48" MIMETYPE="application/xml" CREATED="2024-03-30T21:19:21.918+01:00" CHECKSUM="deaa87fa29f0a607b4a8fe498d0b2c45" CHECKSUMTYPE="MD5">
                    <ns3:FLocat LOCTYPE="OTHER" OTHERLOCTYPE="FILE" ns2:type="simple" ns2:href="page/1416473_0048.xml"/>
                </ns3:file>
                <ns3:file ID="PAGEXML_49" SEQ="49" MIMETYPE="application/xml" CREATED="2024-03-30T21:19:22.642+01:00" CHECKSUM="2d5cb81553d4d94fc4d851398cfc9a77" CHECKSUMTYPE="MD5">
                    <ns3:FLocat LOCTYPE="OTHER" OTHERLOCTYPE="FILE" ns2:type="simple" ns2:href="page/1416473_0049.xml"/>
                </ns3:file>
                <ns3:file ID="PAGEXML_50" SEQ="50" MIMETYPE="application/xml" CREATED="2024-03-30T21:19:23.362+01:00" CHECKSUM="93e467d98f6b97d3ac7411491f909aae" CHECKSUMTYPE="MD5">
                    <ns3:FLocat LOCTYPE="OTHER" OTHERLOCTYPE="FILE" ns2:type="simple" ns2:href="page/1416473_0050.xml"/>
                </ns3:file>
                <ns3:file ID="PAGEXML_51" SEQ="51" MIMETYPE="application/xml" CREATED="2024-03-30T21:19:24.138+01:00" CHECKSUM="bf59f034bcd6afac5656b08309782d35" CHECKSUMTYPE="MD5">
                    <ns3:FLocat LOCTYPE="OTHER" OTHERLOCTYPE="FILE" ns2:type="simple" ns2:href="page/1416473_0051.xml"/>
                </ns3:file>
                <ns3:file ID="PAGEXML_52" SEQ="52" MIMETYPE="application/xml" CREATED="2024-03-30T21:19:24.874+01:00" CHECKSUM="0829194e6185aa9917857b3fe79132e0" CHECKSUMTYPE="MD5">
                    <ns3:FLocat LOCTYPE="OTHER" OTHERLOCTYPE="FILE" ns2:type="simple" ns2:href="page/1416473_0052.xml"/>
                </ns3:file>
                <ns3:file ID="PAGEXML_53" SEQ="53" MIMETYPE="application/xml" CREATED="2024-03-30T21:19:25.582+01:00" CHECKSUM="132f7231c45bf744d62104efcaee787f" CHECKSUMTYPE="MD5">
                    <ns3:FLocat LOCTYPE="OTHER" OTHERLOCTYPE="FILE" ns2:type="simple" ns2:href="page/1416473_0053.xml"/>
                </ns3:file>
                <ns3:file ID="PAGEXML_54" SEQ="54" MIMETYPE="application/xml" CREATED="2024-03-30T21:19:26.310+01:00" CHECKSUM="38cf80f67932190f5ef8895b260e101c" CHECKSUMTYPE="MD5">
                    <ns3:FLocat LOCTYPE="OTHER" OTHERLOCTYPE="FILE" ns2:type="simple" ns2:href="page/1416473_0054.xml"/>
                </ns3:file>
                <ns3:file ID="PAGEXML_55" SEQ="55" MIMETYPE="application/xml" CREATED="2024-03-30T21:19:27.018+01:00" CHECKSUM="37954c5cf89b6e2db4f9f9bdee39576c" CHECKSUMTYPE="MD5">
                    <ns3:FLocat LOCTYPE="OTHER" OTHERLOCTYPE="FILE" ns2:type="simple" ns2:href="page/1416473_0055.xml"/>
                </ns3:file>
                <ns3:file ID="PAGEXML_56" SEQ="56" MIMETYPE="application/xml" CREATED="2024-03-30T21:19:27.998+01:00" CHECKSUM="ce2f6e616b8c34e4229110814254910d" CHECKSUMTYPE="MD5">
                    <ns3:FLocat LOCTYPE="OTHER" OTHERLOCTYPE="FILE" ns2:type="simple" ns2:href="page/1416473_0056.xml"/>
                </ns3:file>
                <ns3:file ID="PAGEXML_57" SEQ="57" MIMETYPE="application/xml" CREATED="2024-03-30T21:19:28.786+01:00" CHECKSUM="1527aca7ce2abfa7ca64bd061b592469" CHECKSUMTYPE="MD5">
                    <ns3:FLocat LOCTYPE="OTHER" OTHERLOCTYPE="FILE" ns2:type="simple" ns2:href="page/1416473_0057.xml"/>
                </ns3:file>
                <ns3:file ID="PAGEXML_58" SEQ="58" MIMETYPE="application/xml" CREATED="2024-03-30T21:19:29.518+01:00" CHECKSUM="895576e568ed809b4464f184420e2d88" CHECKSUMTYPE="MD5">
                    <ns3:FLocat LOCTYPE="OTHER" OTHERLOCTYPE="FILE" ns2:type="simple" ns2:href="page/1416473_0058.xml"/>
                </ns3:file>
                <ns3:file ID="PAGEXML_59" SEQ="59" MIMETYPE="application/xml" CREATED="2024-03-30T21:19:30.322+01:00" CHECKSUM="5d5524f42ffc9c7d387771ce7c9221ff" CHECKSUMTYPE="MD5">
                    <ns3:FLocat LOCTYPE="OTHER" OTHERLOCTYPE="FILE" ns2:type="simple" ns2:href="page/1416473_0059.xml"/>
                </ns3:file>
                <ns3:file ID="PAGEXML_60" SEQ="60" MIMETYPE="application/xml" CREATED="2024-03-30T21:19:31.310+01:00" CHECKSUM="38ffc9162e9e8dffff36d391a6aeb671" CHECKSUMTYPE="MD5">
                    <ns3:FLocat LOCTYPE="OTHER" OTHERLOCTYPE="FILE" ns2:type="simple" ns2:href="page/1416473_0060.xml"/>
                </ns3:file>
                <ns3:file ID="PAGEXML_61" SEQ="61" MIMETYPE="application/xml" CREATED="2024-03-30T21:19:32.070+01:00" CHECKSUM="89ba0c40bcf34691cf94480fa5a94362" CHECKSUMTYPE="MD5">
                    <ns3:FLocat LOCTYPE="OTHER" OTHERLOCTYPE="FILE" ns2:type="simple" ns2:href="page/1416473_0061.xml"/>
                </ns3:file>
                <ns3:file ID="PAGEXML_62" SEQ="62" MIMETYPE="application/xml" CREATED="2024-03-30T21:19:32.818+01:00" CHECKSUM="144307a6ff50054b0a90cb81ed122270" CHECKSUMTYPE="MD5">
                    <ns3:FLocat LOCTYPE="OTHER" OTHERLOCTYPE="FILE" ns2:type="simple" ns2:href="page/1416473_0062.xml"/>
                </ns3:file>
                <ns3:file ID="PAGEXML_63" SEQ="63" MIMETYPE="application/xml" CREATED="2024-03-30T21:19:33.546+01:00" CHECKSUM="1673026ee61a02e58b3c74115bc32a78" CHECKSUMTYPE="MD5">
                    <ns3:FLocat LOCTYPE="OTHER" OTHERLOCTYPE="FILE" ns2:type="simple" ns2:href="page/1416473_0063.xml"/>
                </ns3:file>
                <ns3:file ID="PAGEXML_64" SEQ="64" MIMETYPE="application/xml" CREATED="2024-03-30T21:19:34.298+01:00" CHECKSUM="e825bf5a763763dd2923f1912e9f9567" CHECKSUMTYPE="MD5">
                    <ns3:FLocat LOCTYPE="OTHER" OTHERLOCTYPE="FILE" ns2:type="simple" ns2:href="page/1416473_0064.xml"/>
                </ns3:file>
                <ns3:file ID="PAGEXML_65" SEQ="65" MIMETYPE="application/xml" CREATED="2024-03-30T21:19:35.178+01:00" CHECKSUM="e7a55cdeeaee640089b01620ff040054" CHECKSUMTYPE="MD5">
                    <ns3:FLocat LOCTYPE="OTHER" OTHERLOCTYPE="FILE" ns2:type="simple" ns2:href="page/1416473_0065.xml"/>
                </ns3:file>
                <ns3:file ID="PAGEXML_66" SEQ="66" MIMETYPE="application/xml" CREATED="2024-03-30T21:19:35.894+01:00" CHECKSUM="607f0188948dac52b6f38a785774650c" CHECKSUMTYPE="MD5">
                    <ns3:FLocat LOCTYPE="OTHER" OTHERLOCTYPE="FILE" ns2:type="simple" ns2:href="page/1416473_0066.xml"/>
                </ns3:file>
                <ns3:file ID="PAGEXML_67" SEQ="67" MIMETYPE="application/xml" CREATED="2024-03-30T21:19:36.646+01:00" CHECKSUM="161cb939e9c49719086e72e5ffa3cc17" CHECKSUMTYPE="MD5">
                    <ns3:FLocat LOCTYPE="OTHER" OTHERLOCTYPE="FILE" ns2:type="simple" ns2:href="page/1416473_0067.xml"/>
                </ns3:file>
                <ns3:file ID="PAGEXML_68" SEQ="68" MIMETYPE="application/xml" CREATED="2024-03-30T21:19:37.362+01:00" CHECKSUM="bb7fb40bf547b4ab2849c99e657e4ccc" CHECKSUMTYPE="MD5">
                    <ns3:FLocat LOCTYPE="OTHER" OTHERLOCTYPE="FILE" ns2:type="simple" ns2:href="page/1416473_0068.xml"/>
                </ns3:file>
                <ns3:file ID="PAGEXML_69" SEQ="69" MIMETYPE="application/xml" CREATED="2024-03-30T21:19:38.082+01:00" CHECKSUM="a2047ba95c9a2c1055da67c3b719e71b" CHECKSUMTYPE="MD5">
                    <ns3:FLocat LOCTYPE="OTHER" OTHERLOCTYPE="FILE" ns2:type="simple" ns2:href="page/1416473_0069.xml"/>
                </ns3:file>
                <ns3:file ID="PAGEXML_70" SEQ="70" MIMETYPE="application/xml" CREATED="2024-03-30T21:19:38.834+01:00" CHECKSUM="bc2ec7097946122aa3a2c791a4a4af3a" CHECKSUMTYPE="MD5">
                    <ns3:FLocat LOCTYPE="OTHER" OTHERLOCTYPE="FILE" ns2:type="simple" ns2:href="page/1416473_0070.xml"/>
                </ns3:file>
                <ns3:file ID="PAGEXML_71" SEQ="71" MIMETYPE="application/xml" CREATED="2024-03-30T21:19:39.670+01:00" CHECKSUM="c31f4e77dd97963e23eb153208e3bff5" CHECKSUMTYPE="MD5">
                    <ns3:FLocat LOCTYPE="OTHER" OTHERLOCTYPE="FILE" ns2:type="simple" ns2:href="page/1416473_0071.xml"/>
                </ns3:file>
            </ns3:fileGrp>
        </ns3:fileGrp>
    </ns3:fileSec>
    <ns3:structMap ID="TRP_STRUCTMAP" TYPE="MANUSCRIPT">
        <ns3:div ID="TRP_DOC_DIV" ADMID="MD_ORIG">
            <ns3:div ID="PAGE_1" ORDER="1" TYPE="SINGLE_PAGE">
                <ns3:fptr>
                    <ns3:area FILEID="IMG_1"/>
                </ns3:fptr>
                <ns3:fptr>
                    <ns3:area FILEID="PAGEXML_1"/>
                </ns3:fptr>
            </ns3:div>
            <ns3:div ID="PAGE_2" ORDER="2" TYPE="SINGLE_PAGE">
                <ns3:fptr>
                    <ns3:area FILEID="IMG_2"/>
                </ns3:fptr>
                <ns3:fptr>
                    <ns3:area FILEID="PAGEXML_2"/>
                </ns3:fptr>
            </ns3:div>
            <ns3:div ID="PAGE_3" ORDER="3" TYPE="SINGLE_PAGE">
                <ns3:fptr>
                    <ns3:area FILEID="IMG_3"/>
                </ns3:fptr>
                <ns3:fptr>
                    <ns3:area FILEID="PAGEXML_3"/>
                </ns3:fptr>
            </ns3:div>
            <ns3:div ID="PAGE_4" ORDER="4" TYPE="SINGLE_PAGE">
                <ns3:fptr>
                    <ns3:area FILEID="IMG_4"/>
                </ns3:fptr>
                <ns3:fptr>
                    <ns3:area FILEID="PAGEXML_4"/>
                </ns3:fptr>
            </ns3:div>
            <ns3:div ID="PAGE_5" ORDER="5" TYPE="SINGLE_PAGE">
                <ns3:fptr>
                    <ns3:area FILEID="IMG_5"/>
                </ns3:fptr>
                <ns3:fptr>
                    <ns3:area FILEID="PAGEXML_5"/>
                </ns3:fptr>
            </ns3:div>
            <ns3:div ID="PAGE_6" ORDER="6" TYPE="SINGLE_PAGE">
                <ns3:fptr>
                    <ns3:area FILEID="IMG_6"/>
                </ns3:fptr>
                <ns3:fptr>
                    <ns3:area FILEID="PAGEXML_6"/>
                </ns3:fptr>
            </ns3:div>
            <ns3:div ID="PAGE_7" ORDER="7" TYPE="SINGLE_PAGE">
                <ns3:fptr>
                    <ns3:area FILEID="IMG_7"/>
                </ns3:fptr>
                <ns3:fptr>
                    <ns3:area FILEID="PAGEXML_7"/>
                </ns3:fptr>
            </ns3:div>
            <ns3:div ID="PAGE_8" ORDER="8" TYPE="SINGLE_PAGE">
                <ns3:fptr>
                    <ns3:area FILEID="IMG_8"/>
                </ns3:fptr>
                <ns3:fptr>
                    <ns3:area FILEID="PAGEXML_8"/>
                </ns3:fptr>
            </ns3:div>
            <ns3:div ID="PAGE_9" ORDER="9" TYPE="SINGLE_PAGE">
                <ns3:fptr>
                    <ns3:area FILEID="IMG_9"/>
                </ns3:fptr>
                <ns3:fptr>
                    <ns3:area FILEID="PAGEXML_9"/>
                </ns3:fptr>
            </ns3:div>
            <ns3:div ID="PAGE_10" ORDER="10" TYPE="SINGLE_PAGE">
                <ns3:fptr>
                    <ns3:area FILEID="IMG_10"/>
                </ns3:fptr>
                <ns3:fptr>
                    <ns3:area FILEID="PAGEXML_10"/>
                </ns3:fptr>
            </ns3:div>
            <ns3:div ID="PAGE_11" ORDER="11" TYPE="SINGLE_PAGE">
                <ns3:fptr>
                    <ns3:area FILEID="IMG_11"/>
                </ns3:fptr>
                <ns3:fptr>
                    <ns3:area FILEID="PAGEXML_11"/>
                </ns3:fptr>
            </ns3:div>
            <ns3:div ID="PAGE_12" ORDER="12" TYPE="SINGLE_PAGE">
                <ns3:fptr>
                    <ns3:area FILEID="IMG_12"/>
                </ns3:fptr>
                <ns3:fptr>
                    <ns3:area FILEID="PAGEXML_12"/>
                </ns3:fptr>
            </ns3:div>
            <ns3:div ID="PAGE_13" ORDER="13" TYPE="SINGLE_PAGE">
                <ns3:fptr>
                    <ns3:area FILEID="IMG_13"/>
                </ns3:fptr>
                <ns3:fptr>
                    <ns3:area FILEID="PAGEXML_13"/>
                </ns3:fptr>
            </ns3:div>
            <ns3:div ID="PAGE_14" ORDER="14" TYPE="SINGLE_PAGE">
                <ns3:fptr>
                    <ns3:area FILEID="IMG_14"/>
                </ns3:fptr>
                <ns3:fptr>
                    <ns3:area FILEID="PAGEXML_14"/>
                </ns3:fptr>
            </ns3:div>
            <ns3:div ID="PAGE_15" ORDER="15" TYPE="SINGLE_PAGE">
                <ns3:fptr>
                    <ns3:area FILEID="IMG_15"/>
                </ns3:fptr>
                <ns3:fptr>
                    <ns3:area FILEID="PAGEXML_15"/>
                </ns3:fptr>
            </ns3:div>
            <ns3:div ID="PAGE_16" ORDER="16" TYPE="SINGLE_PAGE">
                <ns3:fptr>
                    <ns3:area FILEID="IMG_16"/>
                </ns3:fptr>
                <ns3:fptr>
                    <ns3:area FILEID="PAGEXML_16"/>
                </ns3:fptr>
            </ns3:div>
            <ns3:div ID="PAGE_17" ORDER="17" TYPE="SINGLE_PAGE">
                <ns3:fptr>
                    <ns3:area FILEID="IMG_17"/>
                </ns3:fptr>
                <ns3:fptr>
                    <ns3:area FILEID="PAGEXML_17"/>
                </ns3:fptr>
            </ns3:div>
            <ns3:div ID="PAGE_18" ORDER="18" TYPE="SINGLE_PAGE">
                <ns3:fptr>
                    <ns3:area FILEID="IMG_18"/>
                </ns3:fptr>
                <ns3:fptr>
                    <ns3:area FILEID="PAGEXML_18"/>
                </ns3:fptr>
            </ns3:div>
            <ns3:div ID="PAGE_19" ORDER="19" TYPE="SINGLE_PAGE">
                <ns3:fptr>
                    <ns3:area FILEID="IMG_19"/>
                </ns3:fptr>
                <ns3:fptr>
                    <ns3:area FILEID="PAGEXML_19"/>
                </ns3:fptr>
            </ns3:div>
            <ns3:div ID="PAGE_20" ORDER="20" TYPE="SINGLE_PAGE">
                <ns3:fptr>
                    <ns3:area FILEID="IMG_20"/>
                </ns3:fptr>
                <ns3:fptr>
                    <ns3:area FILEID="PAGEXML_20"/>
                </ns3:fptr>
            </ns3:div>
            <ns3:div ID="PAGE_21" ORDER="21" TYPE="SINGLE_PAGE">
                <ns3:fptr>
                    <ns3:area FILEID="IMG_21"/>
                </ns3:fptr>
                <ns3:fptr>
                    <ns3:area FILEID="PAGEXML_21"/>
                </ns3:fptr>
            </ns3:div>
            <ns3:div ID="PAGE_22" ORDER="22" TYPE="SINGLE_PAGE">
                <ns3:fptr>
                    <ns3:area FILEID="IMG_22"/>
                </ns3:fptr>
                <ns3:fptr>
                    <ns3:area FILEID="PAGEXML_22"/>
                </ns3:fptr>
            </ns3:div>
            <ns3:div ID="PAGE_23" ORDER="23" TYPE="SINGLE_PAGE">
                <ns3:fptr>
                    <ns3:area FILEID="IMG_23"/>
                </ns3:fptr>
                <ns3:fptr>
                    <ns3:area FILEID="PAGEXML_23"/>
                </ns3:fptr>
            </ns3:div>
            <ns3:div ID="PAGE_24" ORDER="24" TYPE="SINGLE_PAGE">
                <ns3:fptr>
                    <ns3:area FILEID="IMG_24"/>
                </ns3:fptr>
                <ns3:fptr>
                    <ns3:area FILEID="PAGEXML_24"/>
                </ns3:fptr>
            </ns3:div>
            <ns3:div ID="PAGE_25" ORDER="25" TYPE="SINGLE_PAGE">
                <ns3:fptr>
                    <ns3:area FILEID="IMG_25"/>
                </ns3:fptr>
                <ns3:fptr>
                    <ns3:area FILEID="PAGEXML_25"/>
                </ns3:fptr>
            </ns3:div>
            <ns3:div ID="PAGE_26" ORDER="26" TYPE="SINGLE_PAGE">
                <ns3:fptr>
                    <ns3:area FILEID="IMG_26"/>
                </ns3:fptr>
                <ns3:fptr>
                    <ns3:area FILEID="PAGEXML_26"/>
                </ns3:fptr>
            </ns3:div>
            <ns3:div ID="PAGE_27" ORDER="27" TYPE="SINGLE_PAGE">
                <ns3:fptr>
                    <ns3:area FILEID="IMG_27"/>
                </ns3:fptr>
                <ns3:fptr>
                    <ns3:area FILEID="PAGEXML_27"/>
                </ns3:fptr>
            </ns3:div>
            <ns3:div ID="PAGE_28" ORDER="28" TYPE="SINGLE_PAGE">
                <ns3:fptr>
                    <ns3:area FILEID="IMG_28"/>
                </ns3:fptr>
                <ns3:fptr>
                    <ns3:area FILEID="PAGEXML_28"/>
                </ns3:fptr>
            </ns3:div>
            <ns3:div ID="PAGE_29" ORDER="29" TYPE="SINGLE_PAGE">
                <ns3:fptr>
                    <ns3:area FILEID="IMG_29"/>
                </ns3:fptr>
                <ns3:fptr>
                    <ns3:area FILEID="PAGEXML_29"/>
                </ns3:fptr>
            </ns3:div>
            <ns3:div ID="PAGE_30" ORDER="30" TYPE="SINGLE_PAGE">
                <ns3:fptr>
                    <ns3:area FILEID="IMG_30"/>
                </ns3:fptr>
                <ns3:fptr>
                    <ns3:area FILEID="PAGEXML_30"/>
                </ns3:fptr>
            </ns3:div>
            <ns3:div ID="PAGE_31" ORDER="31" TYPE="SINGLE_PAGE">
                <ns3:fptr>
                    <ns3:area FILEID="IMG_31"/>
                </ns3:fptr>
                <ns3:fptr>
                    <ns3:area FILEID="PAGEXML_31"/>
                </ns3:fptr>
            </ns3:div>
            <ns3:div ID="PAGE_32" ORDER="32" TYPE="SINGLE_PAGE">
                <ns3:fptr>
                    <ns3:area FILEID="IMG_32"/>
                </ns3:fptr>
                <ns3:fptr>
                    <ns3:area FILEID="PAGEXML_32"/>
                </ns3:fptr>
            </ns3:div>
            <ns3:div ID="PAGE_33" ORDER="33" TYPE="SINGLE_PAGE">
                <ns3:fptr>
                    <ns3:area FILEID="IMG_33"/>
                </ns3:fptr>
                <ns3:fptr>
                    <ns3:area FILEID="PAGEXML_33"/>
                </ns3:fptr>
            </ns3:div>
            <ns3:div ID="PAGE_34" ORDER="34" TYPE="SINGLE_PAGE">
                <ns3:fptr>
                    <ns3:area FILEID="IMG_34"/>
                </ns3:fptr>
                <ns3:fptr>
                    <ns3:area FILEID="PAGEXML_34"/>
                </ns3:fptr>
            </ns3:div>
            <ns3:div ID="PAGE_35" ORDER="35" TYPE="SINGLE_PAGE">
                <ns3:fptr>
                    <ns3:area FILEID="IMG_35"/>
                </ns3:fptr>
                <ns3:fptr>
                    <ns3:area FILEID="PAGEXML_35"/>
                </ns3:fptr>
            </ns3:div>
            <ns3:div ID="PAGE_36" ORDER="36" TYPE="SINGLE_PAGE">
                <ns3:fptr>
                    <ns3:area FILEID="IMG_36"/>
                </ns3:fptr>
                <ns3:fptr>
                    <ns3:area FILEID="PAGEXML_36"/>
                </ns3:fptr>
            </ns3:div>
            <ns3:div ID="PAGE_37" ORDER="37" TYPE="SINGLE_PAGE">
                <ns3:fptr>
                    <ns3:area FILEID="IMG_37"/>
                </ns3:fptr>
                <ns3:fptr>
                    <ns3:area FILEID="PAGEXML_37"/>
                </ns3:fptr>
            </ns3:div>
            <ns3:div ID="PAGE_38" ORDER="38" TYPE="SINGLE_PAGE">
                <ns3:fptr>
                    <ns3:area FILEID="IMG_38"/>
                </ns3:fptr>
                <ns3:fptr>
                    <ns3:area FILEID="PAGEXML_38"/>
                </ns3:fptr>
            </ns3:div>
            <ns3:div ID="PAGE_39" ORDER="39" TYPE="SINGLE_PAGE">
                <ns3:fptr>
                    <ns3:area FILEID="IMG_39"/>
                </ns3:fptr>
                <ns3:fptr>
                    <ns3:area FILEID="PAGEXML_39"/>
                </ns3:fptr>
            </ns3:div>
            <ns3:div ID="PAGE_40" ORDER="40" TYPE="SINGLE_PAGE">
                <ns3:fptr>
                    <ns3:area FILEID="IMG_40"/>
                </ns3:fptr>
                <ns3:fptr>
                    <ns3:area FILEID="PAGEXML_40"/>
                </ns3:fptr>
            </ns3:div>
            <ns3:div ID="PAGE_41" ORDER="41" TYPE="SINGLE_PAGE">
                <ns3:fptr>
                    <ns3:area FILEID="IMG_41"/>
                </ns3:fptr>
                <ns3:fptr>
                    <ns3:area FILEID="PAGEXML_41"/>
                </ns3:fptr>
            </ns3:div>
            <ns3:div ID="PAGE_42" ORDER="42" TYPE="SINGLE_PAGE">
                <ns3:fptr>
                    <ns3:area FILEID="IMG_42"/>
                </ns3:fptr>
                <ns3:fptr>
                    <ns3:area FILEID="PAGEXML_42"/>
                </ns3:fptr>
            </ns3:div>
            <ns3:div ID="PAGE_43" ORDER="43" TYPE="SINGLE_PAGE">
                <ns3:fptr>
                    <ns3:area FILEID="IMG_43"/>
                </ns3:fptr>
                <ns3:fptr>
                    <ns3:area FILEID="PAGEXML_43"/>
                </ns3:fptr>
            </ns3:div>
            <ns3:div ID="PAGE_44" ORDER="44" TYPE="SINGLE_PAGE">
                <ns3:fptr>
                    <ns3:area FILEID="IMG_44"/>
                </ns3:fptr>
                <ns3:fptr>
                    <ns3:area FILEID="PAGEXML_44"/>
                </ns3:fptr>
            </ns3:div>
            <ns3:div ID="PAGE_45" ORDER="45" TYPE="SINGLE_PAGE">
                <ns3:fptr>
                    <ns3:area FILEID="IMG_45"/>
                </ns3:fptr>
                <ns3:fptr>
                    <ns3:area FILEID="PAGEXML_45"/>
                </ns3:fptr>
            </ns3:div>
            <ns3:div ID="PAGE_46" ORDER="46" TYPE="SINGLE_PAGE">
                <ns3:fptr>
                    <ns3:area FILEID="IMG_46"/>
                </ns3:fptr>
                <ns3:fptr>
                    <ns3:area FILEID="PAGEXML_46"/>
                </ns3:fptr>
            </ns3:div>
            <ns3:div ID="PAGE_47" ORDER="47" TYPE="SINGLE_PAGE">
                <ns3:fptr>
                    <ns3:area FILEID="IMG_47"/>
                </ns3:fptr>
                <ns3:fptr>
                    <ns3:area FILEID="PAGEXML_47"/>
                </ns3:fptr>
            </ns3:div>
            <ns3:div ID="PAGE_48" ORDER="48" TYPE="SINGLE_PAGE">
                <ns3:fptr>
                    <ns3:area FILEID="IMG_48"/>
                </ns3:fptr>
                <ns3:fptr>
                    <ns3:area FILEID="PAGEXML_48"/>
                </ns3:fptr>
            </ns3:div>
            <ns3:div ID="PAGE_49" ORDER="49" TYPE="SINGLE_PAGE">
                <ns3:fptr>
                    <ns3:area FILEID="IMG_49"/>
                </ns3:fptr>
                <ns3:fptr>
                    <ns3:area FILEID="PAGEXML_49"/>
                </ns3:fptr>
            </ns3:div>
            <ns3:div ID="PAGE_50" ORDER="50" TYPE="SINGLE_PAGE">
                <ns3:fptr>
                    <ns3:area FILEID="IMG_50"/>
                </ns3:fptr>
                <ns3:fptr>
                    <ns3:area FILEID="PAGEXML_50"/>
                </ns3:fptr>
            </ns3:div>
            <ns3:div ID="PAGE_51" ORDER="51" TYPE="SINGLE_PAGE">
                <ns3:fptr>
                    <ns3:area FILEID="IMG_51"/>
                </ns3:fptr>
                <ns3:fptr>
                    <ns3:area FILEID="PAGEXML_51"/>
                </ns3:fptr>
            </ns3:div>
            <ns3:div ID="PAGE_52" ORDER="52" TYPE="SINGLE_PAGE">
                <ns3:fptr>
                    <ns3:area FILEID="IMG_52"/>
                </ns3:fptr>
                <ns3:fptr>
                    <ns3:area FILEID="PAGEXML_52"/>
                </ns3:fptr>
            </ns3:div>
            <ns3:div ID="PAGE_53" ORDER="53" TYPE="SINGLE_PAGE">
                <ns3:fptr>
                    <ns3:area FILEID="IMG_53"/>
                </ns3:fptr>
                <ns3:fptr>
                    <ns3:area FILEID="PAGEXML_53"/>
                </ns3:fptr>
            </ns3:div>
            <ns3:div ID="PAGE_54" ORDER="54" TYPE="SINGLE_PAGE">
                <ns3:fptr>
                    <ns3:area FILEID="IMG_54"/>
                </ns3:fptr>
                <ns3:fptr>
                    <ns3:area FILEID="PAGEXML_54"/>
                </ns3:fptr>
            </ns3:div>
            <ns3:div ID="PAGE_55" ORDER="55" TYPE="SINGLE_PAGE">
                <ns3:fptr>
                    <ns3:area FILEID="IMG_55"/>
                </ns3:fptr>
                <ns3:fptr>
                    <ns3:area FILEID="PAGEXML_55"/>
                </ns3:fptr>
            </ns3:div>
            <ns3:div ID="PAGE_56" ORDER="56" TYPE="SINGLE_PAGE">
                <ns3:fptr>
                    <ns3:area FILEID="IMG_56"/>
                </ns3:fptr>
                <ns3:fptr>
                    <ns3:area FILEID="PAGEXML_56"/>
                </ns3:fptr>
            </ns3:div>
            <ns3:div ID="PAGE_57" ORDER="57" TYPE="SINGLE_PAGE">
                <ns3:fptr>
                    <ns3:area FILEID="IMG_57"/>
                </ns3:fptr>
                <ns3:fptr>
                    <ns3:area FILEID="PAGEXML_57"/>
                </ns3:fptr>
            </ns3:div>
            <ns3:div ID="PAGE_58" ORDER="58" TYPE="SINGLE_PAGE">
                <ns3:fptr>
                    <ns3:area FILEID="IMG_58"/>
                </ns3:fptr>
                <ns3:fptr>
                    <ns3:area FILEID="PAGEXML_58"/>
                </ns3:fptr>
            </ns3:div>
            <ns3:div ID="PAGE_59" ORDER="59" TYPE="SINGLE_PAGE">
                <ns3:fptr>
                    <ns3:area FILEID="IMG_59"/>
                </ns3:fptr>
                <ns3:fptr>
                    <ns3:area FILEID="PAGEXML_59"/>
                </ns3:fptr>
            </ns3:div>
            <ns3:div ID="PAGE_60" ORDER="60" TYPE="SINGLE_PAGE">
                <ns3:fptr>
                    <ns3:area FILEID="IMG_60"/>
                </ns3:fptr>
                <ns3:fptr>
                    <ns3:area FILEID="PAGEXML_60"/>
                </ns3:fptr>
            </ns3:div>
            <ns3:div ID="PAGE_61" ORDER="61" TYPE="SINGLE_PAGE">
                <ns3:fptr>
                    <ns3:area FILEID="IMG_61"/>
                </ns3:fptr>
                <ns3:fptr>
                    <ns3:area FILEID="PAGEXML_61"/>
                </ns3:fptr>
            </ns3:div>
            <ns3:div ID="PAGE_62" ORDER="62" TYPE="SINGLE_PAGE">
                <ns3:fptr>
                    <ns3:area FILEID="IMG_62"/>
                </ns3:fptr>
                <ns3:fptr>
                    <ns3:area FILEID="PAGEXML_62"/>
                </ns3:fptr>
            </ns3:div>
            <ns3:div ID="PAGE_63" ORDER="63" TYPE="SINGLE_PAGE">
                <ns3:fptr>
                    <ns3:area FILEID="IMG_63"/>
                </ns3:fptr>
                <ns3:fptr>
                    <ns3:area FILEID="PAGEXML_63"/>
                </ns3:fptr>
            </ns3:div>
            <ns3:div ID="PAGE_64" ORDER="64" TYPE="SINGLE_PAGE">
                <ns3:fptr>
                    <ns3:area FILEID="IMG_64"/>
                </ns3:fptr>
                <ns3:fptr>
                    <ns3:area FILEID="PAGEXML_64"/>
                </ns3:fptr>
            </ns3:div>
            <ns3:div ID="PAGE_65" ORDER="65" TYPE="SINGLE_PAGE">
                <ns3:fptr>
                    <ns3:area FILEID="IMG_65"/>
                </ns3:fptr>
                <ns3:fptr>
                    <ns3:area FILEID="PAGEXML_65"/>
                </ns3:fptr>
            </ns3:div>
            <ns3:div ID="PAGE_66" ORDER="66" TYPE="SINGLE_PAGE">
                <ns3:fptr>
                    <ns3:area FILEID="IMG_66"/>
                </ns3:fptr>
                <ns3:fptr>
                    <ns3:area FILEID="PAGEXML_66"/>
                </ns3:fptr>
            </ns3:div>
            <ns3:div ID="PAGE_67" ORDER="67" TYPE="SINGLE_PAGE">
                <ns3:fptr>
                    <ns3:area FILEID="IMG_67"/>
                </ns3:fptr>
                <ns3:fptr>
                    <ns3:area FILEID="PAGEXML_67"/>
                </ns3:fptr>
            </ns3:div>
            <ns3:div ID="PAGE_68" ORDER="68" TYPE="SINGLE_PAGE">
                <ns3:fptr>
                    <ns3:area FILEID="IMG_68"/>
                </ns3:fptr>
                <ns3:fptr>
                    <ns3:area FILEID="PAGEXML_68"/>
                </ns3:fptr>
            </ns3:div>
            <ns3:div ID="PAGE_69" ORDER="69" TYPE="SINGLE_PAGE">
                <ns3:fptr>
                    <ns3:area FILEID="IMG_69"/>
                </ns3:fptr>
                <ns3:fptr>
                    <ns3:area FILEID="PAGEXML_69"/>
                </ns3:fptr>
            </ns3:div>
            <ns3:div ID="PAGE_70" ORDER="70" TYPE="SINGLE_PAGE">
                <ns3:fptr>
                    <ns3:area FILEID="IMG_70"/>
                </ns3:fptr>
                <ns3:fptr>
                    <ns3:area FILEID="PAGEXML_70"/>
                </ns3:fptr>
            </ns3:div>
            <ns3:div ID="PAGE_71" ORDER="71" TYPE="SINGLE_PAGE">
                <ns3:fptr>
                    <ns3:area FILEID="IMG_71"/>
                </ns3:fptr>
                <ns3:fptr>
                    <ns3:area FILEID="PAGEXML_71"/>
                </ns3:fptr>
            </ns3:div>
        </ns3:div>
    </ns3:structMap>
</ns3:mets>
